Workbook
Name \A: #REF!
Name \A: '[1]1.1 INDIC ACC'!#REF!
Name \A: #REF!
Name \A: #REF!
Name \A: #REF!
Name \A: #REF!
Name \A: #REF!
Name \A: #REF!
Name \A: '[1]1.1 INDIC ACC'!#REF!
Name \A: #REF!
Name \A: #REF!
Name \A: '[1]1.1 INDIC ACC'!#REF!
Name \A: #REF!
Name \B: #REF!
Name \B: #REF!
Name \B: #REF!
Name \B: #REF!
Name \B: #REF!
Name \C: #REF!
Name \C: #REF!
Name \C: #REF!
Name \C: #REF!
Name \C: #REF!
Name \D: #REF!
Name \D: #REF!
Name \D: #REF!
Name \D: #REF!
Name \D: #REF!
Name \E: #REF!
Name \E: #REF!
Name \E: #REF!
Name \E: #REF!
Name \E: #REF!
Name \F: #REF!
Name \F: #REF!
Name \F: #REF!
Name \F: #REF!
Name \F: #REF!
Name \G: #REF!
Name \G: #REF!
Name \G: #REF!
Name \G: #REF!
Name \G: #REF!
Name \H: #REF!
Name \H: #REF!
Name \H: #REF!
Name \H: #REF!
Name \H: #REF!
Name \I: #REF!
Name \I: #REF!
Name \I: #REF!
Name \I: #REF!
Name \I: #REF!
Name \J: #REF!
Name \J: #REF!
Name \J: #REF!
Name \J: #REF!
Name \J: #REF!
Name \K: #REF!
Name \K: #REF!

Sheet IMF Tools TOC
A1: Macronia_MASTER_10132015.xlsx
B5: Tab Name | C5: Tab Description | D5: Hidden
B6: Workbook_Flowchart
B7: Solutions
B8: SEFI table
B9: GDP table
B10: GDP_Nominal
B11: LRY
B12: GDP_Real
B13: GDP_Deflator
B14: BOP
B15: IIP
B16: EX_Debt
B17: EX_Stock_Ind
... B53: Fiscal&Monetary (through 2014)

Sheet Soluciones
D1: USE ESTA HOJA PARA LLEVAR UN REGISTRO DE LAS RESPUESTAS QUE INGRESARÁ EN EL PORTAL DEL CURSO EDX.ORG | F1: RESPUESTA | I1: at the beginning of module 3 real sector, start with the initial assumptions listed below
D2: HOJA DE SOLUCIONES DE MACRONIA (Las soluciones numéricas aparecerán en la columna E tan pronto complete sus tareas) | E2: Proyección actual | F2: supuestos de ronda inicial/solución | I2: table (real and nominal) then go through module external sector without doing GDP convergence yet.
I3: file name | J3: main assumptions | K3: tab/cell
B4: Módulo 03 | D4: SECTOR REAL, INFLACIÓN Y DEFLACTOR DEL PIB | E4: 2014 | F4: 2014 | I4: Macronia_baseline phase 1
B5: =B4 -> Módulo 03 | D5: crecimiento del PIB real | E5: ='Cuadro PIB'!J28 -> 4.4517021 | F5: 4.63 | I5: real GDP growth | J5: =E5 -> 4.4517021 | K5: ='Cuadro PIB'!J28
D6: tasa de interés nominal de política monetaria (igual a la del año previo) fijada en la regla de Taylor | E6: ='Regla de Taylor '!E9 -> 9.6716905 | F6: 0.088660415 | H6: exog | I6: nominal policy interest rate | J6: =F6 -> 0.088660415 | K6: ='Taylor Rule '!D8
D7: tasa de interés real de política monetaria (igual a la del año previo) | E7: ='TC nominal'!I40 -> 0.023160213 | F7: 0.027301901 | H7: exog | I7: real policy interest rate | J7: =F7 -> 0.027301901 | K7: ='TC Nominal'!I40
D8: tasa de interés nominal interbancaria (igual a la del año previo) en función de inversión | E8: ='Inversión privada real'!I16 -> 14.671691 | F8: 12.2 | H8: endo | I8: Inflation | J8: =$F$21 -> 7.4814516 | K8: =Inflation!O34
D9: tasa de interés nominal interbancaria (igual a la del año previo) en tasa de interés de sector gob. | E9: =Gob_Stock_Ind!L20 -> 14.671691 | F9: 12.2 | I9: nominal interbank interest rate (set equal to previous year) in Investment function | J9: =F8 -> 12.2 | K9: ='Real private investment'I15
D10: tasa de interés nominal interbancaria (igual a la del año previo) en función de demanda de dinero | E10: =DD!H33 -> 14.671691 | F10: 12.2 | I10: fiscal stimulus (pct of potential output 2013) | J10: 2 | K10: ='Cuadro PIB'!K36
D11: TC nominal (promedio) | E11: ='TC nominal'!I13 -> 563.14785 | F11: 561.46514 | I11: RER gap or Implicit UIP-based RER change (in real terms) (+ depreciation) | J11: ='TC nominal'!I34 -> -0.0031602132 | K11: ='TC Nominal'!I34
D12: índice del tipo de cambio real | E12: ='TC nominal'!H22 -> 99.26981 | F12: 99.26981
B13: =B5 -> Módulo 03 | C13: 3.05 | D13: Pronosticar producto potencial | E13: ='PIB real y brecha del producto'!F14 -> 13178.694 | F13: 13178.694 | I13: memo item:
B14: =B13 -> Módulo 03 | C14: 3.06 | D14: Pronosticar PIB real | E14: ='PIB real y brecha del producto'!G30 -> 13343.319 | F14: 13366.096 | I14: Nominal GDP | J14: ='Cuadro PIB'!L26 -> 26705.763 | K14: ='Cuadro PIB'!L26
B15: =B14 -> Módulo 03 | C15: 3.07 | D15: Pronosticar BRECHA DEL PRODUCTO en porcentaje del producto potencial (porcentaje) | E15: ='PIB real y brecha del producto'!G32 -> 1.2491751 | F15: 1.4220063
B16: =B15 -> Módulo 03 | C16: 3.13 | D16: PRONOSTICAR NIVEL DE CONSUMO REAL (usando proporción del PIB según método simplista) | E16: ='Consumo real privado'!H28 -> 9701.4741 | F16: 9718.0344
B17: =B16 -> Módulo 03 | C17: 3.15 | D17: PRONOSTICAR NIVEL DE DE CONSUMO REAL (usando modelo de corrección de errores del método de regresión y parámetro a corto plazo) | E17: ='Consumo real privado'!H32 -> 9556.7582 | F17: 9567.5224
B18: =B17 -> Módulo 03 | C18: 3.17 | D18: PRONOSTICAR NIVEL DE INVERSIÓN PRIVADA REAL (usando proporción del PIB según método simplista) | E18: ='Inversión privada real'!H30 -> 2440.0991 | F18: 2444.2643
B19: =B18 -> Módulo 03 | C19: 3.2 | D19: PRONOSTICAR NIVEL DE INVERSIÓN PRIVADA REAL (usando método de regresión) y basado en supuesto inicial de tasa de interés | E19: ='Inversión privada real'!H32 -> 2453.5587 | F19: 2538.6693
B20: =B19 -> Módulo 03 | D20: Supuesto de tasa de interés real | E20: ='Inversión privada real'!K16 -> 7.3160213 | F20: 4.7185484
B21: =B20 -> Módulo 03 | C21: 3.25 | D21: PRONOSTICAR INFLACIÓN (con curva de Phillips) | E21: =Inflación!O34 -> 7.3556692 | F21: 7.4814516
B22: =B21 -> Módulo 03 | C22: 3.26 | D22: Usar la ecuación de Phillips para pronosticar la inflación con brecha del producto=2% y brecha del TCR=2,65% | E22: 9.21 | F22: 9.212
B23: =B22 -> Módulo 03 | D23: Supuesto de brecha del TCR (basado en supuesto inicial de tasa de interés real) | E23: =Inflación!K29 -> -0.31525678 | F23: -0.73019014
B24: =B23 -> Módulo 03 | D24: Supuesto: fijar crecimiento inicial de deflactor del PIB igual a la inflación de base | E24: ='Cuadro PIB'!I28 -> 8.1255598 | F24: 7.4814516
B25: =B24 -> Módulo 03 | D25: Dado el deflactor del PIB en 2013 | E25: =Deflactor_PIB!K35 -> 185.1027 | F25: 185.1027
B26: =B25 -> Módulo 03 | C26: 3.28 | D26: Pronosticar PIB nominal inicial (usando fórmula) | E26: ='Cuadro PIB'!L28 -> 26705.763 | F26: 26591.991
B27: =B26 -> Módulo 03 | C27: 3.29 | D27: PIB real | E27: ='PIB real y brecha del producto'!G22 -> 4.4517021 | F27: 4.63
B28: =B27 -> Módulo 03 | D28: Brecha del producto | E28: ='PIB real y brecha del producto'!G32 -> 1.2491751 | F28: 1.4220063
B29: =B28 -> Módulo 03 | D29: Inflación media | E29: =Inflación!O31 -> 7.3556692 | F29: 7.4814516
B31: Módulo 04 | D31: SECTOR EXTERNO | F31: SEMANA 3
B32: Módulo 04 | C32: 4.9 | D32: Pronosticar nivel TCR para 2014 | E32: ='TC nominal'!I22 -> 99.683979 | F32: 99.26981
B33: Módulo 04 | C33: 4.1 | D33: Pronosticar nivel del TC nominal Macronia/USD | E33: ='TC nominal'!I13 -> 563.14785 | F33: 561.46514
B34: Módulo 04 | C34: 4.11 | D34: Pronosticar de variación de TCN para 2014 | E34: ='TC nominal'!I16 -> 6.2104172 | F34: 5.8930557
B35: Módulo 04 | C35: 4.14 | D35: PRONOSTICAR VARIACIÓN DE PRECIO RELATIVO DE IMPORTACIONES | E35: ='Importaciones reales de bienes'!F22 -> 0.41721528 | F35: 0
B36: Módulo 04 | C36: 4.15 | D36: PRONOSTICAR VARIACIÓN DE VOLUMEN DE IMPORTACIONES REALES | E36: ='Importaciones reales de bienes'!O24 -> 5.3384819 | F36: 5.8235001
B37: Módulo 04 | C37: 4.16 | D37: PRONOSTICAR VARIACIÓN DE PRECIO RELATIVO DE EXPORTACIONES | E37: ='Exportaciones reales de bienes'!F23 -> 0.41721528 | F37: 0
B38: Módulo 04 | C38: 4.17 | D38: PRONOSTICAR VARIACIÓN DE VOLUMEN DE EXPORTACIONES REALES | E38: ='Exportaciones reales de bienes'!O25 -> 4.2607596 | F38: 4
B39: Módulo 04 | C39: 4.18 | D39: Pronosticar exportaciones nominales en miles de millones de USD | E39: ='Import. y export. nominales'!M8/1000 -> 12.800176 | F39: 12.768163
B40: Módulo 04 | C40: 4.18 | D40: Pronosticar importaciones nominales en miles de millones de USD | E40: ='Import. y export. nominales'!M10/1000 -> 19.555251 | F40: 19.645291
B41: Módulo 04 | C41: 4.19 | D41: SERVICIOS DE CRÉDITO | E41: =Servicios!I8 -> 6129.8593 | F41: 6114.5284
B42: Módulo 04 | C42: 4.19 | D42: SERVICIOS DE DÉBITO | E42: =Servicios!I10 -> 2184.671 | F42: 2194.73
B43: Módulo 04 | C43: 4.2 | D43: PAGOS DE INTERESES SOBRE DEUDA EXT. | E43: ='Ingreso primario'!I18 -> 295.30314 | F43: 295.30314
B44: Módulo 04 | C44: 4.21 | D44: SALDO DE INGRESO SECUNDARIO | E44: ='Ingreso secundario'!J6 -> 352.57201 | F44: 352.57201
B45: Módulo 04 | C45: 4.23 | D45: CUENTA FINANCIERA Inversiones directas en millones de USD | E45: =BP!L22 -> -2111.1857 | F45: -2130.2468
B46: Módulo 04 | C46: 4.24 | D46: pronosticar Otra inversión de cartera (neta) | E46: =BP!L30 -> 259.89048 | F46: 262.23694
B47: Módulo 04 | C47: 4.25 | D47: cuenta externa SEFI - cuenta corriente | E47: =BP!L47 -> -7.0207629 | F47: -7.266076
B48: Módulo 04 | C48: 4.25 | D48: cuenta externa SEFI - cuenta financiera | E48: =BP!L49 -> -6.486106 | F48: -6.479391
B49: Módulo 04 | C49: 4.25 | D49: cuenta externa SEFI - variación de reservas | E49: =BP!L50 -> -0.51567847 | F49: -0.76787648
B50: Módulo 04 | C50: 4.26 | D50: activos de reserva en meses de importaciones | E50: =BP!L52 -> 2.5029508 | F50: 2.4239595
B52: Módulo 05 | D52: SECTOR GOBIERNO | F52: SEMANA 4
B53: Módulo 05 | D53: ingresar el estímulo fiscal en el gobierno (en porcentaje del producto potencial y con respecto a 2013) | E53: ='Cuadro PIB'!K36 -> 0.02 | F53: 0.02
B54: Módulo 05 | D54: Ingresos
B55: Módulo 05 | C55: 5.16 | D55: pronosticar ingresos por renta usando TEI | E55: =Gob_GTR_Proy!J50 -> 1110.6037 | F55: 1130.8978
B56: Módulo 05 | C56: 5.16 | D56: pronosticar ingresos por bienes y servicios usando TEI | E56: =Gob_GTR_Proy!J51 -> 763.93218 | F56: 774.72262
B57: Módulo 05 | C57: 5.16 | D57: pronosticar ingresos por impuestos internacionales usando TEI | E57: =Gob_GTR_Proy!J52 -> 1087.5547 | F57: 1107.409
B58: Módulo 05 | C58: 5.16 | D58: pronosticar otros impuestos usando TEI (usar PIB nominal como variable representativa de la base tributaria) | E58: =Gob_GTR_Proy!J53 -> 808.75684 | F58: 823.53528
B59: Módulo 05 | C59: 5.16 | D59: ¿cuál es el ingreso tributario total en 2014 según TIE (sumar los componentes individuales)? | E59: =Gob_GTR_Proy!J49 -> 3770.8474 | F59: 3836.5647
B60: Módulo 05 | C60: 5.17 | D60: pronosticar ingresos por renta usando capacidad de reacción | E60: =Gob_GTR_Proy!J57 -> 1094.9239 | F60: 1112.7171
B61: Módulo 05 | C61: 5.18 | D61: pronosticar ingresos por bienes y servicios usando capacidad de reacción | E61: =Gob_GTR_Proy!J58 -> 746.7644 | F61: 755.52008
B62: Módulo 05 | C62: 5.19 | D62: pronosticar ingresos por impuestos internacionales usando capacidad de reacción | E62: =Gob_GTR_Proy!J59 -> 1108.0894 | F62: 1131.0835
B63: Módulo 05 | C63: 5.2 | D63: pronosticar otros impuestos usando capacidad de reacción (usar PIB nominal como variable representativa de la base tributaria) | E63: =Gob_GTR_Proy!J60 -> 798.02819 | F63: 811.09544
B64: Módulo 05 | C64: 5.21 | D64: ¿cuál es el ingreso tributario total en 2014 según la capacidad de reacción (sumar los componentes individuales)? | E64: =Gob_GTR_Proy!J56 -> 3747.8059 | F64: 3810.4161
B65: Módulo 05 | C65: 5.22 | D65: pronosticar ingreso totales (sumar: impuestos, contribuciones sociales, donaciones y otros ingresos) | E65: =Gob_EOG!L5 -> 4081.623 | F65: 4150
B66: Módulo 05 | D66: Gastos
B67: Módulo 05 | C67: 5.26 | D67: pronosticar remuneración de empleados (conforma crecimiento de PIB nominal) | E67: ='Hoja-Gob_Exp_Proy.'!I11 -> 2590.2094 | F67: 2615.3627
B68: Módulo 05 | C68: 5.27 | D68: pronosticar uso de bienes y servicios | E68: ='Hoja-Gob_Exp_Proy.'!I12 -> 204.35724 | F68: 206.34173
B69: Módulo 05 | C69: 5.27 | D69: pronosticar consumo de capital fijo | E69: ='Hoja-Gob_Exp_Proy.'!I13 -> 17.156154 | F69: 17.322755
B70: Módulo 05 | C70: 5.27 | D70: pronosticar subsidios | E70: ='Hoja-Gob_Exp_Proy.'!I28 -> 2782.6192 | F70: 2809.6409
B71: Módulo 05 | C71: 5.27 | D71: pronosticar donaciones | E71: ='Hoja-Gob_Exp_Proy.'!I29 -> 21.884533 | F71: 22.097051
B72: Módulo 05 | C72: 5.27 | D72: pronosticar prestaciones sociales | E72: ='Hoja-Gob_Exp_Proy.'!I30 -> 381.76402 | F72: 385.47129
B73: Módulo 05 | C73: 5.28 | D73: pronosticar «Adquisición de activos no financieros» | E73: ='Hoja-Gob_Exp_Proy.'!I35 -> 49.885507 | F73: 53.084502
B74: Módulo 05 | C74: 5.29 | D74: pronosticar adquisición neta de activos no financieros | E74: ='Hoja-Gob_Exp_Proy.'!I34 -> 32.729354 | F74: 35.761746
B75: Módulo 05 | C75: 5.3 | D75: pronosticar pagos de intereses por deuda externa (en miles de millones de moneda nacional) | E75: ='Hoja-Gob_Exp_Proy.'!I16 -> 72.016115 | F75: 72.380242
B76: Módulo 05 | C76: 5.31 | D76: calcular RON | E76: ='Hoja-Gob_Exp_Proy.'!I33 -> -3318.9393 | F76: -3015.8073
B77: Módulo 05 | C77: 5.32 | D77: pronosticar pagos de intereses por deuda interna | E77: ='Hoja-Gob_Exp_Proy.'!I25 -> 1330.5556 | F77: 1037.5238
B78: Módulo 05 | C78: 5.33 | D78: calcular financiamiento | E78: ='Hoja-Gob_Exp_Proy.'!I39 -> 3051.6687 | F78: 2751.569
B80: Módulo 06 | D80: SECTOR MONETARIO | E80: CORRIENTE | F80: SEMANA 5
B81: Módulo 06 | C81: 6.16 | D81: pronosticar tasa de política monetaria para 2014 usando regla de Taylor | E81: ='Regla de Taylor '!E9 -> 9.6716905 | F81: 11.194554
B82: Módulo 06 | C82: 6.23 | D82: calcular logaritmo de demanda de dinero real (ln M3R) para 2014 (redondeado a un punto decimal): | E82: =DD!D33 -> 11.111436 | F82: 11.1008
B83: Módulo 06 | C83: 6.23 | D83: calcular la velocidad de circulación para 2014 (redondeada a un punto decimal): | E83: ='Velocidad y demanda de dinero '!L13 -> 2.0977448 | F83: 2.0756821
B84: Módulo 06 | C84: 6.27 | D84: calcular AEN al final de 2014 (en miles de millones de moneda nacional) | E84: ='AEN y OPN totales'!C15 -> 2418.4629 | F84: 2271.8554
B85: Módulo 06 | C85: 6.3 | D85: calcular Otras partidas netas al final de 2014 (en miles de millones de moneda nacional) | E85: ='AEN y OPN totales'!C33 -> -3864.7861 | F85: -3887.2558
B86: Módulo 06 | C86: 6.31 | D86: calcular crédito al sector privado | E86: =MON_PSD!L13 -> 11968.402 | F86: 12215
B87: Módulo 06 | C87: 6.32 | D87: crecimiento del crédito al sector privado | E87: =MON_IND!L9 -> 2.9443063 | F87: 5.1
B88: Módulo 06 | C88: 6.34 | D88: dinero de reserva en 2014 | E88: ='Multiplicador del dinero'!K10 -> 2765.4908 | F88: 2762.8048
B89: Módulo 06 | C89: 6.35 | D89: activos del BC frente a otras sociedades de depósito | E89: =MON_PSD!L28 -> 1563.7073 | F89: 1725.1504
B90: Módulo 06 | C90: 6.35 | D90: pasivos del BC frente a otras sociedades de depósito. | E90: =MON_PSD!L36 -> 1805.7633 | F90: 1804.0095
B92: Módulo 07 | D92: ESCENARIO BASE | E92: CORRIENTE | F92: SEMANA 6
B93: Módulo 07 | C93: 7.3 | D93: Sector real e inflación (variación porcentual anual, salvo especificación)
B94: Módulo 07 | D94: PIB real | E94: ='Cuadro SEFI'!J6 -> 4.4517021 | F94: 4.4507184
B95: Módulo 07 | D95: Brecha del producto (porcentaje del PIB potencial) | E95: ='Cuadro SEFI'!J7 -> 1.2491751 | F95: 1.2482215
B96: Módulo 07 | D96: deflactor del PIB | E96: ='Cuadro SEFI'!J8 -> 8.1255598 | F96: 8.1228984
B97: Módulo 07 | D97: Índice de precios al consumidor (promedio) | E97: ='Cuadro SEFI'!J9 -> 7.3556692 | F97: 7.3529899
B98: Módulo 07 | D98: Tas de interés real (tasa interbancaria) | E98: ='Cuadro SEFI'!J11 -> 7.3160213 | F98: 7.3169248
B99: Módulo 07 | D99: Tipo de cambio (MN por USD, promedio) (- apreciación) | E99: ='Cuadro SEFI'!J19 -> 6.2104172 | F99: 6.2068039
B100: Módulo 07 | C100: 7.4 | D100: Externo (en porcentaje del PIB, salvo especificación)
B101: Módulo 07 | D101: Saldo en cuenta corriente | E101: ='Cuadro SEFI'!J24 -> -7.0207629 | F101: -7.0206833
B102: Módulo 07 | D102: Saldo en cuenta financiera y de capital | E102: ='Cuadro SEFI'!J26 -> -6.5050844 | F102: -6.5051226
B103: Módulo 07 | D103: Activos de reserva (millones de USD) | E103: ='Cuadro SEFI'!J28 -> 4534.4963 | F103: =ROUNDDOWN(4534.55214159877,0) -> 4534
B104: Módulo 07 | D104: En meses de importaciones (bienes y servicios) | E104: ='Cuadro SEFI'!J30 -> 2.5029508 | F104: 2.5029979
...

Sheet Cuadro SEFI
C2: Macronia: Indicadores económicos seleccionados, 2008-14
D3: 2008 | E3: =D3+1 -> 2009 | F3: =E3+1 -> 2010 | G3: =F3+1 -> 2011 | H3: =G3+1 -> 2012 | I3: =H3+1 -> 2013 | J3: Base: 2014
D4: (Variación porcentual anual, salvo especificación)
C5: Ingreso nacional y precios
C6: PIB real | D6: 2.4011889 | E6: -1.6305202 | F6: 4.8594958 | G6: 5.6553885 | H6: 4.185179 | I6: 4.557993 | J6: =PIB_real!L23 -> 4.4517021
C7: Brecha del PIB (porcentaje del PIB potencial) | D7: 3.7527713 | E7: -1.579742 | F7: -1.2262808 | G7: -1.3561522 | H7: 0.27332419 | I7: 0.81132237 | J7: =PIB_real!L50 -> 1.2491751
C8: Deflactor del PIB | D8: 11.077943 | E8: 8.6233366 | F8: 6.763734 | G8: 4.3046031 | H8: 4.5272294 | I8: 6.8916443 | J8: =100*(Deflactor_PIB!L35/Deflactor_PIB!K35-1) -> 8.1255598
C9: Índice de precios al consumidor (promedio) | D9: 13.424651 | E9: 7.8427557 | F9: 5.6626532 | G9: 4.8781492 | H9: 4.6130302 | I9: 6.1358513 | J9: =Inflación!R49 -> 7.3556692
C10: Índice de precios al consumidor (fin del período) | D10: 13.900308 | E10: 4.0477107 | F10: 5.8279713 | G10: 4.731288 | H10: 5 | I10: 6.6042632 | J10: =Inflación!R50 -> 7.037935
C11: Tasa de interés real (tasa interbancaria) | D11: -1.9246506 | E11: 0.40724435 | F11: 2.3373468 | G11: 3.1218508 | H11: 4.6369698 | I11: 6.0641487 | J11: ='Inversión privada real'!K16 -> 7.3160213
C13: Sector externo
C14: Exportación de bienes y servicios (variación de volumen) | D14: -3.2262497 | E14: -14.738922 | F14: 4.9130977 | G14: 6.9688892 | H14: 8.5805633 | I14: 3.6726139 | J14: ='Exportaciones reales de bienes'!O25 -> 4.2607596
C15: Exportación de bienes y servicios (variación de precios) | D15: 9.6618891 | E15: 6.9024072 | F15: -0.68224333 | G15: -0.52769458 | H15: 3.3981633 | I15: 1.5 | J15: ='Exportaciones reales de bienes'!F23 -> 0.41721528
C16: Importación de bienes y servicios (variación de volumen) | D16: 4.0192093 | E16: -23.5 | F16: 13.985452 | G16: 12.161374 | H16: 8.7396552 | I16: 4.6261335 | J16: ='Importaciones reales de bienes'!O24 -> 5.3384819
C17: Importación de bienes y servicios (variación de precios) | D17: 12.142037 | E17: -2.4075477 | F17: -5.2576711 | G17: 0.27208527 | H17: 1.5719142 | I17: 1.5 | J17: ='Importaciones reales de bienes'!F22 -> 0.41721528
C18: Términos de intercambio (positivos -) | D18: -2.2116133 | E18: 9.539626 | F18: 4.8293385 | G18: -0.79760967 | H18: 1.7979862 | I18: 0 | J18: =(((1+J15/100)/(1+J17/100))-1)*100 -> 0
C19: Tipo de cambio (MN por USD, promedio) (- apreciación) | D19: 1.8617498 | E19: 8.941328 | F19: -8.2783452 | G19: -3.6949642 | H19: 0.86682713 | I19: 3.8038008 | J19: =100*(BP!L58/BP!K58-1) -> 6.2104172
C20: Tipo de cambio (MN por USD, fin del período) | D20: 11.517768 | E20: 1.7588709 | F20: -9.2473993 | G20: -0.46981305 | H20: 0.089945393 | I20: 7.5143188 | J20: =100*(BP!L59/BP!K59-1) -> 4.9976471
C21: Tipo de cambio real (bilateral MN/USD) (- apreciación) | D21: … | E21: 0.84628357 | F21: -11.877525 | G21: -5.541248 | H21: -1.6935658 | I21: -0.73019014 | J21: =100*('TC nominal'!I22/'TC nominal'!H22-1) -> 0.41721528
D23: (En porcentaje del PIB, salvo indicación en contrario)
C24: Saldo en cuenta corriente | D24: -10.464345 | E24: -1.0412049 | F24: -3.5232025 | G24: -5.766358 | H24: -6.5810767 | I24: -6.653527 | J24: =100*(PIB_Nominal!L26/PIB_Nominal!L6) -> -7.0207629
C25: Del cual: Saldo comercial | D25: -10.394907 | E25: 0.62446844 | F25: -2.4541238 | G25: -4.824109 | H25: -5.1845419 | I25: -5.4825381 | J25: =100*(PIB_Nominal!L14/PIB_Nominal!L6) -> -5.9252434
C26: Saldo en cuenta financiera y de capital | D26: -8.8837946 | E26: -2.6765801 | F26: -5.5293997 | G26: -6.6219847 | H26: -6.5723177 | I26: -6.5879872 | J26: =100*(BP!L21-BP!L19)/BP!L57 -> -6.5050844
C27: Variación de activos de reserva (millones de USD, aumento +) | D27: -314.9 | E27: 267.5 | F27: 563.5 | G27: 128.6 | H27: 49.971609 | I27: -29.228791 | J27: =(PII!L13-PII!K13) -> -244.54656
C28: Activos de reserva (millones de USD) | D28: 3798.7 | E28: 4066.2 | F28: 4629.7 | G28: 4758.3 | H28: 4808.2716 | I28: 4779.0428 | J28: =PII!L13 -> 4534.4963
C29: de los cuales: Financiamiento del FMI (programa) | F29: … | G29: ... | H29: ... | I29: ... | J29: =BP!L44 -> 0
C30: En meses de importaciones (bienes y servicios) | D30: 2.7709037 | E30: 3.9728074 | F30: 3.7694257 | G30: 3.3062959 | H30: 3.0135026 | I30: 2.8204427 | J30: =J28/((BP!L8+BP!L11)/12) -> 2.5029508
C32: Finanzas públicas | D32: (En porcentaje del PIB)
C33: Ingreso | D33: 16.896242 | E33: 15.007707 | F33: 15.486725 | G33: 15.564533 | H33: 15.462876 | I33: 15.332847 | J33: =Gob_EOG_Ind!L6 -> 15.283679
C34: Gasto | D34: 15.899072 | E34: 18.195114 | F34: 20.817859 | G34: 19.614825 | H34: 20.017705 | I34: 23.152225 | J34: =Gob_EOG_Ind!L7 -> 27.711481
C35: del cual Gastos primarios | D35: 13.591401 | E35: 15.908288 | F35: 18.540138 | G35: 17.301764 | H35: 17.78875 | I35: 19.689076 | J35: =Gob_EOG_Ind!L8 -> 22.459537
C36: Saldo primario global | D36: 2.8878592 | E36: -1.434776 | F36: -3.8157089 | G36: -2.5765204 | H36: -3.6374833 | I36: -4.4867053 | J36: =Gob_EOG_Ind!L14 -> -7.2984131
C37: Saldo primario estructural (porcentaje del PIB potencial) | D37: 2.7016741 | E37: -0.61338272 | F37: -2.7973698 | G37: -1.470682 | H37: -2.3808242 | I37: -4.5345448 | J37: =Gob_EOG_Ind!L26 -> -7.4848508
C38: Impulso fiscal (expansivo +) | E38: 3.3150568 | F38: 2.1839871 | G38: -1.3266878 | H38: 0.91014217 | I38: 2.1537206 | J38: =-(J37-I37) -> 2.9503059
C39: Saldo global | D39: 0.58018797 | E39: -3.721602 | F39: -6.0934293 | G39: -4.8895819 | H39: -5.8664381 | I39: -7.9498542 | J39: =Gob_EOG_Ind!L13 -> -12.550357
C40: Deuda del gobierno general | D40: 41.730548 | E40: 42.947517 | F40: 43.945377 | G40: 44.055857 | H40: 44.600625 | I40: 48.102738 | J40: =Gob_Stock_Ind!L7 -> 55.470857
C42: Sector monetario
C43: Dinero en sentido amplio (crecimiento porcentual anual, f.d.p.) | D43: 17.401568 | E43: 8.0332619 | F43: 0.79500651 | G43: 7.3200399 | H43: 9.1 | I43: 9.0006394 | J43: =(MON_PSD!L17-MON_PSD!K17)/MON_PSD!K17*100 -> 8.1977181
C44: Crédito al sector privado (variación porcentual anual) | D44: 31.618642 | E44: 5.299032 | F44: 4.9429232 | G44: 12.392878 | H44: 8.0410539 | I44: 6.8386355 | J44: =(MON_PSD!L13-MON_PSD!K13)/MON_PSD!K13*100 -> 2.9443063
C45: Velocidad (PIB/promedio dinero en sentido amplio) | D45: 1.8087583 | E45: 1.7203628 | F45: 1.84703 | G45: 1.9558777 | H45: 1.9678115 | I45: 2.0168154 | J45: =MON_IND!L27 -> 2.0977448
C46: Tasa de política monetaria (porcentaje; fin de período) | D46: 7.9575 | E46: 9.54 | F46: 8.255 | G46: 5.6416667 | H46: 5 | I46: 8.8660415 | J46: ='Regla de Taylor '!D9 -> 9.6716905
C47: Tasa interbancaria (promedio, en porcentaje) | D47: 11.5 | E47: 8.25 | F47: 8 | G47: 8 | H47: 9.25 | I47: 12.2 | J47: =DD!$H33 -> 14.671691
D49: (Contribuciones al crecimiento del dinero en sentido amplio)
C50: Activos externos netos (sociedades de depósito) | D50: -0.62737612 | E50: 5.6537957 | F50: 0.2041281 | G50: -4.2714935 | H50: 5.9029336 | I50: 0.70630247 | J50: =(MON_PSD!L7-MON_PSD!K7)/MON_PSD!K17*100 -> -1.095204
C51: Crédito interno neto (sociedades de depósito) | D51: 26.476064 | E51: 7.8131246 | F51: 4.8988597 | G51: 14.093459 | H51: 10.639451 | I51: 11.68968 | J51: =(MON_PSD!L9-MON_PSD!K9)/MON_PSD!K17*100 -> 10.285091
C52: Del cual: derechos netos frente al sector público | D52: 0.48495402 | E52: 2.9297317 | F52: 0.45893224 | G52: 2.5035948 | H52: 2.7639696 | I52: 5.0568684 | J52: =(MON_PSD!L10-MON_PSD!K10)/MON_PSD!K17*100 -> 7.4860421
C53: Del cual: derechos netos frente al resto del sector privado | D53: 25.99111 | E53: 4.8833928 | F53: 4.4399275 | G53: 11.589864 | H53: 7.8754811 | I53: 6.6328112 | J53: =(MON_PSD!L13-MON_PSD!K13)/MON_PSD!K17*100 -> 2.7990487
C54: Otras partidas (sociedades de depósito) | D54: -8.4471195 | E54: -5.4336583 | F54: -4.3079813 | G54: -2.5019254 | H54: -7.4423843 | I54: -3.3953427 | J54: =(MON_PSD!L14-MON_PSD!K14)/MON_PSD!K17*100 -> -0.99216868
C56: Ahorro e inversión | D56: (En porcentaje del PIB, salvo especificación)
C57: Inversión | D57: 27.441326 | E57: 15.642271 | F57: 19.644637 | G57: 22.06772 | H57: 21.240237 | I57: 20.963677 | J57: =PIB_Nominal!L35 -> 20.964149
C58: Ahorro interno | D58: 16.976981 | E58: 14.601066 | F58: 16.121434 | G58: 16.301362 | H58: 14.65916 | I58: 14.31015 | J58: =PIB_Nominal!L34 -> 13.943386
C60: PIB a precios corrientes (miles de millones de moneda nacional) | D60: 14737.186 | E60: 15747.009 | F60: 17629.078 | G60: 19427.849 | H60: 21157.293 | I60: 23646.186 | J60: =PIB_Nominal!L6 -> 26705.763
C61: PIB a precios corrientes (miles de millones de USD) | D61: 28.004925 | E61: 27.467887 | F61: 33.526244 | G61: 38.364631 | H61: 41.420758 | I61: 44.597015 | J61: =BP!L57/1000 -> 47.422294
C63: Fuente: Datos proporcionados por las autoridades de Macronia y estimaciones del personal técnico del FMI.

Sheet Cuadro PIB
C2: Macronia: PIB, coherencia de precios y volúmenes, 2014
C3: Pronóstico de base
D4: 2013 | G4: 2014
D5: Valor (miles de millones de MN) | H5: % Δ precio | J5: % Δ | K5: Valor (miles de millones de MN) | M5: proporción %
D6: a precios de '05 | E6: a precios de '13 | G6: USD | H6: MN/USD | I6: MN | J6: volumen | K6: a precios de '05 | L6: a precios de '14 | M6: del PIB
D7: [I] | E7: [II] | G7: [III] | H7: [IV] | I7: [V]= III*IV | J7: [VI] | K7: [VII]= I*VI | L7: [VIII]= VII*V | M7: [IX]
C10: Consumo | D10: =PIB_real!K7 -> 10605.631 | E10: =PIB_Nominal!K7 -> 19985.487 | G10: . . . | H10: . . . | I10: =(L10/E10/(1+J10%)-1)*100 -> 8.1038324 | J10: =(K10/D10-1)*100 -> 5.0193341 | K10: =K11+K12 -> 11137.963 | L10: =L11+L12 -> 22689.509 | M10: =L10/L$26*100 -> 84.961094
C11: Privado | D11: =PIB_real!K8 -> 9288 | E11: =PIB_Nominal!K8 -> 16647.635 | G11: . . . | H11: . . . | I11: =Inflación!O31 -> 7.3556692 | J11: ='Consumo real privado'!J34 -> 2.8936064 | K11: =D11*(1+J11/100) -> 9556.7582 | L11: =E11*(1+I11/100)*(1+J11/100) -> 18389.33 | M11: =L11/L$26*100 -> 68.859033
C12: Público | D12: =PIB_real!K9 -> 1317.6308 | E12: =PIB_Nominal!K9 -> 3337.8524 | G12: . . . | H12: . . . | I12: =(L12/E12/(1+J12%)-1)*100 -> 7.3556692 | J12: =100*(K12/D12-1) -> 20.003622 | K12: =D12+(K36*K32) -> 1581.2047 | L12: =L13+L14 -> 4300.1784 | M12: =L12/L$26*100 -> 16.102061
C13: Gobierno general | D13: . . . | E13: =Gob_EOG!K16+Gob_EOG!K17 -> 2169.1777 | I13: =I11 -> 7.3556692 | J13: =J12 -> 20.003622 | K13: . . . | L13: =E13*(1+I13/100)*(1+J13/100) -> 2794.5667 | M13: =L13/L$26*100 -> 10.464283
C14: Resto del sector público | D14: . . . | E14: =E12-E13 -> 1168.6747 | G14: . . . | H14: . . . | I14: =I13 -> 7.3556692 | J14: =J12 -> 20.003622 | K14: . . . | L14: =E14*(1+I14/100)*(1+J14/100) -> 1505.6117 | M14: =L14/L$26*100 -> 5.6377782
C15: Inversión | D15: =PIB_real!K10 -> 2941 | E15: =PIB_Nominal!K10 -> 4957.11 | G15: . . . | H15: . . . | I15: =(L15/E15/(1+J15%)-1)*100 -> 7.5348309 | J15: =((K15/D15)-1)*100 -> 5.0278602 | K15: =(K18+K17+K16) -> 3088.8694 | L15: =(L18+L17+L16) -> 5598.6359 | M15: =L15/L$26*100 -> 20.964149
C16: Privado | D16: =PIB_real!K11 -> 2336.1027 | E16: =PIB_Nominal!K11 -> 4062.9269 | G16: . . . | H16: . . . | I16: =0.6*I11+0.4*I22 -> 7.5348309 | J16: ='Inversión privada real'!J36 -> 5.0278602 | K16: =D16*(1+J16/100) -> 2453.5587 | L16: =E16*(1+I16/100)*(1+J16/100) -> 4588.7319 | M16: =L16/L$26*100 -> 17.182553
C17: Público | D17: =PIB_real!K12 -> 339.92761 | E17: =PIB_Nominal!K12 -> 590.02673 | G17: . . . | H17: . . . | I17: =0.6*I11+0.4*I22 -> 7.5348309 | J17: =J16 -> 5.0278602 | K17: =D17*(1+J17/100) -> 357.0187 | L17: =E17*(1+I17/100)*(1+J17/100) -> 666.38523 | M17: =L17/L$26*100 -> 2.4952862
C18: =PIB_Nominal!C13 -> Variación de saldos | D18: =PIB_real!K13 -> 264.96964 | E18: =PIB_Nominal!K13 -> 304.15633 | G18: . . . | H18: . . . | I18: =0.6*I11+0.4*I22 -> 7.5348309 | J18: =J17 -> 5.0278602 | K18: =D18*(1+J18/100) -> 278.29195 | L18: =E18*(1+I18/100)*(1+J18/100) -> 343.51882 | M18: =L18/L$26*100 -> 1.2863097
C20: =PIB_Nominal!C15 -> Exportaciones de bienes y servicios | D20: =PIB_real!K15 -> 6523 | E20: =PIB_Nominal!K15 -> 9484.6174 | G20: ='Exportaciones reales de bienes'!F17 -> 1.5 | H20: ='TC nominal'!I16 -> 6.2104172 | I20: =((1+G20/100)*(1+H20/100)-1)*100 -> 7.8035735 | J20: ='Exportaciones reales de bienes'!O25 -> 4.2607596 | K20: =D20*(1+J20/100) -> 6800.9293 | L20: =E20*(1+I20/100)*(1+J20/100) -> 10660.409 | M20: =L20/L$26*100 -> 39.918008
C22: =PIB_Nominal!C16 -> Importaciones de bienes y servicios | D22: =PIB_real!K16 -> 7295 | E22: =PIB_Nominal!K16 -> 10781.029 | G22: ='Importaciones reales de bienes'!F16 -> 1.5 | H22: =H20 -> 6.2104172 | I22: =((1+G22/100)*(1+H22/100)-1)*100 -> 7.8035735 | J22: ='Importaciones reales de bienes'!O24 -> 5.3384819 | K22: =D22*(1+J22/100) -> 7684.4423 | L22: =E22*(1+I22/100)*(1+J22/100) -> 12242.79 | M22: =L22/L$26*100 -> 45.843252
C24: Discrepancia estadística | D24: =PIB_real!K17 -> 0 | E24: =PIB_Nominal!K17 -> 0 | G24: . . . | H24: . . . | I24: =I28 -> 8.1255598 | J24: -100 | K24: =D24*(1+J24/100) -> 0 | L24: =K24*(1+I24/100) -> 0 | M24: =L24/L$26*100 -> 0
C26: PIB-suma de gastos | D26: =D10+D15+D20-D22+D24 -> 12774.631 | E26: =E10+E15+E20-E22+E24 -> 23646.186 | G26: . . . | H26: . . . | I26: =(L26/E26/(1+J26/100)-1)*100 -> 8.1255598 | J26: =((K26/D26)-1)*100 -> 4.4517021 | K26: =K10+K15+K20-K22+K24 -> 13343.319 | L26: =L10+L15+L20-L22+L24 -> 26705.763 | M26: 100
C28: PIB-proyección inicial | G28: . . . | H28: . . . | I28: 8.1255598 | J28: 4.4517021 | K28: =D26*(1+J28/100) -> 13343.319 | L28: =E26*(1+I28/100)*(1+J28/100) -> 26705.763 | P28: Note: | Y28: Cell I28 | Z28: Cell J28
C29: verificación | K29: =K26-K28 -> 0 | L29: =L26-L28 -> 0 | P29: - Until Module 5, your cells I28 and J28 will use the initial assumptions. | X29: Initial | Y29: 7.48 | Z29: 4.63
P30: - In Module 5, you will revise them to reflect the expenditure approach estimation. | X30: Revised | Y30: 9.2087336 | Z30: 5.305556
C31: Partida informativa:
C32: Producto potencial (precios de 2005) | D32: =PIB_real!K19 -> 12671.821 | K32: =PIB_real!L19 -> 13178.694
C33: Demanda interna | D33: =D10+D15 -> 13546.631 | E33: =D33/D$26*100 -> 106.04323 | K33: =K10+K15 -> 14226.832 | L33: =L10+L15 -> 28288.144 | M33: =M10+M15 -> 105.92524
C34: Exportaciones netas | D34: =D20-D22 -> -772 | E34: =D34/D$26*100 -> -6.0432275 | K34: =K20-K22 -> -883.51291 | L34: =L20-L22 -> -1582.3815 | M34: =L34/L$26*100 -> -5.9252434
C36: Estímulo fiscal (en porcentaje del producto potencial, respecto a 2013) | K36: 0.02
C37: Proyección de brecha del tipo de cambio real pestaña TC nominal (verificar que sea igual a lo siguiente) | K37: ='TC nominal'!I34*100 -> -0.31602132
C38: Proyección de brecha del tipo de cambio real pestaña Inflación | K38: =Inflación!K29 -> -0.31525678
C39: Endeudamiento interno (verificar=0 de Hoja Gob_exp_proy) | K39: ='Hoja-Gob_Exp_Proy.'!I41 -> -4.0927262e-12
C42: NOTA
C43: Nivel deflactor 2013
C44: Deflactor del consumo (privado) | D44: =E11/D11 -> 1.792381
C45: Deflactor del consumo (público) | D45: =E12/D12 -> 2.5332228

Sheet PIB_Nominal
B2: Macronia: PIB nominal, 2006-14
D3: 2006 | E3: 2007 | F3: 2008 | G3: 2009 | H3: 2010 | I3: 2011 | J3: 2012 | K3: 2013 | L3: 2014
B4: (en miles de millones de moneda nacional)
C5: Producto interno bruto, a precios corrientes
C6: PIB | D6: 10964.62 | E6: 12956.322 | F6: 14737.186 | G6: 15747.009 | H6: 17629.078 | I6: 19427.849 | J6: 21157.293 | K6: 23646.186 | L6: ='Cuadro PIB'!L26 -> 26705.763
C7: Consumo final | D7: 8700.4437 | E7: 10352.871 | F7: 12200.565 | G7: 13108.591 | H7: 14576.657 | I7: 16016.788 | J7: 17760.343 | K7: 19985.487 | L7: =L8+L9 -> 22689.509
C8: Privado | D8: 7624.2096 | E8: 9087.1639 | F8: 10645.097 | G8: 11176.638 | H8: 12277.757 | I8: 13520.438 | J8: 15027.228 | K8: 16647.635 | L8: ='Cuadro PIB'!L11 -> 18389.33
C9: Público | D9: 1076.2341 | E9: 1265.7069 | F9: 1555.4684 | G9: 1931.9535 | H9: 2298.9 | I9: 2496.35 | J9: 2733.1145 | K9: 3337.8524 | L9: ='Cuadro PIB'!L12 -> 4300.1784
C10: Formación bruta de capital fijo | D10: 2919.2115 | E10: 3202.1678 | F10: 4044.0793 | G10: 2463.1898 | H10: 3463.1683 | I10: 4287.2834 | J10: 4493.8592 | K10: 4957.11 | L10: =L11+L12+L13 -> 5598.6359
C11: Privada | D11: 1935.5708 | E11: 2523.1836 | F11: 3083.0458 | G11: 3105.0591 | H11: 2992.8914 | I11: 3513.9263 | J11: 3683.2391 | K11: 4062.9269 | L11: ='Cuadro PIB'!L16 -> 4588.7319
C12: Pública | D12: 234.02446 | E12: 286.08395 | F12: 335.24812 | G12: 328.85775 | H12: 425.53619 | I12: 510.29972 | J12: 534.88768 | K12: 590.02673 | L12: ='Cuadro PIB'!L17 -> 666.38523
C13: Variación de saldos | D13: 749.61619 | E13: 392.90029 | F13: 625.78538 | G13: -970.72705 | H13: 44.740729 | I13: 263.05738 | J13: 275.73238 | K13: 304.15633 | L13: ='Cuadro PIB'!L18 -> 343.51882
C14: Saldo externo | D14: -708.14401 | E14: -653.40526 | F14: -1531.9167 | G14: 98.335101 | H14: -432.6394 | I14: -937.22061 | J14: -1096.9087 | K14: -1296.4112 | L14: =+L15-L16 -> -1582.3815
C15: Exportaciones de bienes y servicios | D15: 5658.5976 | E15: 6623.9268 | F15: 7134.1258 | G15: 7122.0184 | H15: 7248.1128 | I15: 7780.1097 | J15: 8683.1333 | K15: 9484.6174 | L15: ='Cuadro PIB'!L20 -> 10660.409
C16: Importaciones de bienes y servicios | D16: 6366.7416 | E16: 7277.3321 | F16: 8666.0425 | G16: 7023.6833 | H16: 7680.7522 | I16: 8717.3303 | J16: 9780.042 | K16: 10781.029 | L16: ='Cuadro PIB'!L22 -> 12242.79
C17: Discrepancia estadística | D17: 53.108978 | E17: 54.688654 | F17: 24.458182 | G17: 76.893057 | H17: 21.891565 | I17: 60.998131 | J17: 0 | K17: 0 | L17: =L6-L7-L10-L14 -> 0
C19: Ingreso nacional, absorción, ahorro y saldo ahorro-inversión
C20: Ingreso nacional bruto | D20: 10926.691 | E20: 12650.86 | F20: 14469.74 | G20: 15202.127 | H20: 17226.001 | I20: 19020.276 | J20: 20691.475 | K20: 23187.478 | L20: =L6+L40 -> 26214.646
C21: Ingreso nacional bruto disponible | D21: 11105.187 | E21: 12893.516 | F21: 14702.494 | G21: 15407.822 | H21: 17418.718 | I21: 19183.792 | J21: 20861.824 | K21: 23369.292 | L21: =L6+L40+L41 -> 26413.196
C22: Absorción | D22: 11619.655 | E22: 13555.039 | F22: 16244.644 | G22: 15571.781 | H22: 18039.826 | I22: 20304.072 | J22: 22254.202 | K22: 24942.597 | L22: =L7+L10 -> 28288.144
C23: Ahorro nacional | D23: 2404.7433 | E23: 2540.6447 | F23: 2501.9293 | G23: 2299.2311 | H23: 2842.0602 | I23: 3167.0041 | J23: 3101.4815 | K23: 3383.8046 | L23: =L21-L7 -> 3723.6876
C24: Inversión | D24: 2919.2115 | E24: 3202.1678 | F24: 4044.0793 | G24: 2463.1898 | H24: 3463.1683 | I24: 4287.2834 | J24: 4493.8592 | K24: 4957.11 | L24: =L10 -> 5598.6359
C25: Saldo ahorro-inversión | D25: -514.46823 | E25: -661.52313 | F25: -1542.15 | G25: -163.95864 | H25: -621.10812 | I25: -1120.2793 | J25: -1392.3777 | K25: -1573.3054 | L25: =L23-L24 -> -1874.9483
C26: Saldo en cuenta corriente (miles de millones MN) | D26: -514.46823 | E26: -661.52313 | F26: -1542.15 | G26: -163.95864 | H26: -621.10812 | I26: -1120.2793 | J26: -1392.3777 | K26: -1573.3054 | L26: =L14+L40+L41 -> -1874.9483
B27: (en porcentaje del PIB)
C28: Indicadores económicos seleccionados
C29: Absorción | D29: 105.97408 | E29: 104.62104 | F29: 110.22894 | G29: 98.887229 | H29: 102.32995 | I29: 104.51014 | J29: 105.18454 | K29: 105.48254 | L29: =L22/L6*100 -> 105.92524
C30: Consumo final | D30: 79.350161 | E30: 79.905939 | F30: 82.787618 | G30: 83.244958 | H30: 82.685308 | I30: 82.442416 | J30: 83.944305 | K30: 84.518861 | L30: =L7/L6*100 -> 84.961094
C31: Formación bruta de capital fijo | D31: 26.623918 | E31: 24.715099 | F31: 27.441326 | G31: 15.642271 | H31: 19.644637 | I31: 22.06772 | J31: 21.240237 | K31: 20.963677 | L31: =L10/L6*100 -> 20.964149
C32: Exportaciones de bienes y servicios | D32: 51.607785 | E32: 51.125055 | F32: 48.40901 | G32: 45.227753 | H32: 41.114532 | I32: 40.046171 | J32: 41.040852 | K32: 40.110559 | L32: =L15/L6*100 -> 39.918008
C33: Importaciones de bienes y servicios | D33: 58.06623 | E33: 56.168194 | F33: 58.803916 | G33: 44.603285 | H33: 43.568655 | I33: 44.87028 | J33: 46.225393 | K33: 45.593097 | L33: =L16/L6*100 -> 45.843252
C34: Ahorro nacional | D34: 21.931843 | E34: 19.609305 | F34: 16.976981 | G34: 14.601066 | H34: 16.121434 | I34: 16.301362 | J34: 14.65916 | K34: 14.31015 | L34: =L23/L6*100 -> 13.943386
C35: Inversión | D35: 26.623918 | E35: 24.715099 | F35: 27.441326 | G35: 15.642271 | H35: 19.644637 | I35: 22.06772 | J35: 21.240237 | K35: 20.963677 | L35: =L10/L6*100 -> 20.964149
C36: Saldo ahorro-inversión | D36: -4.6920752 | E36: -5.1057941 | F36: -10.464345 | G36: -1.0412049 | H36: -3.5232025 | I36: -5.766358 | J36: -6.5810767 | K36: -6.653527 | L36: =L25/L6*100 -> -7.0207629
B38: (en miles de millones de moneda nacional)
C39: Otras partidas, de la balanza de pagos
C40: Saldo de ingreso primario | D40: -37.928659 | E40: -305.46171 | F40: -267.44546 | G40: -544.88251 | H40: -403.07669 | I40: -407.57341 | J40: -465.8177 | K40: -458.70834 | L40: =BP!L12*BP!L58/1000 -> -491.117
C41: Saldo de ingreso secundario | D41: 178.49546 | E41: 242.65519 | F41: 232.75397 | G41: 205.69572 | H41: 192.7164 | I41: 163.51656 | J41: 170.34874 | K41: 181.81414 | L41: =BP!L17*'TC nominal'!I13/1000 -> 198.55017

Sheet LRY
B1: PRODUCTO RESUMIDO
B3: Estadísticas de la regresión
B4: R múltiple | C4: 0.99405164
B5: R cuadrado | C5: 0.98813867
B6: R cuadrado ajustado | C6: 0.98784937
B7: Error estándar | C7: 0.05600592
B8: Observaciones | C8: 43
B10: ANOVA
C11: df | D11: SS | E11: MS | F11: F | G11: Significancia F
B12: Regresión | C12: 1 | D12: 10.713619 | E12: 10.713619 | F12: 3415.6103 | G12: 4.1219775e-41
B13: Residuo | C13: 41 | D13: 0.12860319 | E13: 0.0031366631
B14: Total | C14: 42 | D14: 10.842222
C16: Coeficiente | D16: Error estándar | E16: Estadística t | F16: Valor P | G16: 95% inferior | H16: 95% superior | I16: 95,0% inferior | J16: 95,0% superior
B17: Ordenada en el origen | C17: 7.6744177 | D17: 0.017383999 | E17: 441.46446 | F17: 5.1572067e-77 | G17: 7.63931 | H17: 7.7095254 | I17: 7.63931 | J17: 7.7095254
B18: X Variable 1 | C18: 0.040222912 | D18: 0.00068823911 | E18: 58.443223 | F18: 4.1219775e-41 | G18: 0.038832985 | H18: 0.041612839 | I18: 0.038832985 | J18: 0.041612839
B20: Notación:
B21: RY | C21: PIB real
B22: ln RY | C22: Logaritmo natural del PIB real
B23: Tiempo | C23: Tendencia de tiempo
C24: RY | D24: LRY | E24: Tendencia de tiempo
C25: PIB real efectivo | D25: Log o PIB real | E25: Tendencia de tiempo | F25: Ajustado | G25: Observación | H25: LRY predicha | I25: Residuos | J25: serie original | K25: verificación
B26: 1970 | C26: 2113.5785 | D26: =LN(C26) -> 7.6561378 | E26: 1 | F26: =$C$17+$C$18*G26 -> 7.7146406 | G26: 1 | H26: 7.7146406 | I26: -0.058502881 | J26: =F26+I26 -> 7.6561378 | K26: =J26-D26 -> 0
B27: =B26+1 -> 1971 | C27: 2256.8475 | D27: =LN(C27) -> 7.7217242 | E27: =E26+1 -> 2 | F27: =$C$17+$C$18*G27 -> 7.7548636 | G27: 2 | H27: 7.7548636 | I27: -0.033139333 | J27: =F27+I27 -> 7.7217242 | K27: =J27-D27 -> 0
B28: =B27+1 -> 1972 | C28: 2441.4135 | D28: =LN(C28) -> 7.8003325 | E28: =E27+1 -> 3 | F28: =$C$17+$C$18*G28 -> 7.7950865 | G28: 3 | H28: 7.7950865 | I28: 0.0052460053 | J28: =F28+I28 -> 7.8003325 | K28: =J28-D28 -> 0
B29: =B28+1 -> 1973 | C29: 2629.6201 | D29: =LN(C29) -> 7.8745946 | E29: =E28+1 -> 4 | F29: =$C$17+$C$18*G29 -> 7.8353094 | G29: 4 | H29: 7.8353094 | I29: 0.039285272 | J29: =F29+I29 -> 7.8745946 | K29: =J29-D29 -> 0
B30: =B29+1 -> 1974 | C30: 2775.4299 | D30: =LN(C30) -> 7.9285609 | E30: =E29+1 -> 5 | F30: =$C$17+$C$18*G30 -> 7.8755323 | G30: 5 | H30: 7.8755323 | I30: 0.053028629 | J30: =F30+I30 -> 7.9285609 | K30: =J30-D30 -> 0
B31: =B30+1 -> 1975 | C31: 2833.7159 | D31: =LN(C31) -> 7.9493442 | E31: =E30+1 -> 6 | F31: =$C$17+$C$18*G31 -> 7.9157552 | G31: 6 | H31: 7.9157552 | I31: 0.033588952 | J31: =F31+I31 -> 7.9493442 | K31: =J31-D31 -> 0
B32: =B31+1 -> 1976 | C32: 2990.068 | D32: =LN(C32) -> 8.0030514 | E32: =E31+1 -> 7 | F32: =$C$17+$C$18*G32 -> 7.9559781 | G32: 7 | H32: 7.9559781 | I32: 0.047073281 | J32: =F32+I32 -> 8.0030514 | K32: =J32-D32 -> 0
B33: =B32+1 -> 1977 | C33: 3256.3178 | D33: =LN(C33) -> 8.0883523 | E33: =E32+1 -> 8 | F33: =$C$17+$C$18*G33 -> 7.996201 | G33: 8 | H33: 7.996201 | I33: 0.092151299 | J33: =F33+I33 -> 8.0883523 | K33: =J33-D33 -> 0
B34: =B33+1 -> 1978 | C34: 3460.4136 | D34: =LN(C34) -> 8.1491434 | E34: =E33+1 -> 9 | F34: =$C$17+$C$18*G34 -> 8.0364239 | G34: 9 | H34: 8.0364239 | I34: 0.11271946 | J34: =F34+I34 -> 8.1491434 | K34: =J34-D34 -> 0
B35: =B34+1 -> 1979 | C35: 3631.4035 | D35: =LN(C35) -> 8.1973745 | E35: =E34+1 -> 10 | F35: =$C$17+$C$18*G35 -> 8.0766468 | G35: 10 | H35: 8.0766468 | I35: 0.12072766 | J35: =F35+I35 -> 8.1973745 | K35: =J35-D35 -> 0
B36: =B35+1 -> 1980 | C36: 3658.7073 | D36: =LN(C36) -> 8.2048652 | E36: =E35+1 -> 11 | F36: =$C$17+$C$18*G36 -> 8.1168698 | G36: 11 | H36: 8.1168698 | I36: 0.087995417 | J36: =F36+I36 -> 8.2048652 | K36: =J36-D36 -> 0
B37: =B36+1 -> 1981 | C37: 3575.879 | D37: =LN(C37) -> 8.1819663 | E37: =E36+1 -> 12 | F37: =$C$17+$C$18*G37 -> 8.1570927 | G37: 12 | H37: 8.1570927 | I37: 0.024873635 | J37: =F37+I37 -> 8.1819663 | K37: =J37-D37 -> 0
B38: =B37+1 -> 1982 | C38: 3315.3264 | D38: =LN(C38) -> 8.1063114 | E38: =E37+1 -> 13 | F38: =$C$17+$C$18*G38 -> 8.1973156 | G38: 13 | H38: 8.1973156 | I38: -0.091004222 | J38: =F38+I38 -> 8.1063114 | K38: =J38-D38 -> 0
B39: =B38+1 -> 1983 | C39: 3453.1153 | D39: =LN(C39) -> 8.1470321 | E39: =E38+1 -> 14 | F39: =$C$17+$C$18*G39 -> 8.2375385 | G39: 14 | H39: 8.2375385 | I39: -0.090506407 | J39: =F39+I39 -> 8.1470321 | K39: =J39-D39 -> 0
B40: =B39+1 -> 1984 | C40: 3730.3475 | D40: =LN(C40) -> 8.2242567 | E40: =E39+1 -> 15 | F40: =$C$17+$C$18*G40 -> 8.2777614 | G40: 15 | H40: 8.2777614 | I40: -0.053504733 | J40: =F40+I40 -> 8.2242567 | K40: =J40-D40 -> 0 | M40: results from Eviews
B41: =B40+1 -> 1985 | C41: 3757.2658 | D41: =LN(C41) -> 8.2314468 | E41: =E40+1 -> 16 | F41: =$C$17+$C$18*G41 -> 8.3179843 | G41: 16 | H41: 8.3179843 | I41: -0.086537539 | J41: =F41+I41 -> 8.2314468 | K41: =J41-D41 -> 0
B42: =B41+1 -> 1986 | C42: 3965.2774 | D42: =LN(C42) -> 8.2853311 | E42: =E41+1 -> 17 | F42: =$C$17+$C$18*G42 -> 8.3582072 | G42: 17 | H42: 8.3582072 | I42: -0.072876133 | J42: =F42+I42 -> 8.2853311 | K42: =J42-D42 -> 0
B43: =B42+1 -> 1987 | C43: 4154.2044 | D43: =LN(C43) -> 8.3318762 | E43: =E42+1 -> 18 | F43: =$C$17+$C$18*G43 -> 8.3984301 | G43: 18 | H43: 8.3984301 | I43: -0.066553939 | J43: =F43+I43 -> 8.3318762 | K43: =J43-D43 -> 0
B44: =B43+1 -> 1988 | C44: 4296.7828 | D44: =LN(C44) -> 8.3656218 | E44: =E43+1 -> 19 | F44: =$C$17+$C$18*G44 -> 8.4386531 | G44: 19 | H44: 8.4386531 | I44: -0.07303122 | J44: =F44+I44 -> 8.3656218 | K44: =J44-D44 -> 0
B45: =B44+1 -> 1989 | C45: 4540.2375 | D45: =LN(C45) -> 8.4207346 | E45: =E44+1 -> 20 | F45: =$C$17+$C$18*G45 -> 8.478876 | G45: 20 | H45: 8.478876 | I45: -0.058141373 | J45: =F45+I45 -> 8.4207346 | K45: =J45-D45 -> 0
B46: =B45+1 -> 1990 | C46: 4703.686 | D46: =LN(C46) -> 8.4561017 | E46: =E45+1 -> 21 | F46: =$C$17+$C$18*G46 -> 8.5190989 | G46: 21 | H46: 8.5190989 | I46: -0.062997141 | J46: =F46+I46 -> 8.4561017 | K46: =J46-D46 -> 0
B47: =B46+1 -> 1991 | C47: 4810.1336 | D47: =LN(C47) -> 8.4784801 | E47: =E46+1 -> 22 | F47: =$C$17+$C$18*G47 -> 8.5593218 | G47: 22 | H47: 8.5593218 | I47: -0.080841651 | J47: =F47+I47 -> 8.4784801 | K47: =J47-D47 -> 0
B48: =B47+1 -> 1992 | C48: 5250.3578 | D48: =LN(C48) -> 8.5660515 | E48: =E47+1 -> 23 | F48: =$C$17+$C$18*G48 -> 8.5995447 | G48: 23 | H48: 8.5995447 | I48: -0.033493193 | J48: =F48+I48 -> 8.5660515 | K48: =J48-D48 -> 0
B49: =B48+1 -> 1993 | C49: 5639.6029 | D49: =LN(C49) -> 8.6375689 | E49: =E48+1 -> 24 | F49: =$C$17+$C$18*G49 -> 8.6397676 | G49: 24 | H49: 8.6397676 | I49: -0.0021986811 | J49: =F49+I49 -> 8.6375689 | K49: =J49-D49 -> 0
B50: =B49+1 -> 1994 | C50: 5906.3333 | D50: =LN(C50) -> 8.6837805 | E50: =E49+1 -> 25 | F50: =$C$17+$C$18*G50 -> 8.6799905 | G50: 25 | H50: 8.6799905 | I50: 0.0037899742 | J50: =F50+I50 -> 8.6837805 | K50: =J50-D50 -> 0
B51: =B50+1 -> 1995 | C51: 6137.9138 | D51: =LN(C51) -> 8.7222402 | E51: =E50+1 -> 26 | F51: =$C$17+$C$18*G51 -> 8.7202134 | G51: 26 | H51: 8.7202134 | I51: 0.0020267503 | J51: =F51+I51 -> 8.7222402 | K51: =J51-D51 -> 0
B52: =B51+1 -> 1996 | C52: 6192.3321 | D52: =LN(C52) -> 8.731067 | E52: =E51+1 -> 27 | F52: =$C$17+$C$18*G52 -> 8.7604363 | G52: 27 | H52: 8.7604363 | I52: -0.029369303 | J52: =F52+I52 -> 8.731067 | K52: =J52-D52 -> 0
... B68: =B67+1 -> 2012 | C68: 12074.868 | D68: =LN(C68) -> 9.3988815 | E68: =E67+1 -> 43 | F68: =$C$17+$C$18*G68 -> 9.4040029 | G68: 43 | H68: 9.4040029 | I68: -0.0051214153 | J68: =F68+I68 -> 9.3988815 | K68: =J68-D68 -> 0

Sheet PIB_real
B2: Macronia: PIB real y crecimiento, 2008-14
D3: 2006 | E3: 2007 | F3: 2008 | G3: 2009 | H3: 2010 | I3: 2011 | J3: 2012 | K3: 2013 | L3: =+K3+1 -> 2014
B4: (en miles de millones de moneda nacional)
C5: Producto interno bruto por gasto, a precios constantes de 2005
C6: PIB | D6: 9864.103 | E6: 10508.008 | F6: 10760.325 | G6: 10584.876 | H6: 11099.247 | I6: 11726.953 | J6: 12217.747 | K6: 12774.631 | L6: =L7+L10+L14+L17 -> 13343.319
C7: Consumo final | D7: 7726.1683 | E7: 8269.9833 | F7: 8549.1915 | G7: 8737.0493 | H7: 9135.1104 | I7: 9504.6399 | J7: 10043.482 | K7: 10605.631 | L7: =L8+L9 -> 11137.963
C8: Privado | D8: 6791.1229 | E8: 7301.5719 | F8: 7553.2801 | G8: 7682.1636 | H8: 8033.693 | I8: 8406.4347 | J8: 8898.374 | K8: 9288 | L8: =K8*(1+L25/100) -> 9556.7582
C9: Público | D9: 935.04534 | E9: 968.41137 | F9: 995.91147 | G9: 1054.8857 | H9: 1101.4174 | I9: 1098.2052 | J9: 1145.1083 | K9: 1317.6308 | L9: =K9*(1+L26/100) -> 1581.2047
C10: Formación bruta de capital fijo | D10: 2553.3827 | E10: 2388.8262 | F10: 2881.415 | G10: 1647.7264 | H10: 2250.0575 | I10: 2803.1322 | J10: 2821.4848 | K10: 2941 | L10: =L11+L12+L13 -> 3088.8694
C11: Privada | D11: 1667.8795 | E11: 1987.7598 | F11: 2155.8517 | G11: 1924.3946 | H11: 1897.3962 | I11: 2226.5912 | J11: 2241.1691 | K11: 2336.1027 | L11: =K11*(1+L28/100) -> 2453.5587
C12: Pública | D12: 202.05922 | E12: 225.82414 | F12: 234.89139 | G12: 204.21807 | H12: 270.31204 | I12: 323.99253 | J12: 326.11377 | K12: 339.92761 | L12: =K12*(1+L29/100) -> 357.0187
C13: Variación de saldos | D13: 683.44407 | E13: 175.24233 | F13: 490.6719 | G13: -480.8862 | H13: 82.349342 | I13: 252.54843 | J13: 254.20191 | K13: 264.96964 | L13: =K13*(1+L30/100) -> 278.29195
C14: Saldo externo | D14: -463.29412 | E14: -195.84423 | F14: -688.20384 | G14: 148.11167 | H14: -299.6251 | I14: -617.35019 | J14: -680.52337 | K14: -772 | L14: =+L15-L16 -> -883.51291
C15: Exportaciones de bienes y servicios | D15: 5101.933 | E15: 5607.2954 | F15: 5494.3211 | G15: 5163.4984 | H15: 5417.1861 | I15: 5794.7038 | J15: 6291.922 | K15: 6523 | L15: =+K15*(1+L32/100) -> 6800.9293
C16: Importaciones de bienes y servicios | D16: 5565.2271 | E16: 5803.1396 | F16: 6182.525 | G16: 5015.3867 | H16: 5716.8112 | I16: 6412.054 | J16: 6972.4454 | K16: 7295 | L16: =+K16*(1+L33/100) -> 7684.4423
C17: Discrepancia estadística | D17: 47.846148 | E17: 45.04249 | F17: 17.922271 | G17: 51.988291 | H17: 13.704398 | I17: 36.53094 | J17: 33.303032 | K17: 0 | L17: =+K17*(1+L34/100) -> 0
C19: Producto potencial | D19: 9649.9079 | E19: 9961.0923 | F19: 10371.121 | G19: 10754.773 | H19: 11237.045 | I19: 11888.175 | J19: 12184.444 | K19: 12671.821 | L19: ='PIB real y brecha del producto'!F14 -> 13178.694
C22: Tasas de crecimiento
C23: PIB | D23: 8.8431346 | E23: 6.5277581 | F23: 2.4011889 | G23: -1.6305202 | H23: 4.8594958 | I23: 5.6553885 | J23: 4.185179 | K23: 4.557993 | L23: =(L6/K6-1)*100 -> 4.4517021
C24: Consumo final | D24: 5.4417978 | E24: 7.0386127 | F24: 3.3761643 | G24: 2.1973742 | H24: 4.5560134 | I24: 4.0451562 | J24: 5.6692565 | K24: 5.5971473 | L24: =(L7/K7-1)*100 -> 5.0193341
C25: Privado | D25: 5.7411312 | E25: 7.5164157 | F25: 3.4473142 | G25: 1.7063254 | H25: 4.575916 | I25: 4.6397309 | J25: 5.851938 | K25: 4.3786197 | L25: ='Cuadro PIB'!J11 -> 2.8936064
C26: Público | D26: 3.3176026 | E26: 3.5683867 | F26: 2.8397127 | G26: 5.92163 | H26: 4.4110735 | I26: -0.29164671 | J26: 4.2708835 | K26: 15.066047 | L26: ='Cuadro PIB'!J12 -> 20.003622
C27: Formación bruta de capital fijo | D27: 15.027749 | E27: -6.444647 | F27: 20.620534 | G27: -42.815372 | H27: 36.555287 | I27: 24.580465 | J27: 0.65471915 | K27: 4.2358972 | L27: =(L10/K10-1)*100 -> 5.0278602
C28: Privada | D28: 11.557973 | E28: 19.178863 | F28: 8.4563498 | G28: -10.736227 | H28: -1.4029552 | I28: 17.349832 | J28: 0.65471915 | K28: 4.2358972 | L28: ='Cuadro PIB'!J16 -> 5.0278602
C29: Pública | D29: 6.6221782 | E29: 11.761366 | F29: 4.015179 | G29: -13.058512 | H29: 32.36441 | I29: 19.858711 | J29: 0.65471915 | K29: 4.2358972 | L29: ='Cuadro PIB'!J17 -> 5.0278602
C30: Variación de saldos | D30: 27.696678 | E30: -74.358936 | F30: 179.99622 | G30: -198.00565 | H30: -117.1245 | I30: 206.67935 | J30: 0.65471915 | K30: 4.2358972 | L30: ='Cuadro PIB'!J18 -> 5.0278602
C31: Saldo externo | D31: … | E31: ... | F31: ... | G31: ... | H31: ... | I31: ... | J31: ... | K31: ... | L31: ...
C32: Exportaciones de bienes y servicios | D32: 10.278473 | E32: 9.9053129 | F32: -2.0147725 | G32: -6.0211766 | H32: 4.9130977 | I32: 6.9688892 | J32: 8.5805633 | K32: 3.6726139 | L32: ='Cuadro PIB'!J20 -> 4.2607596
C33: Importaciones de bienes y servicios | D33: 8.0920212 | E33: 4.2749835 | F33: 6.5375881 | G33: -18.87802 | H33: 13.985452 | I33: 12.161374 | J33: 8.7396552 | K33: 4.6261335 | L33: ='Cuadro PIB'!J22 -> 5.3384819
C34: Discrepancia estadística | D34: … | E34: ... | F34: -60.210301 | G34: 190.07647 | H34: -73.639452 | I34: 166.56362 | J34: -8.8360914 | K34: -100 | L34: ='Cuadro PIB'!J24 -> -100
C36: Producto potencial | D36: 4.7601995 | E36: 3.2247387 | F36: 4.1162981 | G36: 3.6992418 | H36: 4.4842567 | I36: 5.7944911 | J36: 2.4921336 | K36: 4 | L36: =L19/K19*100-100 -> 4
C39: Contribución al crecimiento del PIB
C40: Consumo final | D40: … | E40: 5.5130716 | F40: 2.6570995 | G40: 1.745837 | H40: 3.7606595 | I40: 3.3293202 | J40: 4.5949056 | K40: 4.6010816 | L40: =(L7-K7)/K6*100 -> 4.1671032
C41: Consumo privado | E41: 5.1748145 | F41: 2.3953934 | G41: 1.1977662 | H41: 3.3210532 | I41: 3.3582614 | J41: 4.1949461 | K41: 3.1890165 | L41: =(L8-K8)/K6*100 -> 2.1038429
C42: Consumo público | E42: 0.33825715 | F42: 0.26170613 | G42: 0.54807074 | H42: 0.43960632 | I42: -0.028941131 | J42: 0.39995952 | K42: 1.4120652 | L42: =(L9-K9)/K7*100 -> 2.4852259
C43: Formación bruta de capital fijo | D43: … | E43: -1.6682359 | F43: 4.6877461 | G43: -11.465161 | H43: 5.6904884 | I43: 4.9829921 | J43: 0.15649967 | K43: 0.97820981 | L43: =(L10-K10)/K6*100 -> 1.1575236
C44: Inversión privada | E44: 3.2428728 | F44: 1.5996554 | G44: -2.1510236 | H44: -0.25506575 | I44: 2.9659222 | J44: 0.12431123 | K44: 0.77701415 | L44: =(L11-K11)/K6*100 -> 0.91944716
C45: Inversión pública | E45: 0.24092332 | F45: 0.086288892 | G45: -0.28505942 | H45: 0.62441898 | I45: 0.48364079 | J45: 0.018088596 | K45: 0.11306376 | L45: =(L12-K12)/K6*100 -> 0.13378927
C46: Exportaciones de bienes y servicios | D46: … | E46: 5.1232476 | F46: -1.0751253 | G46: -3.0744683 | H46: 2.3967001 | I46: 3.401291 | J46: 4.239961 | K46: 1.8913308 | L46: =(L15-K15)/K6*100 -> 2.1756351
C47: Importaciones de bienes y servicios | D47: … | E47: -2.4119024 | F47: -3.6104405 | G47: 10.846683 | H47: -6.6266673 | I47: -6.2638732 | J47: -4.7786618 | K47: -2.6400501 | L47: =-(L16-K16)/K6*100 -> -3.0485597
C49: Brecha del producto
C50: Brecha del producto, en porcentaje del producto potencial | D50: 2.2196594 | E50: 5.4905179 | F50: 3.7527713 | G50: -1.579742 | H50: -1.2262808 | I50: -1.3561522 | J50: 0.27332419 | K50: 0.81132237 | L50: =(L6-L19)/L19*100 -> 1.2491751
A79: Tasa de interés real | L79: =(AVERAGE('Regla de Taylor '!D8:D8)-AVERAGE('Regla de Taylor '!F8:F8))/100 -> 0.027301901
A80: Delta r
A82: Precio de las exportaciones
A83: variación % | L83: =#REF! -> #REF!
A85: Precio de las importaciones
A86: variación % | L86: =#REF! -> #REF!
A88: Tipo de cambio real
L89: ='TC nominal'!H22 -> 99.26981
A92: r menos rbar | L92: =L79-L93 -> 0.017301901
A93: rbar | L93: 0.01

Sheet Deflactor_PIB
C2: Macronia: Deflactor del PIB, 2006-12
D3: 2006 | E3: 2007 | F3: 2008 | G3: 2009 | H3: 2010 | I3: 2011 | J3: 2012 | K3: 2013 | L3: 2014 | P3: 2012 | Q3: 2013 | R3: 2014
D4: (en miles de millones de moneda nacional) | P4: (tasa de crecimiento anual, porcentaje)
C5: Producto interno bruto por gasto, a precios corrientes
C6: PIB | D6: 10964.62 | E6: 12956.322 | F6: 14737.186 | G6: 15747.009 | H6: 17629.078 | I6: 19427.849 | J6: 21157.293 | K6: 23646.186 | L6: =PIB_Nominal!L6 -> 26705.763 | P6: =J6/I6-1 -> 0.089018811 | Q6: =K6/J6-1 -> 0.11763758 | R6: =L6/K6-1 -> 0.12938988
C7: Consumo final | D7: 8700.4437 | E7: 10352.871 | F7: 12200.565 | G7: 13108.591 | H7: 14576.657 | I7: 16016.788 | J7: 17760.343 | K7: 19985.487 | L7: =PIB_Nominal!L7 -> 22689.509 | P7: =J7/I7-1 -> 0.10885793 | Q7: =K7/J7-1 -> 0.12528725 | R7: =L7/K7-1 -> 0.13529925
C8: Privado | D8: 7624.2096 | E8: 9087.1639 | F8: 10645.097 | G8: 11176.638 | H8: 12277.757 | I8: 13520.438 | J8: 15027.228 | K8: 16647.635 | L8: =PIB_Nominal!L8 -> 18389.33 | P8: =J8/I8-1 -> 0.11144535 | Q8: =K8/J8-1 -> 0.10783137 | R8: =L8/K8-1 -> 0.1046212
C9: Público | D9: 1076.2341 | E9: 1265.7069 | F9: 1555.4684 | G9: 1931.9535 | H9: 2298.9 | I9: 2496.35 | J9: 2733.1145 | K9: 3337.8524 | L9: =PIB_Nominal!L9 -> 4300.1784 | P9: =J9/I9-1 -> 0.094844277 | Q9: =K9/J9-1 -> 0.22126328 | R9: =L9/K9-1 -> 0.28830691
C10: Formación bruta de capital fijo | D10: 2919.2115 | E10: 3202.1678 | F10: 4044.0793 | G10: 2463.1898 | H10: 3463.1683 | I10: 4287.2834 | J10: 4493.8592 | K10: 4957.11 | L10: =PIB_Nominal!L10 -> 5598.6359 | P10: =J10/I10-1 -> 0.048183377 | Q10: =K10/J10-1 -> 0.10308528 | R10: =L10/K10-1 -> 0.12941532
C11: Privada | D11: 1935.5708 | E11: 2523.1836 | F11: 3083.0458 | G11: 3105.0591 | H11: 2992.8914 | I11: 3513.9263 | J11: 3683.2391 | K11: 4062.9269 | L11: =PIB_Nominal!L11 -> 4588.7319 | P11: =J11/I11-1 -> 0.048183377 | Q11: =K11/J11-1 -> 0.10308528 | R11: =L11/K11-1 -> 0.12941532
C12: Pública | D12: 234.02446 | E12: 286.08395 | F12: 335.24812 | G12: 328.85775 | H12: 425.53619 | I12: 510.29972 | J12: 534.88768 | K12: 590.02673 | L12: =PIB_Nominal!L12 -> 666.38523 | P12: =J12/I12-1 -> 0.048183377 | Q12: =K12/J12-1 -> 0.10308528 | R12: =L12/K12-1 -> 0.12941532
C13: Variación de saldos | D13: 749.61619 | E13: 392.90029 | F13: 625.78538 | G13: -970.72705 | H13: 44.740729 | I13: 263.05738 | J13: 275.73238 | K13: 304.15633 | L13: =PIB_Nominal!L13 -> 343.51882 | P13: =J13/I13-1 -> 0.048183377 | Q13: =K13/J13-1 -> 0.10308528 | R13: =L13/K13-1 -> 0.12941532
C14: Saldo externo | D14: -708.14401 | E14: -653.40526 | F14: -1531.9167 | G14: 98.335101 | H14: -432.6394 | I14: -937.22061 | J14: -1096.9087 | K14: -1296.4112 | L14: =PIB_Nominal!L14 -> -1582.3815 | P14: =J14/I14-1 -> 0.17038476 | Q14: =K14/J14-1 -> 0.18187697 | R14: =L14/K14-1 -> 0.22058612
C15: Exportaciones de bienes y servicios | D15: 5658.5976 | E15: 6623.9268 | F15: 7134.1258 | G15: 7122.0184 | H15: 7248.1128 | I15: 7780.1097 | J15: 8683.1333 | K15: 9484.6174 | L15: =PIB_Nominal!L15 -> 10660.409 | P15: =J15/I15-1 -> 0.11606823 | Q15: =K15/J15-1 -> 0.092303554 | R15: =L15/K15-1 -> 0.12396825
C16: Importaciones de bienes y servicios | D16: 6366.7416 | E16: 7277.3321 | F16: 8666.0425 | G16: 7023.6833 | H16: 7680.7522 | I16: 8717.3303 | J16: 9780.042 | K16: 10781.029 | L16: =PIB_Nominal!L16 -> 12242.79 | P16: =J16/I16-1 -> 0.12190793 | Q16: =K16/J16-1 -> 0.10234992 | R16: =L16/K16-1 -> 0.13558648
C17: Discrepancia estadística | D17: 53.108978 | E17: 54.688654 | F17: 24.458182 | G17: 76.893057 | H17: 21.891565 | I17: 60.998131 | J17: 0 | K17: 0 | L17: =PIB_Nominal!L17 -> 0
D19: (en miles de millones de moneda nacional)
C20: Producto interno bruto por gasto, a precios constantes de 2005
C21: PIB | D21: 9864.103 | E21: 10508.008 | F21: 10760.325 | G21: 10584.876 | H21: 11099.247 | I21: 11726.953 | J21: 12217.747 | K21: 12774.631 | L21: =PIB_real!L6 -> 13343.319 | P21: =J21/I21-1 -> 0.04185179 | Q21: =K21/J21-1 -> 0.04557993 | R21: =L21/K21-1 -> 0.044517021
C22: Consumo final | D22: 7726.1683 | E22: 8269.9833 | F22: 8549.1915 | G22: 8737.0493 | H22: 9135.1104 | I22: 9504.6399 | J22: 10043.482 | K22: 10605.631 | L22: =PIB_real!L7 -> 11137.963 | P22: =J22/I22-1 -> 0.056692565 | Q22: =K22/J22-1 -> 0.055971473 | R22: =L22/K22-1 -> 0.050193341
C23: Privado | D23: 6791.1229 | E23: 7301.5719 | F23: 7553.2801 | G23: 7682.1636 | H23: 8033.693 | I23: 8406.4347 | J23: 8898.374 | K23: 9288 | L23: =PIB_real!L8 -> 9556.7582 | P23: =J23/I23-1 -> 0.05851938 | Q23: =K23/J23-1 -> 0.043786197 | R23: =L23/K23-1 -> 0.028936064
C24: Público | D24: 935.04534 | E24: 968.41137 | F24: 995.91147 | G24: 1054.8857 | H24: 1101.4174 | I24: 1098.2052 | J24: 1145.1083 | K24: 1317.6308 | L24: =PIB_real!L9 -> 1581.2047 | P24: =J24/I24-1 -> 0.042708835 | Q24: =K24/J24-1 -> 0.15066047 | R24: =L24/K24-1 -> 0.20003622
C25: Formación bruta de capital fijo | D25: 2553.3827 | E25: 2388.8262 | F25: 2881.415 | G25: 1647.7264 | H25: 2250.0575 | I25: 2803.1322 | J25: 2821.4848 | K25: 2941 | L25: =PIB_real!L10 -> 3088.8694 | P25: =J25/I25-1 -> 0.0065471915 | Q25: =K25/J25-1 -> 0.042358972 | R25: =L25/K25-1 -> 0.050278602
C26: Privada | D26: 1667.8795 | E26: 1987.7598 | F26: 2155.8517 | G26: 1924.3946 | H26: 1897.3962 | I26: 2226.5912 | J26: 2241.1691 | K26: 2336.1027 | L26: =PIB_real!L11 -> 2453.5587 | P26: =J26/I26-1 -> 0.0065471915 | Q26: =K26/J26-1 -> 0.042358972 | R26: =L26/K26-1 -> 0.050278602
C27: Pública | D27: 202.05922 | E27: 225.82414 | F27: 234.89139 | G27: 204.21807 | H27: 270.31204 | I27: 323.99253 | J27: 326.11377 | K27: 339.92761 | L27: =PIB_real!L12 -> 357.0187 | P27: =J27/I27-1 -> 0.0065471915 | Q27: =K27/J27-1 -> 0.042358972 | R27: =L27/K27-1 -> 0.050278602
C28: Variación de saldos | D28: 683.44407 | E28: 175.24233 | F28: 490.6719 | G28: -480.8862 | H28: 82.349342 | I28: 252.54843 | J28: 254.20191 | K28: 264.96964 | L28: =PIB_real!L13 -> 278.29195 | P28: =J28/I28-1 -> 0.0065471915 | Q28: =K28/J28-1 -> 0.042358972 | R28: =L28/K28-1 -> 0.050278602
C29: Saldo externo | D29: -463.29412 | E29: -195.84423 | F29: -688.20384 | G29: 148.11167 | H29: -299.6251 | I29: -617.35019 | J29: -680.52337 | K29: -772 | L29: =PIB_real!L14 -> -883.51291 | P29: =J29/I29-1 -> 0.10232958
C30: Exportaciones de bienes y servicios | D30: 5101.933 | E30: 5607.2954 | F30: 5494.3211 | G30: 5163.4984 | H30: 5417.1861 | I30: 5794.7038 | J30: 6291.922 | K30: 6523 | L30: =PIB_real!L15 -> 6800.9293 | P30: =J30/I30-1 -> 0.085805633 | Q30: =K30/J30-1 -> 0.036726139 | R30: =L30/K30-1 -> 0.042607596
C31: Importaciones de bienes y servicios | D31: 5565.2271 | E31: 5803.1396 | F31: 6182.525 | G31: 5015.3867 | H31: 5716.8112 | I31: 6412.054 | J31: 6972.4454 | K31: 7295 | L31: =PIB_real!L16 -> 7684.4423 | P31: =J31/I31-1 -> 0.087396552 | Q31: =K31/J31-1 -> 0.046261335 | R31: =L31/K31-1 -> 0.053384819
C32: Discrepancia estadística | D32: 47.846148 | E32: 45.04249 | F32: 17.922271 | G32: 51.988291 | H32: 13.704398 | I32: 36.53094 | J32: 33.303032 | K32: 0 | L32: =PIB_real!L17 -> 0
C34: Deflactor del PIB
C35: PIB | D35: 111.15679 | E35: 123.29951 | F35: 136.95856 | G35: 148.76896 | H35: 158.83129 | I35: 165.66835 | J35: 173.16854 | K35: 185.1027 | L35: =L6/L21*100 -> 200.14333 | P35: =J35/I35-1 -> 0.045272294 | Q35: =K35/J35-1 -> 0.068916443 | R35: =L35/K35-1 -> 0.081255598
C36: Consumo final | D36: 112.61007 | E36: 125.18611 | F36: 142.71016 | G36: 150.03453 | H36: 159.56739 | I36: 168.51547 | J36: 176.83451 | K36: 188.44223 | L36: =L7/L22*100 -> 203.71327 | P36: =J36/I36-1 -> 0.049366647 | Q36: =K36/J36-1 -> 0.06564171 | R36: =L36/K36-1 -> 0.081038324
C37: Privado | D37: 112.26729 | E37: 124.4549 | F37: 140.93343 | G37: 145.48815 | H37: 152.82831 | I37: 160.83439 | J37: 168.87611 | K37: 179.2381 | L37: =L8/L23*100 -> 192.42226 | P37: =J37/I37-1 -> 0.05 | Q37: =K37/J37-1 -> 0.061358513 | R37: =L37/K37-1 -> 0.073556692
C38: Público | D38: 115.09967 | E38: 130.6993 | F38: 156.18541 | G38: 183.1434 | H38: 208.72195 | I38: 227.3118 | J38: 238.67739 | K38: 253.32228 | L38: =L9/L24*100 -> 271.95583 | P38: =J38/I38-1 -> 0.05 | Q38: =K38/J38-1 -> 0.061358513 | R38: =L38/K38-1 -> 0.073556692
C39: Formación bruta de capital fijo | D39: 114.32722 | E39: 134.04775 | F39: 140.35046 | G39: 149.49021 | H39: 153.91465 | I39: 152.94617 | J39: 159.27285 | K39: 168.55185 | L39: =L10/L25*100 -> 181.25195 | P39: =J39/I39-1 -> 0.041365359 | Q39: =K39/J39-1 -> 0.058258539 | R39: =L39/K39-1 -> 0.075348309
C40: Privada | D40: 116.0498 | E40: 126.93604 | F40: 143.00825 | G40: 161.35252 | H40: 157.73677 | I40: 157.81641 | J40: 164.34454 | K40: 173.91902 | L40: =L11/L26*100 -> 187.02352 | P40: =J40/I40-1 -> 0.041365359 | Q40: =K40/J40-1 -> 0.058258539 | R40: =L40/K40-1 -> 0.075348309
C41: Pública | D41: 115.81974 | E41: 126.6844 | F41: 142.72474 | G41: 161.03264 | H41: 157.42406 | I41: 157.50355 | J41: 164.01874 | K41: 173.57423 | L41: =L12/L27*100 -> 186.65275 | P41: =J41/I41-1 -> 0.041365359 | Q41: =K41/J41-1 -> 0.058258539 | R41: =L41/K41-1 -> 0.075348309
C42: Variación de saldos | D42: 109.68216 | E42: 224.20398 | F42: 127.53642 | G42: 201.86212 | H42: 54.330402 | I42: 104.16116 | J42: 108.46983 | K42: 114.78912 | L42: =L13/L28*100 -> 123.43829 | P42: =J42/I42-1 -> 0.041365359 | Q42: =K42/J42-1 -> 0.058258539 | R42: =L42/K42-1 -> 0.075348309
C43: Saldo externo | D43: … | E43: ... | F43: ... | G43: ... | H43: ... | I43: ... | J43: ... | K43: ... | L43: ...
C44: Exportaciones de bienes y servicios | D44: 110.91086 | E44: 118.13051 | F44: 129.84545 | G44: 137.9301 | H44: 133.79848 | I44: 134.26242 | J44: 138.00447 | K44: 145.40269 | L44: =L15/L30*100 -> 156.74929 | P44: =J44/I44-1 -> 0.027871103 | Q44: =K44/J44-1 -> 0.053608578 | R44: =L44/K44-1 -> 0.078035735
C45: Importaciones de bienes y servicios | D45: 114.40219 | E45: 125.40336 | F45: 140.16995 | G45: 140.04271 | H45: 134.35378 | I45: 135.95223 | J45: 140.26703 | K45: 147.78655 | L45: =L16/L31*100 -> 159.31918 | P45: =J45/I45-1 -> 0.03173762 | Q45: =K45/J45-1 -> 0.053608578 | R45: =L45/K45-1 -> 0.078035735
C46: Discrepancia estadística | D46: … | E46: ... | F46: ... | G46: ... | H46: ... | I46: ... | J46: ... | K46: ... | L46: ...

Sheet BP
C2: Macronia: Balanza de pagos, 2006-13
D3: 2006 | E3: 2007 | F3: 2008 | G3: 2009 | H3: 2010 | I3: 2011 | J3: 2012 | K3: 2013 | L3: =1+K3 -> 2014
D4: (en millones dólares de EE.UU.)
C5: Cuenta corriente | D5: -1101.1511 | E5: -1372.9554 | F5: -2878.3333 | G5: -442.61129 | H5: -1302.5123 | I5: -2396.441 | J5: =J6+J9+J12+J17 -> -2724.3801 | K5: =K6+K9+K12+K17 -> -2959.8354 | L5: =L6+L9+L12+L17 -> -3329.4068
C6: Bienes | D6: -2727.1352 | E6: -2985.4503 | F6: -5013.3306 | G6: -2039.0602 | H6: -3439.6934 | I6: -5151.371 | J6: -5728.0786 | K6: -6194.2117 | L6: =L7-L8 -> -6755.0748
C7: Crédito | D7: 8101.7336 | E7: 9299.4773 | F7: 9555.3677 | G7: 8838.2254 | H7: 9516.2515 | I7: 10383.11 | J7: 11494.734 | K7: 12095.645 | L7: ='Import. y export. nominales'!M8 -> 12800.176
C8: Débito | D8: 10828.869 | E8: 12284.928 | F8: 14568.698 | G8: 10877.286 | H8: 12955.945 | I8: 15534.481 | J8: 17222.813 | K8: 18289.856 | L8: ='Import. y export. nominales'!M10 -> 19555.251
C9: Servicios | D9: 1351.0647 | E9: 1734.0675 | F9: 2200.9213 | G9: 2188.1006 | H9: 2537.2355 | I9: 3236.8748 | J9: 3580.602 | K9: 3749.1634 | L9: =L10-L11 -> 3945.1884
C10: Crédito | D10: 2971.6628 | E10: 3552.1823 | F10: 4083.3176 | G10: 3592.9105 | H10: 4319.9815 | I10: 4972.3539 | J10: 5504.6979 | K10: 5792.4672 | L10: =Servicios!I8 -> 6129.8593
C11: Débito | D11: 1620.5981 | E11: 1818.1148 | F11: 1882.3964 | G11: 1404.8099 | H11: 1782.7461 | I11: 1735.4792 | J11: 1924.0959 | K11: 2043.3038 | L11: =Servicios!I10 -> 2184.671
C12: Ingreso primario | D12: -74.180567 | E12: -591.2726 | F12: -508.22389 | G12: -950.4517 | H12: -766.5544 | I12: -804.8448 | J12: =J13-J15 -> -910.40435 | K12: =K13-K15 -> -857.69087 | L12: =L13-L15 -> -872.09248
C13: Crédito | D13: 705.91943 | E13: 703.4384 | F13: 617.81711 | G13: 253.4883 | H13: 316.8296 | I13: 272.3782 | J13: ='Ingreso primario'!G8 -> 173.86689 | K13: ='Ingreso primario'!H8 -> 184.98126 | L13: ='Ingreso primario'!I8 -> 170.57965
C14: del cual: renta de inversión | D14: 632.61943 | E14: 631.1384 | F14: 546.91711 | G14: 228.9883 | H14: 281.6296 | I14: 209.1782 | J14: ='Ingreso primario'!G9 -> 133.5245 | K14: ='Ingreso primario'!H9 -> 142.06 | L14: ='Ingreso primario'!I9 -> 131
C15: Débito | D15: 780.1 | E15: 1294.711 | F15: 1126.041 | G15: 1203.94 | H15: 1083.384 | I15: 1077.223 | J15: 1084.2712 | K15: 1042.6721 | L15: ='Ingreso primario'!H17 -> 1042.6721
C16: del cual: intereses | D16: 266.9 | E16: 438.2 | F16: 352.6 | G16: 308 | H16: 306.6 | I16: 284.1 | J16: 285.95886 | K16: 274.98777 | L16: ='Ingreso primario'!I18 -> 295.30314
C17: Ingreso secundario | D17: 349.1 | E17: 469.7 | F17: 442.3 | G17: 358.8 | H17: 366.5 | I17: 322.9 | J17: 333.50078 | K17: 342.90384 | L17: ='Ingreso secundario'!J6 -> 352.57201
C19: Cuenta de capital | D19: 1.1 | E19: 21.2 | F19: 7.4 | G19: 58.3 | H19: 53.6 | I19: 21.6 | J19: 37.513907 | K19: 9 | L19: 9
C21: Cuenta financiera: Préstamo neto (+)/endeudamiento neto (-) | D21: -1793.9 | E21: -2411.9 | F21: -2480.5 | G21: -676.9 | H21: -1800.2 | I21: -2518.9 | J21: -2684.7899 | K21: -2929.0456 | L21: =L22+L26+L33+L31 -> -3075.8603
C22: Inversión directa | D22: -1371 | E22: -1633.7 | F22: -2072.3 | G22: -1339 | H22: -1440.8 | I22: -2118.3 | J22: -1844.0043 | K22: -1985.4075 | L22: =(K22/K57)*L57 -> -2111.1857
C23: Adquisición neta de activos | D23: 98.1 | E23: 262.4 | F23: 5.9 | G23: 7.5 | H23: 24.8 | I23: 57.8 | J23: 505.44391 | K23: 544.20272 | L23: =K23/K$57*L$57 -> 578.67868
C24: Incurrimiento neto de pasivos | D24: 1469.1 | E24: 1896.1 | F24: 2078.2 | G24: 1346.5 | H24: 1465.6 | I24: 2176.1 | J24: 2349.4482 | K24: 2529.6102 | L24: =K24/K$57*L$57 -> 2689.8644
C26: Inversión de cartera | D26: 442.1 | E26: -11.6 | F26: -356.6 | G26: 276.1 | H26: -268.1 | I26: -261.4 | J26: -784.86019 | K26: -781.82486 | L26: =L27-L28 -> -792.61027
C27: Adquisición neta de activos | D27: 509.3 | E27: 170.4 | F27: -537.3 | G27: 321.7 | H27: -218.6 | I27: -258.9 | J27: 0 | K27: 0 | L27: 0
C28: Incurrimiento neto de pasivos | D28: 67.2 | E28: 182 | F28: -180.7 | G28: 45.6 | H28: 49.5 | I28: 2.5 | J28: 784.86019 | K28: 781.82486 | L28: =L29+L30 -> 792.61027
C29: Gobierno general | F29: -238.6 | G29: 101.7 | H29: 117.8 | I29: -207.7 | J29: 557.86019 | K29: 537.41788 | L29: =Gob_EOG!L47/'TC nominal'!I13*1000 -> 532.71979
C30: Otros (neto) | F30: 57.9 | G30: -56.1 | H30: -68.3 | I30: 210.2 | J30: 227 | K30: 244.40698 | L30: =(K30/K57)*L57 -> 259.89048
C31: Derivados financieros | D31: -25 | E31: 50 | F31: -19 | G31: 18 | H31: 78 | I31: 69 | J31: 74.496542 | K31: 80.209139 | L31: =K31/K$57*L$57 -> 85.290494
C33: Otra inversión | D33: -840 | E33: -816.6 | F33: -32.6 | G33: 368 | H33: -169.3 | I33: -208.2 | J33: -130.42202 | K33: -242.02236 | L33: =L34-L35 -> -257.35479
C34: Adquisición neta de activos | D34: -474.6 | E34: 155.8 | F34: 684.6 | G34: -332.2 | H34: 376.5 | I34: 214 | J34: 231.04725 | K34: 248.76457 | L34: =K34/K$57*L$57 -> 264.52414
C35: Incurrimiento neto de pasivos | D35: 365.4 | E35: 972.4 | F35: 717.2 | G35: -700.2 | H35: 545.8 | I35: 422.2 | J35: 455.83246 | K35: 490.78693 | L35: =K35/K$57*L$57 -> 521.87893
C36: del cual: otras sociedades de depósito | I36: 168.88 | J36: 182.33298 | K36: 294.47216 | L36: =0.4*L35 -> 208.75157
C37: del cual: gobierno general | D37: -52.9 | E37: -55.3 | F37: -43.2 | G37: -22.3 | H37: 477.6 | I37: 18.5 | J37: 0 | K37: 0 | L37: 0
C39: Errores y omisiones netos | D39: 56.951079 | E39: -42.444576 | F39: 42.433273 | G39: -32.688705 | H39: 9.8123142 | I39: -11.659001 | J39: 53.59964 | K39: 0 | L39: 0
C41: Saldo global | D41: 750.8 | E41: 1017.7 | F41: -348 | G41: 259.9 | H41: 561.1 | I41: 132.4 | J41: =J5+J19-J21+J39 -> 51.523344 | K41: =K5+K19-K21+K39 -> -21.789759 | L41: =L5+L19-L21+L39 -> -244.54656
C43: Activos de reserva (- = disminución) | D43: 750.8 | E43: 1017.7 | F43: -348 | G43: 259.9 | H43: 561.1 | I43: 132.4 | J43: =J41 -> 51.523344 | K43: =K41 -> -21.789759 | L43: =L41+L44 -> -244.54656
C44: Financiamiento del FMI
D45: (en porcentaje del PIB, salvo indicación en contrario)
C46: Indicadores económicos seleccionados | D46: 2006 | E46: 2007 | F46: 2008 | G46: 2009 | H46: 2010 | I46: 2011 | J46: 2012 | K46: 2013 | L46: =1+K46 -> 2014
C47: Saldo en cuenta corriente | D47: -5.1348842 | E47: -5.4744907 | F47: -10.277954 | G47: -1.6113773 | H47: -3.8850529 | I47: -6.2464852 | J47: =J5/J57*100 -> -6.5773304 | K47: =K5/K57*100 -> -6.6368464 | L47: =L5/L57*100 -> -7.0207629
C48: Saldo en cuenta de capital | D48: 0.0051295165 | E48: 0.08453239 | F48: 0.026423924 | G48: 0.21224785 | H48: 0.15987476 | I48: 0.056301858 | J48: 0.09056789 | K48: 0.021728236 | L48: =L19/$L$57*100 -> 0.018978415
C49: Saldo en cuenta financiera | D49: -8.3653088 | E49: -9.6171543 | F49: -8.8573707 | G49: -2.4643322 | H49: -5.3695249 | I49: -6.5656829 | J49: -6.4817498 | K49: -7.0714437 | L49: =L21/L57*100 -> -6.486106
C50: Saldo global | D50: 3.5011282 | E50: 4.0579535 | F50: -1.2426386 | G50: 0.94619581 | H50: 1.6736143 | I50: 0.34510954 | J50: 0.12064388 | K50: -0.070565562 | L50: =L41/L57*100 -> -0.51567847
C51: Activos de reserva (millones de dólares de EE.UU.) | F51: 3798.7 | G51: 4066.2 | H51: 4629.7 | I51: 4758.3 | J51: 4808.2716 | K51: 4779.0428 | L51: =PII!L13 -> 4534.4963
C52: Activos de reserva (en meses de importaciones de bienes y servicios) | F52: 2.7709037 | G52: 3.9728074 | H52: 3.7694257 | I52: 3.3062959 | J52: 3.0135026 | K52: 2.8204427 | L52: =L51/((L8+L11)/12) -> 2.5029508 | O52: Activos de reserva /((débito bienes + débito servicios)/12)
C55: Partida informativa
C56: PIB nominal en miles de millones de moneda local | D56: 10964.62 | E56: 12956.322 | F56: 14737.186 | G56: 15747.009 | H56: 17629.078 | I56: 19427.849 | J56: 21157.293 | K56: 23646.186 | L56: =PIB_Nominal!L6 -> 26705.763 | N56: =N57*L58/1000 -> 26943.757
C57: PIB nominal en miles de millones de dólares de EE.UU. | D57: 21444.516 | E57: 25079.144 | F57: 28004.925 | G57: 27467.887 | H57: 33526.244 | I57: 38364.631 | J57: 41420.758 | K57: 44597.015 | L57: =L56/L58*1000 -> 47422.294 | N57: =K57/K22*-2130 -> 47844.909
C58: Tipo de cambio, MN por USD, promedio del período | D58: 511.30182 | E58: 516.61739 | F58: 526.23551 | G58: 573.28796 | H58: 525.8292 | I58: 506.4 | J58: 510.78961 | K58: 530.21903 | L58: ='TC nominal'!I13 -> 563.14785
C59: Tipo de cambio, MN por USD, fin del período | D59: 517.895 | E59: 498.1 | F59: 555.47 | G59: 565.24 | H59: 512.97 | I59: 510.56 | J59: 511.01923 | K59: 549.41884 | L59: ='TC nominal'!I14 -> 576.87685
C60: balanza comercial (en millones dólares de EE.UU.) | D60: -1376.0705 | E60: -1251.3828 | F60: -2812.4094 | G60: 149.04041 | H60: -902.45791 | I60: -1914.4962 | J60: -2147.4766 | K60: -2445.0483 | L60: =L6+L9 -> -2809.8864
C61: balanza comercial (en millones porcentaje del PIB) | D61: -6.4168876 | E61: -4.9897349 | F61: -10.042553 | G61: 0.54259872 | H61: -2.6917955 | I61: -4.9902636 | J61: -5.1845419 | K61: -5.4825381 | L61: =100*(L60/L57) -> -5.9252434
D63: 2006 | E63: 2007 | F63: 2008 | G63: 2009 | H63: 2010 | I63: 2011 | J63: 2012 | K63: 2013 | L63: =1+K63 -> 2014
C64: Exportaciones/PIB (porcentaje) | D64: 51.637427 | E64: 51.244411 | F64: 48.701025 | G64: 45.256978 | H64: 41.269858 | I64: 40.025054 | J64: 41.040852 | K64: 40.110559 | L64: =100*(L7+L10)/L57 -> 39.918008
C65: Importaciones/PIB (porcentaje) | D65: 58.054314 | E65: 56.234145 | F65: 58.743578 | G65: 44.71438 | H65: 43.961653 | I65: 45.015318 | J65: 46.225393 | K65: 45.593097 | L65: =100*(L8+L11)/L57 -> 45.843252
C66: Apertura | D66: 109.69174 | E66: 107.47856 | F66: 107.4446 | G66: 89.971358 | H66: 85.231511 | I66: 85.040372 | J66: 87.266245 | K66: 85.703656 | L66: =L64+L65 -> 85.76126
C68: exports (in BN LC) | F68: 7134.1258 | G68: 7122.0184 | H68: 7248.1128 | I68: 7780.1097 | J68: 8683.1333 | K68: 9484.6174 | L68: =PIB_Nominal!L15 -> 10660.409
C69: imports (in bn LC) | F69: 8666.0425 | G69: 7023.6833 | H69: 7680.7522 | I69: 8717.3303 | J69: 9780.042 | K69: 10781.029 | L69: =PIB_Nominal!L16 -> 12242.79
C71: exports (in mn $) | F71: 13638.685 | G71: 12431.136 | H71: 13836.233 | I71: 15355.464 | J71: 16999.432 | K71: 17888.112 | L71: =L7+L10 -> 18930.036
C72: imports (in mn $) | F72: 16451.095 | G72: 12282.095 | H72: 14738.691 | I72: 17269.961 | J72: 19146.909 | K72: 20333.16 | L72: =L8+L11 -> 21739.922
C74: implicit exports( $* average ER) | F74: 13556.907 | G74: 12423.108 | H74: 13784.158 | I74: 15363.566 | J74: 16999.432 | K74: 17888.112 | L74: =L68/L$58*1000 -> 18930.036
C75: implicit imports ( $* average ER) | F75: 16467.992 | G75: 12251.58 | H75: 14606.934 | I75: 17214.317 | J75: 19146.909 | K75: 20333.16 | L75: =L69/L$58*1000 -> 21739.922

Sheet PII
B2: Macronia: Posición de inversión internacional, 2006-2012
D3: 2006 | E3: 2007 | F3: 2008 | G3: 2009 | H3: 2010 | I3: 2011 | J3: 2012 | K3: 2013 | L3: 2014
B4: (en millones dólares de EE.UU.)
C5: Posición de inversión internacional neta | D5: -3563.8 | E5: -4969.8 | F5: -7774.2 | G5: -8174.6 | H5: -9410.3 | I5: -11800.6 | J5: -14565.561 | K5: =K7-K15 -> -17508.076 | L5: =L7-L15 -> -21093.007
C7: Activos | D7: 10162.9 | E7: 11795.4 | F7: 11617.7 | G7: 11915.2 | H7: 12732.4 | I7: 12928.9 | J7: =J8+J9+J10+J11+J13 -> 13775.632 | K7: =K8+K9+K10+K11+K13 -> 14633.787 | L7: =L8+L9+L10+L11+L13 -> 15053.21
C8: Inversiones directas en el exterior | D8: 1268 | E8: 1530.4 | F8: 1536.3 | G8: 1543.8 | H8: 1568.6 | I8: 1626.4 | J8: =I8+BP!J23 -> 2131.8439 | K8: =J8+BP!K23 -> 2676.0466 | L8: =K8+BP!L23 -> 3254.7253
C9: Inversiones de cartera | D9: 1317.9 | E9: 1488.2 | F9: 950.9 | G9: 1275.6 | H9: 1055 | I9: 796.1 | J9: 796.1 | K9: =J9+BP!K27 -> 796.1 | L9: =K9+BP!L27 -> 796.1
C10: Derivados financieros | D10: 351 | E10: 391 | F10: 379 | G10: 402 | H10: 472 | I10: 527 | J10: 568 | K10: =J10+BP!K31 -> 648.20914 | L10: =K10+BP!L31 -> 733.49963
C11: Otras inversiones | D11: 4111.4 | E11: 4272.2 | F11: 4952.8 | G11: 4627.6 | H11: 5007.1 | I11: 5221.1 | J11: 5469.8646 | K11: =J11+BP!L34 -> 5734.3887 | L11: =K11+BP!M34 -> 5734.3887
C12: de las cuales: dinero y depósitos de sociedades de depósito | D12: 656.69085 | E12: 523.13441 | F12: 1153.0422 | G12: 742.75689 | H12: 802.74399 | I12: 795.48962 | J12: … | K12: ... | L12: ...
C13: Activos de reserva | D13: 3114.6 | E13: 4113.6 | F13: 3798.7 | G13: 4066.2 | H13: 4629.7 | I13: 4758.3 | J13: =I13+BP!J43 -> 4809.8233 | K13: 4779.0428 | L13: =K13+BP!L43 -> 4534.4963
C15: Pasivos | D15: 13726.7 | E15: 16765.2 | F15: 19391.9 | G15: 20089.8 | H15: 22142.7 | I15: 24729.5 | J15: 28339.641 | K15: =K16+K19+K23+K24 -> 32141.863 | L15: =L16+L19+L23+L24 -> 36146.216
C16: Inversiones directas | D16: 6906.2 | E16: 8800.3 | F16: 10878.5 | G16: 12226 | H16: 13691.6 | I16: 15867.7 | J16: 18217.148 | K16: 20746.758 | L16: =K16+BP!L24 -> 23436.623
C17: Participaciones de capital y participaciones en fondos de inversión | D17: 6148.8 | E17: 8045.1 | F17: 10084.7 | G17: 11606.7 | H17: 12922.6 | I17: 14388 | J17: 16737.448 | K17: 19267.058 | L17: =L16-L18 -> 21956.923
C18: Títulos de deuda | D18: 757.4 | E18: 755.2 | F18: 793.8 | G18: 619.3 | H18: 769 | I18: 1479.7 | J18: 1479.7 | K18: 1479.7 | L18: =K18 -> 1479.7
C19: Inversiones de cartera | D19: 1177.4 | E19: 1359.4 | F19: 1183.7 | G19: 1229.3 | H19: 1278.8 | I19: 1281.3 | J19: 2066.1602 | K19: 2847.985 | L19: =K19+BP!L28 -> 3640.5953
C20: Participaciones de capital y participaciones en fondos de inversión | D20: 201 | E20: 213 | F20: 168 | G20: 178 | H20: 173 | I20: 171 | J20: 398 | K20: 642.40698 | L20: =L19-L21 -> 902.29746
C21: Títulos de deuda | D21: 976.4 | E21: 1146.4 | F21: 1015.7 | G21: 1051.3 | H21: 1105.8 | I21: 1110.3 | J21: 1668.1602 | K21: 2205.5781 | L21: =L22+(K21-K22) -> 2738.2979
C22: de los cuales: Bonos del gobierno general | D22: 966 | E22: 1122.1 | F22: 883.5 | G22: 985.2 | H22: 1103 | I22: 895.3 | J22: 1453.1602 | K22: 1990.5781 | L22: =K22+BP!L29 -> 2523.2979
C23: Derivados financieros | D23: 102 | E23: 92 | F23: 99 | G23: 104 | H23: 96 | I23: 82 | J23: 102 | K23: 102 | L23: =K23 -> 102
C24: Otras inversiones | D24: 5541.1 | E24: 6513.5 | F24: 7230.7 | G24: 6530.5 | H24: 7076.3 | I24: 7498.5 | J24: 7954.3325 | K24: 8445.1194 | L24: =K24+BP!L35 -> 8966.9983
C25: de las cuales: instrumentos de deuda | D25: 5512.2 | E25: 6464.6 | F25: 7154.8 | G25: 6208.2 | H25: 6757 | I25: 7174.2 | J25: 7088.2938 | K25: 7382.766 | L25: =SUM(L26:L29) -> 7591.5176
C26: Banco central | D26: 94 | E26: 88.9 | F26: 80.6 | G26: 58 | H26: 53.5 | I26: 303.8 | J26: 35.560839 | K26: 35.560839 | L26: =K26 -> 35.560839
C27: Otras sociedades de depósito | D27: 1160.1 | E27: 1693.8 | F27: 2400 | G27: 1582.6 | H27: 1616.3 | I27: 2337.4 | J27: 2519.733 | K27: 2814.2051 | L27: =K27+BP!L36 -> 3022.9567
C28: Gobierno general | D28: 564.5 | E28: 509.2 | F28: 466 | G28: 443.7 | H28: 921.3 | I28: 939.8 | J28: 939.8 | K28: 939.8 | L28: =K28 -> 939.8
C29: Otros sectores | D29: 3693.6 | E29: 4172.7 | F29: 4208.2 | G29: 4123.9 | H29: 4165.9 | I29: 3593.2 | J29: 3593.2 | K29: 3593.2 | L29: =K29 -> 3593.2
B31: (en porcentaje del PIB, salvo indicación en contrario)
C32: Indicadores de saldos
C33: Posición de inversión internacional neta | D33: -16.618701 | E33: -19.816466 | F33: -27.760117 | G33: -29.760571 | H33: -28.068459 | I33: -30.75906 | J33: -35.164882 | K33: -39.253025 | L33: =L5/L38*100 -> -44.479093
C34: Activos | D34: 47.391603 | E34: 47.032705 | F34: 41.484489 | G34: 43.378655 | H34: 37.977413 | I34: 33.70005 | J34: 33.254051 | K34: 32.818757 | L34: =L7/L38*100 -> 31.742897
C35: Pasivos | D35: 64.010304 | E35: 66.849171 | F35: 69.244607 | G35: 73.139225 | H35: 66.045872 | I35: 64.459111 | J35: 68.418933 | K35: 72.071781 | L35: =L15/L38*100 -> 76.22199
C37: Partidas informativas
C38: PIB nominal, en millones de dólares de EE.UU. | D38: 21444.516 | E38: 25079.144 | F38: 28004.925 | G38: 27467.887 | H38: 33526.244 | I38: 38364.631 | J38: 41420.758 | K38: 44597.015 | L38: =BP!L57 -> 47422.294

Sheet Deuda_EX
B2: Macronia: Deuda externa, 2006-12
D3: 2006 | E3: 2007 | F3: 2008 | G3: 2009 | H3: 2010 | I3: 2011 | J3: 2012 | K3: 2013 | L3: 2014
D4: (en millones dólares de EE.UU.)
C5: Deuda externa total | D5: 7246 | E5: 8366.2 | F5: 8964.3 | G5: 7878.8 | H5: 8631.8 | I5: 9764.2 | J5: 10236.154 | K5: 11068.044 | L5: =SUM(L6:L10) -> 11809.515
C6: Gobierno general | D6: 1530.5 | E6: 1631.3 | F6: 1349.5 | G6: 1428.9 | H6: 2024.3 | I6: 1835.1 | J6: 2392.9602 | K6: 2930.3781 | L6: =PII!L22+PII!L28 -> 3463.0979
C7: Banco central | D7: 94 | E7: 88.9 | F7: 80.6 | G7: 58 | H7: 53.5 | I7: 303.8 | J7: 35.560839 | K7: 35.560839 | L7: =PII!L26 -> 35.560839
C8: Otras sociedades de depósito | D8: 1165.3 | E8: 1705.95 | F8: 2466.1 | G8: 1615.65 | H8: 1617.7 | I8: 2444.9 | J8: 2627.233 | K8: 2921.7051 | L8: =PII!L27+(PII!L21-PII!L22)/2 -> 3130.4567
C9: Otros sectores | D9: 3698.8 | E9: 4184.85 | F9: 4274.3 | G9: 4156.95 | H9: 4167.3 | I9: 3700.7 | J9: 3700.7 | K9: 3700.7 | L9: =PII!L29+(PII!L$21-PII!L$22)/2 -> 3700.7
C10: Deuda externa clasificada como inversiones directas | D10: 757.4 | E10: 755.2 | F10: 793.8 | G10: 619.3 | H10: 769 | I10: 1479.7 | J10: 1479.7 | K10: 1479.7 | L10: =PII!L18 -> 1479.7
C12: Total a corto plazo | D12: 2411.8231 | E12: 3093.5913 | F12: 3625.43 | G12: 2290.0028 | H12: 2204.6133 | I12: 1709.1779 | J12: 2556.0993 | K12: 2763.833 | L12: =(K12/K5)*L5 -> 2948.9879
C13: Total a largo plazo | D13: 4834.1769 | E13: 5272.6087 | F13: 5338.87 | G13: 5588.7972 | H13: 6427.1867 | I13: 8055.0221 | J13: 7680.0547 | K13: 8304.2111 | L13: =L5-L12 -> 8860.5275
C14: Deuda a corto plazo en el vencimiento residual | D14: 2918.5548 | E14: 4124.6838 | F14: 4265.6503 | G14: 2924.2015 | H14: 3185.0316 | I14: 2757.4122 | J14: … | K14: ... | L14: ...
C16: Check with IIP
C17: Total debt from IIP | D17: 7246 | E17: 8366.2 | F17: 8964.3 | G17: 7878.8 | H17: 8631.8 | I17: 9764.2 | J17: 3147.8602 | K17: 11068.044 | L17: =PII!L18+PII!L21+PII!L25 -> 11809.515
C18: General government debt, from IIP | D18: 1530.5 | E18: 1631.3 | F18: 1349.5 | G18: 1428.9 | H18: 2024.3 | I18: 1835.1 | J18: 2392.9602 | K18: 2930.3781 | L18: =PII!L22+PII!L28 -> 3463.0979
C20: Memorandum items
C21: Total disbursements long term | D21: 705.88846 | E21: 945.16354 | F21: 1097.3538 | G21: 890.14756 | H21: 1472.5882 | I21: 2608.2537 | J21: 673.26685 | K21: 624.1564 | L21: =L13-K13+L22 -> 556.31642
C22: Total amortization long term | D22: 612.2681 | E22: 506.73175 | F22: 1031.0925 | G22: 640.2203 | H22: 634.19879 | I22: 980.41828 | J22: 1048.2343
C23: Relación deuda a corto plazo/a largo plazo | D23: 49.89108 | E23: 58.672878 | F23: 67.906318 | G23: 40.974876 | H23: 34.301373 | I23: 21.218786 | J23: 33.282306 | K23: 33.282306 | L23: =100*L12/L13 -> 33.282306

Sheet EX_Stock_Ind
B2: Macronia: Indicadores de saldos y de la deuda, 2006-12
D3: 2006 | E3: 2007 | F3: 2008 | G3: 2009 | H3: 2010 | I3: 2011 | J3: 2012 | K3: 2013 | L3: 2014
B4: (en porcentaje, salvo indicación en contrario)
C5: Indicadores de saldos
C6: PII neta/PIB | D6: -16.618701 | E6: -19.816466 | F6: -27.760117 | G6: -29.760571 | H6: -28.068459 | I6: -30.75906 | J6: -35.164882 | K6: -39.253025 | L6: =L30/L23*100 -> -44.479093
C7: Activos/PIB | D7: 47.391603 | E7: 47.032705 | F7: 41.484489 | G7: 43.378655 | H7: 37.977413 | I7: 33.70005 | J7: 33.254051 | K7: 32.818757 | L7: =L31/L23*100 -> 31.742897
C8: Pasivos/PIB | D8: 64.010304 | E8: 66.849171 | F8: 69.244607 | G8: 73.139225 | H8: 66.045872 | I8: 64.459111 | J8: 68.418933 | K8: 72.071781 | L8: =L33/L23*100 -> 76.22199
C9: Deuda/PIB | D9: 33.789524 | E9: 33.359193 | F9: 32.009727 | G9: 28.683677 | H9: 25.746398 | I9: 25.451046 | J9: 24.712618 | K9: 24.817904 | L9: =L34/L23*100 -> 24.902876
C10: Deuda/exportaciones de bienes y servicios. | D10: 65.436111 | E10: 65.098207 | F10: 65.72701 | G10: 63.379566 | H10: 62.385477 | I10: 63.587787 | J10: 60.214682 | K10: 61.873741 | L10: =L34/L24*100 -> 62.385067
C11: Servicio de la deuda/PIB | D11: 4.0997339 | E11: 3.767799 | F11: 4.9408899 | G11: 3.452105 | H11: 2.8061563 | I11: 3.2960522 | J11: 3.2210736 | K11: 3.1580854 | L11: =L29/L23*100 -> 3.1728908
C12: Servicio de la deuda/exportaciones de bienes y servicios. | D12: 7.939462 | E12: 7.3526049 | F12: 10.145351 | G12: 7.6277849 | H12: 6.7995298 | I12: 8.2349726 | J12: 7.8484571 | K12: 7.8734515 | L12: =L29/L24*100 -> 7.9485198
C13: Reservas, en meses de importaciones de bienes y servicios | D13: 2.6501516 | E13: 3.0006027 | F13: 3.7114514 | G13: 3.3106332 | H13: 3.2169384 | I13: 2.9821838 | J13: 2.8376927 | K13: 2.6258452 | L13: =L32/(L25/12) -> 2.5029508
C14: Reservas/deuda a corto plazo en el venc. res. | D14: 106.7172 | E14: 99.731282 | F14: 89.053244 | G14: 139.05334 | H14: 145.35806 | I14: 172.56397 | J14: … | K14: ... | L14: ...
C16: Otros indicadores
C17: Tasa de interés implícita promedio de la deuda externa | D17: … | E17: 5.6135586 | F17: 4.0691267 | G17: 3.657284 | H17: 3.7139777 | I17: 3.0887149 | J17: 2.859538 | K17: 2.581536
C18: Vencimiento medio implícito de la deuda externa a largo plazo | D18: … | E18: 9.5399132 | F18: 5.1136137 | G18: 8.3391138 | H18: 8.8123745 | I18: 6.5555557 | J18: 7.684372 | K18: 6.7759765
C19: Tasa de refinanciamiento, deuda a largo plazo | D19: 115.29075 | E19: 186.52148 | F19: 106.42632 | G19: 139.0377 | H19: 232.19663 | I19: 266.03479 | J19: 64.228662 | K19: 173.39619
B21: (en millones dólares de EE.UU.)
C22: Partidas informativas
C23: PIB nominal, en millones de dólares de EE.UU. | D23: 21444.516 | E23: 25079.144 | F23: 28004.925 | G23: 27467.887 | H23: 33526.244 | I23: 38364.631 | J23: 41420.758 | K23: 44597.015 | L23: =IF(ISBLANK(BP!L57)," ",BP!L57) -> 47422.294
C24: Exportaciones de bienes y servicios, de la BP | D24: 11073.396 | E24: 12851.66 | F24: 13638.685 | G24: 12431.136 | H24: 13836.233 | I24: 15355.464 | J24: 16999.432 | K24: 17888.112 | L24: =BP!L7+BP!L10 -> 18930.036
C25: Importaciones de bienes y servicios, de la BP | D25: 12449.467 | E25: 14103.042 | F25: 16451.095 | G25: 12282.095 | H25: 14738.691 | I25: 17269.961 | J25: 19146.909 | K25: 20333.16 | L25: =BP!L8+BP!L11 -> 21739.922
C26: Pagos de intereses, de la BP | D26: 266.9 | E26: 438.2 | F26: 352.6 | G26: 308 | H26: 306.6 | I26: 284.1 | J26: 285.95886 | K26: 274.98777 | L26: =BP!L16 -> 295.30314
C27: Desembolso total a largo plazo | D27: 705.88846 | E27: 945.16354 | F27: 1097.3538 | G27: 890.14756 | H27: 1472.5882 | I27: 2608.2537 | J27: 673.26685 | K27: 1965.3141 | L27: =L28+L34-K34 -> 1950.8258
C28: Amortización total a largo plazo | D28: 612.2681 | E28: 506.73175 | F28: 1031.0925 | G28: 640.2203 | H28: 634.19879 | I28: 980.41828 | J28: 1048.2343 | K28: 1133.424 | L28: =K28/K34*L34 -> 1209.3545
C29: Servicio de la deuda total | D29: 879.1681 | E29: 944.93175 | F29: 1383.6925 | G29: 948.2203 | H29: 940.79879 | I29: 1264.5183 | J29: 1334.1931 | K29: 1408.4118 | L29: =L26+L28 -> 1504.6576
C30: Posición de inversión internacional neta | D30: -3563.8 | E30: -4969.8 | F30: -7774.2 | G30: -8174.6 | H30: -9410.3 | I30: -11800.6 | J30: -14565.561 | K30: -17505.677 | L30: =PII!L5 -> -21093.007
C31: Activos | D31: 10162.9 | E31: 11795.4 | F31: 11617.7 | G31: 11915.2 | H31: 12732.4 | I31: 12928.9 | J31: 13774.08 | K31: 14636.186 | L31: =PII!L7 -> 15053.21
C32: Activos de reserva | D32: 3114.6 | E32: 4113.6 | F32: 3798.7 | G32: 4066.2 | H32: 4629.7 | I32: 4758.3 | J32: 4808.2716 | K32: 4779.0428 | L32: =PII!L13 -> 4534.4963
C33: Pasivos | D33: 13726.7 | E33: 16765.2 | F33: 19391.9 | G33: 20089.8 | H33: 22142.7 | I33: 24729.5 | J33: 28339.641 | K33: 32141.863 | L33: =PII!L15 -> 36146.216
C34: Deuda externa total | D34: 7246 | E34: 8366.2 | F34: 8964.3 | G34: 7878.8 | H34: 8631.8 | I34: 9764.2 | J34: 10236.154 | K34: 11068.044 | L34: =Deuda_EX!L5 -> 11809.515
C35: Deuda externa a largo plazo total | D35: 4834.1769 | E35: 5272.6087 | F35: 5338.87 | G35: 5588.7972 | H35: 6427.1867 | I35: 8055.0221 | J35: 7680.0547 | K35: 8304.2111 | L35: =Deuda_EX!L13 -> 8860.5275
C36: Deuda a corto plazo en el vencimiento residual | D36: 2918.5548 | E36: 4124.6838 | F36: 4265.6503 | G36: 2924.2015 | H36: 3185.0316 | I36: 2757.4122 | J36: …

Sheet PIB real y brecha del producto
B2: RY | C2: PIB real (miles de millones de moneda nacional, precios de 2005)
B3: TENDENCIA | C3: Tendencia de tiempo (=1 en 1970, 2 en 1971, etc.)
B4: Macronia: Pronóstico del PIB real usando tasa de crecimiento tendencial estimada
B5: Año | C5: RY | D5: Crecimiento % RY | E5: Crecimiento tendencial aplicado al año previo | F5: Producto potencial (informe WEO) | G5: Brecha del producto (en %) | K5: Producto de regresión tendencial
B6: 2006 | C6: 9864.103 | D6: 8.8431346 | F6: =PIB_real!D$19 -> 9649.9079 | G6: =((C6-F6)/F6)*100 -> 2.2196594 | J6: Ln(RY)= 7,674 + 0,040*(tendencia)
B7: =B6+1 -> 2007 | C7: 10508.008 | D7: =(C7/C6-1)*100 -> 6.5277581 | E7: =C6*(1+$L$10) -> 10258.667 | F7: =PIB_real!E$19 -> 9961.0923 | G7: =((C7-F7)/F7)*100 -> 5.4905179 | J7: R2 = 0,988
B8: =B7+1 -> 2008 | C8: 10760.325 | D8: =(C8/C7-1)*100 -> 2.4011889 | E8: =C7*(1+$L$10) -> 10928.328 | F8: =PIB_real!F$19 -> 10371.121 | G8: =((C8-F8)/F8)*100 -> 3.7527713 | J8: obs: 43
B9: =B8+1 -> 2009 | C9: 10584.876 | D9: =(C9/C8-1)*100 -> -1.6305202 | E9: =C8*(1+$L$10) -> 11190.738 | F9: =PIB_real!G$19 -> 10754.773 | G9: =((C9-F9)/F9)*100 -> -1.579742
B10: =B9+1 -> 2010 | C10: 11099.247 | D10: =(C10/C9-1)*100 -> 4.8594958 | E10: =C9*(1+$L$10) -> 11008.271 | F10: =PIB_real!H$19 -> 11237.045 | G10: =((C10-F10)/F10)*100 -> -1.2262808 | J10: Coeficiente de tendencia | L10: 0.04
B11: =B10+1 -> 2011 | C11: 11726.953 | D11: =(C11/C10-1)*100 -> 5.6553885 | E11: =C10*(1+$L$10) -> 11543.217 | F11: =PIB_real!I$19 -> 11888.175 | G11: =((C11-F11)/F11)*100 -> -1.3561522
B12: =B11+1 -> 2012 | C12: 12184.444 | D12: =(C12/C11-1)*100 -> 3.9011919 | E12: =C11*(1+$L$10) -> 12196.031 | F12: =PIB_real!J$19 -> 12184.444 | G12: =((C12-F12)/F12)*100 -> 5.971514e-14
B13: =B12+1 -> 2013 | C13: =PIB_real!K6 -> 12774.631 | D13: =(E13/C12-1)*100 -> 4 | E13: =C12*(1+$L$10) -> 12671.821 | F13: =PIB_real!K$19 -> 12671.821 | G13: =((C13-F13)/F13)*100 -> 0.81132237 | I13: RY2012*(1+0,040), ver regresión
B14: 2014 | E14: =C13*(1+$L$10) -> 13285.616 | F14: =F13*(1+L10) -> 13178.694
B17: Macronia: Pronóstico de crecimiento del PIB (en %)
G19: Pronóstico | I19: Metodología
G20: 2014
B21: PRONÓSTICOS INICIALES
B22: Pronóstico suponiendo producto=evaluación de expertos | G22: ='Cuadro PIB'!J28 -> 4.4517021
B24: Pronóstico suponiendo que producto crece según tasa de crecimiento tendencial | G24: =L10*100 -> 4 | I24: (Coeficiente de regresión)*100
B26: Pronóstico según tasa de crecimiento media reciente | G26: =(((C13/C6)^(1/7))-1)*100 -> 3.7627652 | I26: (((RY2013/RY2006)^(1/7))-1)*100
B28: Pronóstico de crecimiento de se preferencia | G28: =G22 -> 4.4517021
B30: Pronóstico RY usando método preferido | G30: =C13*(1+G22/100) -> 13343.319 | I30: RY2013*(1+g/100)
B32: Brecha del producto | G32: =((G30-F14)/F14)*100 -> 1.2491751 | I32: 100*((RY2014-RYPot)/RYPot)

Sheet Inflación
F13: IPC mensual | L13: Curva de Phillips estimada (con inflación, brecha del producto y brecha del TCR en %)
G14: Variación % interanual | I14: πt = 1,4 + 0,7*πt-1 + 1,4*ygapt + 0.28*TCRgapt
F15: 40544 | G15: 4.8352713
F16: 40575 | G16: 4.5743346 | I16: π es la tasa de inflación
F17: 40603 | G17: 4.5830834 | I17: ygap es la brecha del producto
F18: 40634 | G18: 4.6819018 | I18: TCRgap es la brecha del tipo de cambio real
F19: 40664 | G19: 4.8451392
F20: 40695 | G20: 5.1759636 | I20: Macronia: Pronóstico de inflación media del IPC para 2014
F21: 40725 | G21: 5.193867
F22: 40756 | G22: 5.2518141 | K22: Valores (A) | M22: Coeficientes (B) | O22: A*B
F23: 40787 | G23: 5.1747094 | I23: Constante | K23: 1 | M23: 1.4 | O23: =K23*M23 -> 1.4
F24: 40817 | G24: 4.9263244
F25: 40848 | G25: 4.5554337 | I25: Inflación de año previos | K25: =K40 -> 6.1358513 | M25: 0.7 | O25: =K25*M25 -> 4.2950959
F26: 40878 | G26: 4.73
F27: 40909 | G27: 4.2138539 | I27: Brecha del producto en 2014 | K27: ='PIB real y brecha del producto'!G32 -> 1.2491751 | M27: 1.4 | O27: =K27*M27 -> 1.7488452
F28: 40940 | G28: 4.0533296
F29: 40969 | G29: 4.2080604 | I29: Brecha del TCR | K29: -0.31525678 | M29: 0.28 | O29: =K29*M29 -> -0.0882719
F30: 41000 | G30: 4.7073967
F31: 41030 | G31: 5.0352968 | I31: Pronóstico usando curva de Phillips | O31: =O23+O25+O27+O29 -> 7.3556692
F32: 41061 | G32: 4.6149101
F33: 41091 | G33: 3.9486457
F34: 41122 | G34: 4.2308691 | I34: Check line | K34: =K36-K29 -> -0.00076453413 | O34: =O31 -> 7.3556692
F35: 41153 | G35: 4.4663053
F36: 41183 | G36: 4.6840231 | I36: Brecha del TCR | K36: ='TC nominal'!I34*100 -> -0.31602132 | O36: =O31-O34 -> 0
F37: 41214 | G37: 5.2163663
F38: 41244 | G38: 5 | I38: Constante | K38: 1
F39: 41275 | G39: =$K$25+G27-AVERAGE($G$27:$G$38) -> 5.8181171
F40: 41306 | G40: =$K$25+G28-AVERAGE($G$27:$G$38) -> 5.6575929 | I40: Inflación media en 2013 | K40: 6.1358513
F41: 41334 | G41: =$K$25+G29-AVERAGE($G$27:$G$38) -> 5.8123237
F42: 41365 | G42: =$K$25+G30-AVERAGE($G$27:$G$38) -> 6.3116599 | I42: Brecha del producto en 2014 | K42: =100*(('Cuadro PIB'!K28-PIB_real!L19)/PIB_real!L19) -> 1.2491751
F43: 41395 | G43: =$K$25+G31-AVERAGE($G$27:$G$38) -> 6.6395601
F44: 41426 | G44: =$K$25+G32-AVERAGE($G$27:$G$38) -> 6.2191733 | I44: Brecha del TCR en 2014 | K44: ='TC nominal'!I24-'TC nominal'!I32 -> 0.41721528
F45: 41456 | G45: =$K$25+G33-AVERAGE($G$27:$G$38) -> 5.5529089
F46: 41487 | G46: =$K$25+G34-AVERAGE($G$27:$G$38) -> 5.8351323 | J46: 2006 | K46: 2007 | L46: 2008 | M46: 2009 | N46: 2010 | O46: 2011 | P46: 2012 | Q46: 2013 | R46: 2014
F47: 41518 | G47: =$K$25+G35-AVERAGE($G$27:$G$38) -> 6.0705685 | I47: IPC, promedio del período | J47: 111.47076 | K47: 121.90112 | L47: 138.26591 | M47: 149.10977 | N47: 157.55334 | O47: 165.23903 | P47: 173.50098 | Q47: 184.14674 | R47: =Q47*(1+Inflación!O31/100) -> 197.69197
F48: 41548 | G48: =$K$25+G36-AVERAGE($G$27:$G$38) -> 6.2882864 | I48: IPC, fin del período | J48: 109.4337 | K48: 121.25902 | L48: 138.1144 | M48: 143.70487 | N48: 152.07995 | O48: 159.27529 | P48: 167.39833 | Q48: 178.45376 | R48: =(Q48/Q47)*(Q47*(1+G51/100)) -> 191.01322
F49: 41579 | G49: =$K$25+G37-AVERAGE($G$27:$G$38) -> 6.8206296 | I49: IPC, promedio del período (variación %) | J49: 11.470763 | K49: 9.35703 | L49: 13.424651 | M49: 7.8427557 | N49: 5.6626532 | O49: 4.8781492 | P49: 5 | Q49: 6.1358513 | R49: =100*(R47/Q47-1) -> 7.3556692
F50: 41609 | G50: =$K$25+G38-AVERAGE($G$27:$G$38) -> 6.6042632 | I50: IPC, fin del período (variación %) | K50: 10.805926 | L50: 13.900308 | M50: 4.0477107 | N50: 5.8279713 | O50: 4.731288 | P50: 5.1 | Q50: 6.6042632 | R50: =100*(R48/Q48-1) -> 7.037935
F51: 41640 | G51: =$O$31+G39-AVERAGE($G$39:$G$50) -> 7.037935 | I51: Deflactor del PIB | J51: 11.156788 | K51: 10.923958 | L51: 11.077943 | M51: 8.6233366 | N51: 6.763734 | O51: 4.3046031 | P51: 4.5272294 | Q51: 6.8916443 | R51: =(IF(ISBLANK(Deflactor_PIB!L35)," ",Deflactor_PIB!L35))/(IF(ISBLANK(Deflactor_PIB!K35)," ",Deflactor_PIB!K35))*100-100 -> 8.1255598
F52: 41671 | G52: =$O$31+G40-AVERAGE($G$39:$G$50) -> 6.8774107 | I52: Meta de inflación | J52: 11 | K52: 8 | L52: 9 | M52: 8.5 | N52: 6 | O52: 6 | P52: 5 | Q52: 5 | R52: 5
F53: 41699 | G53: =$O$31+G41-AVERAGE($G$39:$G$50) -> 7.0321416
F54: 41730 | G54: =$O$31+G42-AVERAGE($G$39:$G$50) -> 7.5314778
F55: 41760 | G55: =$O$31+G43-AVERAGE($G$39:$G$50) -> 7.8593779
F56: 41791 | G56: =$O$31+G44-AVERAGE($G$39:$G$50) -> 7.4389912
F57: 41821 | G57: =$O$31+G45-AVERAGE($G$39:$G$50) -> 6.7727268
F58: 41852 | G58: =$O$31+G46-AVERAGE($G$39:$G$50) -> 7.0549502
F59: 41883 | G59: =$O$31+G47-AVERAGE($G$39:$G$50) -> 7.2903864
F60: 41913 | G60: =$O$31+G48-AVERAGE($G$39:$G$50) -> 7.5081042
F61: 41944 | G61: =$O$31+G49-AVERAGE($G$39:$G$50) -> 8.0404474
F62: 41974 | G62: =$O$31+G50-AVERAGE($G$39:$G$50) -> 7.8240811
F63: Inflación del IPC media 2014 | G63: =AVERAGE(G51:G62) -> 7.3556692

Sheet TC nominal
B2: TCN, tipo de cambio nominal medio
B3: TCNF, tipo de cambio nominal medio al fin del ejercicio
B4: TCR, índice de tipo de cambio real
B7: Macronia: Tipos de cambio nominal y real, 2008-2014
C10: 2008 | D10: 2009 | E10: 2010 | F10: 2011 | G10: 2012 | H10: 2013 | I10: 2014 | K10: Metodología
B12: Tipo de cambio nominal
B13: Promedio del período (MN por USD) | C13: 526.23551 | D13: 573.28796 | E13: 525.8292 | F13: 506.4 | G13: 510.78961 | H13: 530.21903 | I13: =H13*(1+I18/100)*(1+I24/100)/(1+I20/100) -> 563.14785 | K13: TCN14 = TCN13 * (1+%ΔP/100)* (1+%ΔTCR/100)/ (1+%ΔPf/100)
B14: Fin del ejercicio (MN por USD) | C14: 555.47 | D14: 565.24 | E14: 512.97 | F14: 510.56 | G14: 511.01923 | H14: 549.41884 | I14: =(I13*2)-H14 -> 576.87685 | K14: TCNF14 = (TCNF14*2) - TCNF13
B16: Variación del tipo de cambio nominal medio (+ depreciación) | D16: 8.941328 | E16: -8.2783452 | F16: -3.6949642 | G16: 0.86682713 | H16: 3.8038008 | I16: =(I13/H13-1)*100 -> 6.2104172 | K16: (TCN14/TCN13-1)*100
B18: Inflación interna (en porcentaje) | C18: 13.424651 | D18: 7.8427557 | E18: 5.6626532 | F18: 4.8781492 | G18: 4.6130302 | H18: 6.1358513 | I18: =Inflación!O31 -> 7.3556692 | K18: %ΔP
B20: Inflación en socios comerciales (en porcentaje) | C20: 3.595251 | D20: -0.17065775 | E20: 1.5164247 | F20: 2.8675084 | G20: 1.9575441 | H20: 1.5 | I20: 1.5 | K20: %ΔPf, supuesto exógeno
B22: Índice de tipo de cambio real (2012=100)1/ | C22: 121.17953 | D22: 122.20505 | E22: 107.69012 | F22: 101.72274 | G22: 100 | H22: 99.26981 | I22: =H31*(1+I34) -> 99.683979 | K22: TCR14 = TCR13 * (1+%ΔTCR/100)
B24: Variación del tipo de cambio real (en porcentaje) | D24: 0.84628357 | E24: -11.877525 | F24: -5.541248 | G24: -1.6935658 | H24: -0.73019014 | I24: =100*(I22/H22-1) -> 0.41721528 | K24: %ΔTCR
B26: 1/ Un aumento denota depreciación real, mientras que una disminución denota apreciación real.
B29: TCR observado (2012 = 100) | C29: =D29/((D13/C13)*(1+D20/100)/(1+D18/100)) -> 121.17953 | D29: =E29/((E13/D13)*(1+E20/100)/(1+E18/100)) -> 122.20505 | E29: =F29/((F13/E13)*(1+F20/100)/(1+F18/100)) -> 107.69012 | F29: =G29/((G13/F13)*(1+G20/100)/(1+G18/100)) -> 101.72274 | G29: =G31 -> 100 | H29: =H31*(1+H34) -> 99.26981 | I29: =I31*(1+I34) -> 99.683979
B30: variación % | D30: =(D29/C29-1)*100 -> 0.84628357 | E30: =(E29/D29-1)*100 -> -11.877525 | F30: =(F29/E29-1)*100 -> -5.541248 | G30: =(G29/F29-1)*100 -> -1.6935658 | H30: =(H29/G29-1)*100 -> -0.73019014 | I30: =(I29/H29-1)*100 -> 0.41721528
B31: TCR tendencial (2012=100) | C31: =D31/(1+D32/100) -> 100 | D31: =E31/(1+E32/100) -> 100 | E31: =F31/(1+F32/100) -> 100 | F31: =G31/(1+G32/100) -> 100 | G31: 100 | H31: =G31*(1+H32/100) -> 100 | I31: =H31*(1+I32/100) -> 100
B32: Variación % | C32: =D32 -> 0 | D32: =E32 -> 0 | E32: =F32 -> 0 | F32: =G32 -> 0 | G32: =H32 -> 0 | H32: =I32 -> 0 | I32: 0
B34: Brecha del TCR o variación TCR basada en UIP implícita (en términos reales) (+ depreciación) | H34: =H36+H38-H40-H42 -> -0.0073019014 | I34: =I36+I38-I40-I42 -> -0.0031602132
B36: Tasa de interés real externa (exógena) | H36: 0.005 | I36: 0.005
B38: prima por riesgo (exógena) | H38: 0.015 | I38: 0.015
B40: Tasa de interés real interna | H40: =(('Regla de Taylor '!D8)-('Regla de Taylor '!F8))/100 -> 0.027301901 | I40: =(('Regla de Taylor '!$D$9)-('Regla de Taylor '!$F$9))/100 -> 0.023160213 | J40: =(('Regla de Taylor '!$D$9)-('Regla de Taylor '!$F$9))/100 -> 0.023160213
B42: TCR tendencial (supuesto) | H42: 0 | I42: 0

Sheet Consumo real privado
B2: RY | C2: PIB real (miles de millones de moneda nacional, precios de 2005)
B3: RCp | C3: Consumo privado real (miles de millones de moneda nacional, precios de 2005)
B5: Año | C5: RCp | D5: RY | E5: RCp/RY en % | K5: Modelo de corrección de errores para consumo privado
K6: ΔLn(RCpt) = C + β*ΔLn(RINBDt) - λ*[Ln(RCpt-1) - δ*Ln(RINBDt-1)]+ εt
B7: 2006 | C7: 6791.1229 | D7: ='PIB real y brecha del producto'!C6 -> 9864.103 | E7: =C7/D7*100 -> 68.846837 | K7: Elasticidad a corto plazo estimada (β): | O7: 0.65
B8: =B7+1 -> 2007 | C8: 7301.5719 | D8: ='PIB real y brecha del producto'!C7 -> 10508.008 | E8: =C8/D8*100 -> 69.485787 | K8: Parámetro a largo plazo (δ): | O8: 0.88
B9: =B8+1 -> 2008 | C9: 7553.2801 | D9: ='PIB real y brecha del producto'!C8 -> 10760.325 | E9: =C9/D9*100 -> 70.19565
B10: =B9+1 -> 2009 | C10: 7682.1636 | D10: ='PIB real y brecha del producto'!C9 -> 10584.876 | E10: =C10/D10*100 -> 72.576796
B11: =B10+1 -> 2010 | C11: 8033.693 | D11: ='PIB real y brecha del producto'!C10 -> 11099.247 | E11: =C11/D11*100 -> 72.380521
B12: =B11+1 -> 2011 | C12: 8406.4347 | D12: ='PIB real y brecha del producto'!C11 -> 11726.953 | E12: =C12/D12*100 -> 71.684732
B13: =B12+1 -> 2012 | C13: 8818.35 | D13: ='PIB real y brecha del producto'!C12 -> 12184.444 | E13: =C13/D13*100 -> 72.373841
B14: =B13+1 -> 2013 | C14: 9288 | D14: ='PIB real y brecha del producto'!C13 -> 12774.631 | E14: =C14/D14*100 -> 72.706602
B15: Promedio: | E15: =AVERAGE(E7:E13) -> 71.077738
B17: Macronia: Pronóstico consumo privado real
H19: Pronóstico | J19: %ΔRCp | L19: RCp/RY en % | O19: Metodología
H20: 2014 | J20: =H20 -> 2014 | L20: =J20 -> 2014
B22: Pronóstico del PIB real- RY2014 | H22: ='PIB real y brecha del producto'!G30 -> 13343.319
B24: Pronóstico de crecimiento del PIB real- %ΔRY2014 | H24: ='PIB real y brecha del producto'!G28 -> 4.4517021
B26: INBD real del sector privado (pronóstico - variación %) | H26: =H24 -> 4.4517021
B28: Pronóstico de RCp suponiendo relación constante con respecto al PIB desde 2013 | H28: =H22*(C14/D14) -> 9701.4741 | J28: =(H28/$C$14-1)*100 -> 4.4517021 | L28: =H28/$H$22*100 -> 72.706602 | O28: RY2014*(RCp2013/RY2013)
B30: Forecast of RCp assuming constant ratio to disposable income since 2013 | H30: =C13*(1+#REF!/100) -> #REF! | J30: =(H30/$C$13-1)*100 -> #REF! | L30: =H30/$H$22*100 -> #REF!
B32: Pronóstico de RCp según método de regresión | H32: =C14*(1+(O7*H24/100)) -> 9556.7582 | J32: =(H32/$C$14-1)*100 -> 2.8936064 | L32: =H32/$H$22*100 -> 71.622045 | O32: RCp2013*(1+(0.65*%ΔRINBD2014/100))
B34: Su método preferido | H34: =H32 -> 9556.7582 | J34: =(H34/$C$14-1)*100 -> 2.8936064 | L34: =H34/$H$22*100 -> 71.622045

Sheet Inversión privada real
B2: RY | C2: PIB real (miles de millones de moneda nacional, precios de 2005)
B3: RIp | C3: Inversión privada real (miles de millones de moneda nacional, precios de 2005)
B4: RIBR | C4: Tasa de interés real (tasa interbancaria), deflactada ex-post usando IPC
B5: Inflación según IPC | N5: Producto de ecuación de inversión privada
B6: Año | C6: RIp | D6: RY | E6: RIp/RY en % | F6: %ΔRY | G6: %ΔRIp | I6: Tasa IBR (%) | J6: Inflación según IPC (%) | K6: RIBR (%) | N6: %D(RIpt) = 1.495*%D(RYt) -1.30*D(RIBR)t
N7: %D(RYt) | Q7: =H28 -> 4.4517021
B8: 2006 | C8: 1667.8795 | D8: ='PIB real y brecha del producto'!C6 -> 9864.103 | E8: =C8/D8*100 -> 16.908577 | F8: 8.8431346 | G8: 11.557973 | I8: =DD!H25 -> 11.25 | J8: 11.470763 | K8: =I8-J8 -> -0.22076281 | N8: Coef. sobre %D(RYt) | Q8: 1.495
B9: =B8+1 -> 2007 | C9: 1987.7598 | D9: ='PIB real y brecha del producto'!C7 -> 10508.008 | E9: =C9/D9*100 -> 18.916619 | F9: =100*(D9/D8-1) -> 6.5277581 | G9: =100*(C9/C8-1) -> 19.178863 | I9: =DD!H26 -> 7 | J9: 9.35703 | K9: =I9-J9 -> -2.35703 | N9: D(RIBR)t | Q9: =(K16-K15) -> 1.2518726
B10: =B9+1 -> 2008 | C10: 2155.8517 | D10: ='PIB real y brecha del producto'!C8 -> 10760.325 | E10: =C10/D10*100 -> 20.035191 | F10: =100*(D10/D9-1) -> 2.4011889 | G10: =100*(C10/C9-1) -> 8.4563498 | I10: =DD!H27 -> 11.5 | J10: 13.424651 | K10: =I10-J10 -> -1.9246506 | N10: Coef. sobre D(RIBR)t | Q10: -1.3
B11: =B10+1 -> 2009 | C11: 1924.3946 | D11: ='PIB real y brecha del producto'!C9 -> 10584.876 | E11: =C11/D11*100 -> 18.180606 | F11: =100*(D11/D10-1) -> -1.6305202 | G11: =100*(C11/C10-1) -> -10.736227 | I11: =DD!H28 -> 8.25 | J11: 7.8427557 | K11: =I11-J11 -> 0.40724435 | N11: %D(RIpt) | Q11: =(Q7*Q8+Q9*Q10) -> 5.0278602
B12: =B11+1 -> 2010 | C12: 1897.3962 | D12: ='PIB real y brecha del producto'!C10 -> 11099.247 | E12: =C12/D12*100 -> 17.094818 | F12: =100*(D12/D11-1) -> 4.8594958 | G12: =100*(C12/C11-1) -> -1.4029552 | I12: =DD!H29 -> 8 | J12: 5.6626532 | K12: =I12-J12 -> 2.3373468
B13: =B12+1 -> 2011 | C13: 2226.5912 | D13: ='PIB real y brecha del producto'!C11 -> 11726.953 | E13: =C13/D13*100 -> 18.986955 | F13: =100*(D13/D12-1) -> 5.6553885 | G13: =100*(C13/C12-1) -> 17.349832 | I13: =DD!H30 -> 8 | J13: 4.8781492 | K13: =I13-J13 -> 3.1218508
B14: =B13+1 -> 2012 | C14: =PIB_real!J11 -> 2241.1691 | D14: ='PIB real y brecha del producto'!C12 -> 12184.444 | E14: =C14/D14*100 -> 18.393693 | F14: =100*(D14/D13-1) -> 3.9011919 | G14: =100*(C14/C13-1) -> 0.65471915 | I14: =DD!H31 -> 9.25 | J14: 5 | K14: =I14-J14 -> 4.25
B15: 2013 | C15: =PIB_real!K11 -> 2336.1027 | D15: ='PIB real y brecha del producto'!C13 -> 12774.631 | E15: =C15/D15*100 -> 18.287047 | F15: =100*(D15/D14-1) -> 4.8437753 | G15: =100*(C15/C14-1) -> 4.2358972 | I15: =DD!H32 -> 12.2 | J15: 6.1358513 | K15: =I15-J15 -> 6.0641487
B16: 2014 | I16: ='Regla de Taylor '!F32 -> 14.671691 | J16: =Inflación!O31 -> 7.3556692 | K16: =I16-J16 -> 7.3160213
I17: ='regla de Taylor '!F32
B21: Macronia: Pronóstico inversión privada real
H23: Pronóstico | J23: %ΔRIp | L23: RIp/RY en % | N23: Metodología
H24: 2014 | J24: 2014 | L24: 2014
B26: Pronóstico del PIB real | H26: ='PIB real y brecha del producto'!G30 -> 13343.319
B28: Pronóstico de crecimiento del PIB real | H28: ='PIB real y brecha del producto'!G28 -> 4.4517021
B30: Pronóstico de RIp según método de proporción del PIB en 2014 | H30: =H26*C15/D15 -> 2440.0991 | J30: =(H30/$C$15-1)*100 -> 4.4517021 | L30: =H30/$H$26*100 -> 18.287047 | N30: RY2014*(RCp2013/RY2013)
B32: Pronóstico de RIp según ecuación calibrada | H32: =C15*(1+Q11/100) -> 2453.5587 | J32: =(H32/$C$15-1)*100 -> 5.0278602 | L32: =H32/$H$26*100 -> 18.387919 | N32: Ver ecuación de regresión arriba.
B36: Su método preferido | H36: =H32 -> 2453.5587 | J36: =(H36/$C$15-1)*100 -> 5.0278602 | L36: =H36/$H$26*100 -> 18.387919

Sheet Importaciones reales de bienes
C2: RMg | D2: Importaciones reales de bienes, en miles de millones de moneda nacional a precios constantes de 2005
C3: TCN | D3: Tipo de cambio nominal medio (moneda nacional por dólar de EE.UU.) | M3: Enfoque de la elasticidad para estimar volumen de importaciones de bienes
C4: Pmf | D4: Deflactor de las importaciones de bienes en dólares de EE.UU.
C5: Prmf | D5: Precio relativo de las importaciones de bienes (ver fórmula para el cálculo) en términos de moneda local
C6: εRM,y | D6: Elasticidad de las importaciones reales de bienes con respecto a la demanda interna (usar PIB real como variable representativa)
C7: εRM,Prmf | D7: Elasticidad de las importaciones reales de bienes con respecto al precio relativo de las importaciones
C9: %ΔPrmf = ((1+%ΔPmf/100)*(1+%ΔTCN/100)/(1+%ΔIPC/100) -1)*100 | L9: Δ%RMg = (εRM,y*Δ%RY) + (εRM,Prmf*Δ%Prmf)
C13: Macronia: Variación del precio relativo de las importaciones de bienes | L13: Macronia: Pronóstico de importaciones reales de bienes
F14: 2014 | O14: 2014
C16: Δ%Pmf | F16: ='TC nominal'!I20 -> 1.5 | L16: Δ%RY | O16: ='PIB real y brecha del producto'!G28 -> 4.4517021
C18: Δ%TCN | F18: =('TC nominal'!I13/'TC nominal'!H13-1)*100 -> 6.2104172 | L18: εRM,y | O18: =1.25777540726631 -> 1.2577754
C20: Δ%IPC | F20: =Inflación!O31 -> 7.3556692 | L20: Δ%Prmf | O20: =F22 -> 0.41721528
C22: Δ%Prmf | F22: =((1+F16/100)*(1+F18/100)/(1+F20/100)-1)*100 -> 0.41721528 | L22: εRM,Prmf | O22: =-'Exportaciones reales de bienes'!O23 -> -0.625
L24: Δ%RMg | O24: =(O18*O16)+(O22*O20) -> 5.3384819

Sheet Exportaciones reales de bienes
C2: RXg | D2: Exportaciones reales de bienes, en miles de millones de moneda nacional a precios constantes de 2005
C3: TCN | D3: Tipo de cambio nominal medio (moneda nacional por dólar de EE.UU.) | M3: Enfoque de la elasticidad para estimar volumen de exportaciones de bienes
C4: RYP | D4: Capacidad productiva interna
C5: Pxf | D5: Precio de exportaciones de bienes en dólares de EE.UU.
C6: Prxf | D6: Precio relativo de las exportaciones de bienes (ver fórmula para el cálculo)
C7: εRX,y | D7: Elasticidad de las exportaciones reales de bienes con respecto a la capacidad productiva interna
C8: εRX,Prxf | D8: Elasticidad de las exportaciones reales de bienes con respecto al precio relativo de las exportaciones
C10: %ΔPrxf = ((1+%ΔPxf/100)*(1+%ΔTCN/100)/(1+%ΔIPC/100) -1 )*100 | L10: Δ%RXg = (εRX,y*Δ%RYp) + (εRX,Prxf*Δ%Prxf)
C14: Macronia: Variación del precio relativo de las exportaciones de bienes | L14: Macronia: Pronóstico de exportaciones reales de bienes
F15: 2014 | O15: 2014
C17: Δ%Pxf | F17: ='TC nominal'!I20 -> 1.5 | L17: Δ%RYP | O17: ='PIB real y brecha del producto'!L10*100 -> 4
C19: Δ%TCN | F19: ='Importaciones reales de bienes'!F18 -> 6.2104172 | L19: εRX,y | O19: 1
C21: Δ%IPC | F21: ='Importaciones reales de bienes'!F20 -> 7.3556692 | L21: Δ%Prxf | O21: =F23 -> 0.41721528
C23: Δ%Prxf | F23: =((1+F17/100)*(1+F19/100)/(1+F21/100)-1)*100 -> 0.41721528 | L23: εRX,Prxf | O23: 0.625
L25: Δ%RXg | O25: =(O19*O17)+(O23*O21) -> 4.2607596

Sheet Import. y export. nominales
C3: Macronia: Proyecciones de importaciones y exportaciones nominales de bienes
L5: Modelo | M5: Pronóstico | O5: Metodología
G6: 2008 | H6: 2009 | I6: 2010 | J6: 2011 | K6: 2012 | L6: 2013 | M6: 2014
C8: Exportaciones nominales de bienes (en millones de dólares de EE.UU.) | G8: =BP!F7 -> 9555.3677 | H8: =BP!G7 -> 8838.2254 | I8: =BP!H7 -> 9516.2515 | J8: =BP!I7 -> 10383.11 | K8: =BP!J7 -> 11494.734 | L8: =BP!K7 -> 12095.645 | M8: =L8*(1+M12/100)*(1+M14/100) -> 12800.176 | O8: Xg2014 = Xg2013 *(1+%ΔRXg/100)*(1+%ΔPxf/100)
C10: Importaciones nominales de bienes (en millones de dólares de EE.UU.) | G10: =BP!F8 -> 14568.698 | H10: =BP!G8 -> 10877.286 | I10: =BP!H8 -> 12955.945 | J10: =BP!I8 -> 15534.481 | K10: =BP!J8 -> 17222.813 | L10: =BP!K8 -> 18289.856 | M10: =L10*(1+M16/100)*(1+M18/100) -> 19555.251 | O10: Mg2014 = Mg2013 *(1+%ΔRMg/100)*(1+%ΔPmf/100)
C12: Variaciones en el volumen de exportaciones de bienes (%ΔRXg) | M12: ='Exportaciones reales de bienes'!O25 -> 4.2607596
C14: Variaciones en el precio en dólares de EE.UU. de exportaciones de bienes (en porcentaje) | M14: ='Exportaciones reales de bienes'!F17 -> 1.5
C16: Variaciones en el volumen de importaciones de bienes (%ΔRMg) | M16: ='Importaciones reales de bienes'!O24 -> 5.3384819
C18: Variaciones en el precio en dólares de EE.UU. de importaciones de bienes (en porcentaje) | M18: ='Importaciones reales de bienes'!F16 -> 1.5

Sheet Servicios
B3: Macronia: Proyecciones de importaciones y exportaciones nominales de servicios
I5: Pronóstico | J5: Metodología
C6: 2008 | D6: 2009 | E6: 2010 | F6: 2011 | G6: 2012 | H6: 2013 | I6: 2014
B8: Crédito por servicios (en millones de dólares de EE.UU.) | C8: 4083.3176 | D8: 3592.9105 | E8: 4319.9815 | F8: 4972.3539 | G8: 5504.6979 | H8: 5792.4672 | I8: =I16/100*I14 -> 6129.8593 | K8: Usar relación créditos por servicios/exportaciones de bienes
B10: Débito por servicios (en millones de dólares de EE.UU.) | C10: 1882.3964 | D10: 1404.8099 | E10: 1782.7461 | F10: 1735.4792 | G10: 1924.0959 | H10: 2043.3038 | I10: =I20/100*I18 -> 2184.671 | K10: Usar relación débitos por servicios/importaciones de bienes
B12: Partidas informativas:
B14: Exportaciones de bienes (en millones de dólares de EE.UU.) | C14: 9555.3677 | D14: 8838.2254 | E14: 9516.2515 | F14: 10383.11 | G14: 11494.734 | H14: 12095.645 | I14: ='Import. y export. nominales'!M8 -> 12800.176
B16: Usar relación créditos por servicios/exportaciones de bienes | C16: 42.733234 | D16: 40.651944 | E16: 45.395832 | F16: 47.888867 | G16: 47.888867 | H16: 47.888867 | I16: =H16 -> 47.888867 | K16: Usar última observación. Puede usarse promedio de un período
B18: Importaciones de bienes (en millones de dólares de EE.UU.) | C18: 14568.698 | D18: 10877.286 | E18: 12955.945 | F18: 15534.481 | G18: 17222.813 | H18: 18289.856 | I18: ='Import. y export. nominales'!M10 -> 19555.251
B20: Usar relación débitos por servicios/importaciones de bienes (%) | C20: 12.920828 | D20: 12.915078 | E20: 13.760062 | F20: 11.171787 | G20: 11.171787 | H20: 11.171787 | I20: =H20 -> 11.171787 | K20: Usar última observación. Puede usarse promedio de un período

Sheet Ingreso primario
B2: Macronia: Pronóstico de ingreso primario
H3: Pronóstico
C4: 2008 | D4: 2009 | E4: 2010 | F4: 2011 | G4: 2012 | H4: 2013 | I4: 2014 | J4: Metodología
C6: (en millones de USD, salvo indicación en contrario)
B8: Créditos por ingreso primario | C8: 617.81711 | D8: 253.4883 | E8: 316.8296 | F8: 272.3782 | G8: =(F8/F9)*G9 -> 173.86689 | H8: =(G8/G9)*H9 -> 184.98126 | I8: =(H8/H9)*I9 -> 170.57965
B9: de los cuales: renta de inversión | C9: 546.91711 | D9: 228.9883 | E9: 281.6296 | F9: 209.1782 | G9: =((F12+G12)/2)*(G13/100) -> 133.5245 | H9: =((G12+H12)/2)*(H13/100) -> 142.06 | I9: 131
B11: Stock de activos externos
B12: (fin del período) | C12: 11617.7 | D12: 11915.2 | E12: 12732.4 | F12: 12928.9 | G12: 13776 | H12: 14636 | I12: 14324 | J12: del cuadro de PII (fijar este valor igual al de la celda H15 hasta que converja)
B13: Tasa media de rendimiento de la renta de la inversión | C13: 4.6718898 | D13: 1.3028984 | E13: 1.5405253 | F13: 1.0896486 | G13: 1 | H13: 1 | I13: 1 | J13: Tasa implícita de rendimiento de la renta de la inversión
B14: Partida informativa: Activos (del cuadro de la PII) | I14: =PII!L7 -> 15053.21
B15: Línea de verificación | I15: =I12-I14 -> -729.20992
B17: Débitos por ingreso primario | C17: 1126.041 | D17: 1203.94 | E17: 1083.384 | F17: 1077.223 | G17: 1084.2712 | H17: 1042.6721 | I17: =I18+I19 -> 1062.9875
B18: Pagos de intereses | C18: 352.6 | D18: 308 | E18: 306.6 | F18: 284.1 | G18: 285.95886 | H18: 274.98777 | I18: =((H21+I21)/2)*(I23/100) -> 295.30314 | J18: (saldo de la deuda medio de 2013-14) * (tasa de interés implícita/100)
B19: Otros pagos | C19: 773.441 | D19: 895.94 | E19: 776.784 | F19: 793.123 | G19: 798.31238 | H19: 767.68436 | I19: =H19 -> 767.68436 | J19: Pronóstico basado en valores pasados o proporción con respecto a pagos de intereses
B21: Stock de deuda externa | C21: 8964.3 | D21: 7878.8 | E21: 8631.8 | F21: 9764.2 | G21: 10236 | H21: 11068 | I21: 11809.883 | J21: Stock del año anterior más flujos de deuda de la cuenta financiera
B22: LIBOR a seis meses sobre depósitos en dólares de EE.UU. (en porcentaje) 1/ | C22: 3.046 | D22: 1.121 | E22: 0.518 | F22: 0.507 | G22: 0.687 | H22: 0.409 | I22: 0.409 | J22: Supuesto exógeno (LIBOR adecuada para reservas)
B23: Tasa de interés implícita media (en porcentaje) | C23: 4.0691267 | D23: 3.657284 | E23: 3.7139777 | F23: 3.0887149 | G23: 2.85956 | H23: 2.58156 | I23: =I22+I24 -> 2.58156 | J23: LIBOR de 2014 + diferencial del pronóstico
B24: Diferencial de tasa de interés sobre pagos (en porcentaje) 2/ | C24: 1.0231267 | D24: 2.536284 | E24: 3.1959777 | F24: 2.5817149 | G24: 2.17256 | H24: 2.17256 | I24: =H24 -> 2.17256 | J24: Pronosticar esto sobre la base de valores pasados
B26: 1/ La LIBOR (tasa interbancaria de oferta de Londres) es un parámetro de referencia común para las reservas oficiales.
B27: Si un país tiene reservas reducidas, por lo general las mantendría en cuentas corrientes o de depósito con vencimientos muy cortos
B28: para fines de liquidez. Una vez que un país acumula reservas más cuantiosas, el banco central puede colocar algunos depósitos con vencimientos más largos
B29: o en instrumentos de mayor rendimiento, como bonos del Tesoro de de Estados Unidos.
B30: 2/ El diferencial es el monto en que la tasa de interés media supera la LIBOR.

Sheet Ingreso secundario
B2: Macronia: Pronóstico de ingreso secundario
J3: Pronóstico | N3: Metodología
H4: 2012 | I4: 2013 | J4: 2014
C6: Ingreso secundario, saldo (en millones de dólares de EE.UU.) | H6: 333.50078 | I6: 342.90384 | J6: =I6*(1+J16/100) -> 352.57201 | N6: SIB2014 = SIB2013*(1+Δ%transferencias/100)
C8: Variación del PIB nominal en países industriales (en porcentaje) | H8: 3.2829922 | I8: 2.8195 | J8: =(((1+J10/100)*(1+J12/100))-1)*100 -> 2.8195 | L8: Δ%Yi | N8: Δ%Yi = {[(1+Δ%Ryi/100)*(1+πi/100)]-1}*100
C10: Variación del PIB real en países industriales (en porcentaje) | H10: 1.3 | I10: 1.3 | J10: 1.3 | L10: Δ%RYi | N10: Supuesto exógeno
C12: Tasa de inflación en países socios comerciales (en porcentaje) | H12: 1.9575441 | I12: 1.5 | J12: ='TC nominal'!I20 -> 1.5 | L12: πi | N12: Supuesto exógeno
C14: Elasticidad de las transferencias netas con respecto al ingreso externo | H14: 1 | I14: 1 | J14: 1 | L14: εtransferencias, Yi | N14: Supuesto exógeno
C16: Variación predicha en las transferencias, neta (en porcentaje) | H16: 3.2829922 | I16: 2.8195 | J16: =J14*J8 -> 2.8195 | L16: Δ%transferencias | N16: Δ%transferencias = εtransferencias, Yi*Δ%Yi

Sheet Gob_EOG
C2: Macronia: Estado de las operaciones del gobierno general, 2006-12
D3: 2006 | E3: 2007 | F3: 2008 | G3: 2009 | H3: 2010 | I3: 2011 | J3: 2012 | K3: 2013 | L3: 2014 | P3: 2011 | Q3: 2012 | R3: 2013 | S3: 2014
B4: (en miles de millones de moneda nacional) | Q4: (en porcentaje del PIB)
C5: Ingresos | D5: 1638.3526 | E5: 2104.7018 | F5: 2490.0306 | G5: 2363.2649 | H5: 2730.1668 | I5: 3023.8539 | J5: 3271.5261 | K5: 3625.6334 | L5: =L6+L11+L12+L13 -> 4081.623 | P5: =I5/PIB_Nominal!I$6 -> 0.15564533 | Q5: =J5/PIB_Nominal!J$6 -> 0.15462876 | R5: =K5/PIB_Nominal!K$6 -> 0.15332847 | S5: =L5/PIB_Nominal!L$6 -> 0.15283679
C6: Impuestos | D6: 1577.733 | E6: 2028.9423 | F6: 2408.5786 | G6: 2262.2893 | H6: 2480.4111 | I6: 2768.9008 | J6: 3007.0638 | K6: 3330.0604 | L6: =SUM(L7:L10) -> 3747.8059 | P6: =I6/PIB_Nominal!I$6 -> 0.14252225 | Q6: =J6/PIB_Nominal!J$6 -> 0.14212895 | R6: =K6/PIB_Nominal!K$6 -> 0.14082865 | S6: =L6/PIB_Nominal!L$6 -> 0.14033697
C7: Impuestos sobre el ingreso, las utilidades y las ganancias de capital | D7: 394.095 | E7: 531.5518 | F7: 689.2247 | G7: 687.4203 | H7: 752.1716 | I7: 832.2036 | J7: 891.4239 | K7: 983.36609 | L7: =Gob_GTR_Proy!J57 -> 1094.9239 | P7: =I7/PIB_Nominal!I$6 -> 0.042835601 | Q7: =J7/PIB_Nominal!J$6 -> 0.042133173 | R7: =K7/PIB_Nominal!K$6 -> 0.041586668 | S7: =L7/PIB_Nominal!L$6 -> 0.040999537
C8: Impuestos sobre bienes y servicios | D8: 324.2719 | E8: 407.0999 | F8: 465.051 | G8: 476.2986 | H8: 511.6052 | I8: 547.7084 | J8: 610.796 | K8: 672.89058 | L8: =Gob_GTR_Proy!J58 -> 746.7644 | P8: =I8/PIB_Nominal!I$6 -> 0.028191922 | Q8: =J8/PIB_Nominal!J$6 -> 0.028869288 | R8: =K8/PIB_Nominal!K$6 -> 0.028456622 | S8: =L8/PIB_Nominal!L$6 -> 0.027962669
C9: Impuestos sobre el comercio internacional | D9: 520.9995 | E9: 681.4017 | F9: 797.421 | G9: 593.6164 | H9: 686.6615 | I9: 803.4734 | J9: 856.2116 | K9: 957.70308 | L9: =Gob_GTR_Proy!J59 -> 1108.0894 | P9: =I9/PIB_Nominal!I$6 -> 0.041356786 | Q9: =J9/PIB_Nominal!J$6 -> 0.040468863 | R9: =K9/PIB_Nominal!K$6 -> 0.040501377 | S9: =L9/PIB_Nominal!L$6 -> 0.041492519
C10: Otros impuestos | D10: 338.3666 | E10: 408.8889 | F10: 456.8819 | G10: 504.954 | H10: 529.9728 | I10: 585.5154 | J10: 648.6323 | K10: 716.10066 | L10: =Gob_GTR_Proy!J60 -> 798.02819 | P10: =I10/PIB_Nominal!I$6 -> 0.030137942 | Q10: =J10/PIB_Nominal!J$6 -> 0.030657622 | R10: =K10/PIB_Nominal!K$6 -> 0.030283982 | S10: =L10/PIB_Nominal!L$6 -> 0.029882247
C11: Contribuciones sociales | D11: 33.3207 | E11: 37.9464 | F11: 43.7314 | G11: 54.3563 | H11: 61.2418 | I11: 66.7702 | J11: 74.084 | K11: 82.799062 | L11: =R11*'Cuadro PIB'!L$28 -> 93.512423 | P11: =I11/PIB_Nominal!I$6 -> 0.0034368292 | Q11: =J11/PIB_Nominal!J$6 -> 0.0035015821 | R11: =K11/PIB_Nominal!K$6 -> 0.0035015821 | S11: =L11/PIB_Nominal!L$6 -> 0.0035015821
C12: Donaciones | D12: 16.2813 | E12: 18.18001 | F12: 25.9252 | G12: 29.272 | H12: 161.318 | I12: 165.3464 | J12: 165.7465 | K12: 185.24452 | L12: =R12*'Cuadro PIB'!L$28 -> 209.21328 | P12: =I12/PIB_Nominal!I$6 -> 0.0085107929 | Q12: =J12/PIB_Nominal!J$6 -> 0.0078340125 | R12: =K12/PIB_Nominal!K$6 -> 0.0078340125 | S12: =L12/PIB_Nominal!L$6 -> 0.0078340125
C13: Otros ingresos 1/ | D13: 11.0176 | E13: 19.6331 | F13: 11.7954 | G13: 17.3473 | H13: 27.1959 | I13: 22.8365 | J13: 24.6318 | K13: 27.529425 | L13: =R13*'Cuadro PIB'!L$28 -> 31.091454 | P13: =I13/PIB_Nominal!I$6 -> 0.0011754518 | Q13: =J13/PIB_Nominal!J$6 -> 0.0011642227 | R13: =K13/PIB_Nominal!K$6 -> 0.0011642227 | S13: =L13/PIB_Nominal!L$6 -> 0.0011642227
C15: Gasto | D15: 1744.1125 | E15: 1998.9584 | F15: 2343.0758 | G15: 2865.1863 | H15: 3669.9965 | I15: 3810.7387 | J15: 4235.2045 | K15: 5474.6182 | L15: =L16+L17+L18+L19+L22+L23+L24+L25 -> 7400.5623 | P15: =I15/PIB_Nominal!I$6 -> 0.19614825 | Q15: =J15/PIB_Nominal!J$6 -> 0.20017705 | R15: =K15/PIB_Nominal!K$6 -> 0.23152225 | S15: =L15/PIB_Nominal!L$6 -> 0.27711481
C16: Remuneración de empleados | D16: 534.6183 | E16: 600.6902 | F16: 720.71 | G16: 936.8567 | H16: 1133.809 | I16: 1268.1951 | J16: 1380.02 | K16: 2010.5531 | L16: ='Hoja-Gob_Exp_Proy.'!I11 -> 2590.2094 | P16: =I16/PIB_Nominal!I$6 -> 0.065277175 | Q16: =J16/PIB_Nominal!J$6 -> 0.06522668 | R16: =K16/PIB_Nominal!K$6 -> 0.085026528 | S16: =L16/PIB_Nominal!L$6 -> 0.096990655
C17: Uso de bienes y servicios | D17: 56.3101 | E17: 72.6149 | F17: 87.6277 | G17: 106.3593 | H17: 120.6757 | I17: 135.6315 | J17: 142.9392 | K17: 158.62466 | L17: ='Hoja-Gob_Exp_Proy.'!I12 -> 204.35724 | P17: =I17/PIB_Nominal!I$6 -> 0.0069812926 | Q17: =J17/PIB_Nominal!J$6 -> 0.0067560249 | R17: =K17/PIB_Nominal!K$6 -> 0.0067082555 | S17: =L17/PIB_Nominal!L$6 -> 0.0076521776
C18: Consumo de capital fijo | D18: 10 | E18: 12 | F18: 9 | G18: 11 | H18: 10 | I18: 13 | J18: 12 | K18: 13.316822 | L18: ='Hoja-Gob_Exp_Proy.'!I13 -> 17.156154 | P18: =I18/PIB_Nominal!I$6 -> 0.00066914252 | Q18: =J18/PIB_Nominal!J$6 -> 0.00056718031 | R18: =K18/PIB_Nominal!K$6 -> 0.00056316997 | S18: =L18/PIB_Nominal!L$6 -> 0.00064241392
C19: Intereses | D19: 436.7021 | E19: 419.6423 | F19: 340.0858 | G19: 360.1067 | H19: 401.5411 | I19: 449.3781 | J19: 471.5865 | K19: 818.90264 | L19: =L20+L21 -> 1402.5718 | P19: =I19/PIB_Nominal!I$6 -> 0.023130615 | Q19: =J19/PIB_Nominal!J$6 -> 0.022289548 | R19: =K19/PIB_Nominal!K$6 -> 0.03463149 | S19: =L19/PIB_Nominal!L$6 -> 0.052519441
C20: Sobre la deuda interna | D20: 349.4543 | E20: 331.6638 | F20: 255.3287 | G20: 280.639 | H20: 336.6388 | I20: 390.8765 | J20: 424.5849 | K20: 762.44566 | L20: ='Hoja-Gob_Exp_Proy.'!I25 -> 1330.5556 | P20: =I20/PIB_Nominal!I$6 -> 0.020119391 | Q20: =J20/PIB_Nominal!J$6 -> 0.020068016 | R20: =K20/PIB_Nominal!K$6 -> 0.032243917 | S20: =L20/PIB_Nominal!L$6 -> 0.049822791
C21: Sobre la deuda externa | D21: 87.2478 | E21: 87.9785 | F21: 84.7571 | G21: 79.4677 | H21: 64.9023 | I21: 58.5016 | J21: 47.0016 | K21: 56.456986 | L21: ='Hoja-Gob_Exp_Proy.'!I16 -> 72.016115 | P21: =I21/PIB_Nominal!I$6 -> 0.0030112237 | Q21: =J21/PIB_Nominal!J$6 -> 0.0022215318 | R21: =K21/PIB_Nominal!K$6 -> 0.0023875726 | S21: =L21/PIB_Nominal!L$6 -> 0.0026966507
C22: Subsidios | D22: 590.0768 | E22: 777.4471 | F22: 1042.2689 | G22: 1246.8462 | H22: 1758.4533 | I22: 1669.5427 | J22: 1946.3238 | K22: 2159.904 | L22: ='Hoja-Gob_Exp_Proy.'!I28 -> 2782.6192 | P22: =I22/PIB_Nominal!I$6 -> 0.08593554 | Q22: =J22/PIB_Nominal!J$6 -> 0.091993044 | R22: =K22/PIB_Nominal!K$6 -> 0.091342594 | S22: =L22/PIB_Nominal!L$6 -> 0.10419546
C23: Donaciones | D23: 15.8599 | E23: 3.7772 | F23: 7.58132 | G23: 26.0885 | H23: 30.1683 | I23: 29.5888 | J23: 15.3073 | K23: 16.987049 | L23: ='Hoja-Gob_Exp_Proy.'!I29 -> 21.884533 | P23: =I23/PIB_Nominal!I$6 -> 0.0015230096 | Q23: =J23/PIB_Nominal!J$6 -> 0.00072349992 | R23: =K23/PIB_Nominal!K$6 -> 0.00071838431 | S23: =L23/PIB_Nominal!L$6 -> 0.00081946854
C24: Prestaciones sociales | D24: 100.5453 | E24: 112.7867 | F24: 135.8021 | G24: 177.9289 | H24: 215.3491 | I24: 245.4025 | J24: 267.0277 | K24: 296.33003 | L24: ='Hoja-Gob_Exp_Proy.'!I30 -> 381.76402 | P24: =I24/PIB_Nominal!I$6 -> 0.012631481 | Q24: =J24/PIB_Nominal!J$6 -> 0.012621071 | R24: =K24/PIB_Nominal!K$6 -> 0.012531832 | S24: =L24/PIB_Nominal!L$6 -> 0.014295193
C25: Otros gastos | D25: 0 | E25: 0 | F25: 0 | G25: 0 | H25: 0 | I25: 0 | J25: 0 | K25: 0 | L25: ='Hoja-Gob_Exp_Proy.'!I31 -> 0 | P25: =I25/PIB_Nominal!I$6 -> 0 | Q25: =J25/PIB_Nominal!J$6 -> 0 | R25: =K25/PIB_Nominal!K$6 -> 0 | S25: =L25/PIB_Nominal!L$6 -> 0
C27: Resultado operativo neto | D27: -105.7599 | E27: 105.74341 | F27: 146.95478 | G27: -501.9214 | H27: -939.8297 | I27: -786.8848 | J27: -963.6784 | K27: -1848.9848 | L27: =L5-L15 -> -3318.9393 | N27: ='Hoja-Gob_Exp_Proy.'!I33 -> -3318.9393 | P27: =I27/PIB_Nominal!I$6 -> -0.040502929 | Q27: =J27/PIB_Nominal!J$6 -> -0.045548284 | R27: =K27/PIB_Nominal!K$6 -> -0.078193786 | S27: =L27/PIB_Nominal!L$6 -> -0.12427802
C29: Adquisición neta de activos no financieros | D29: 15.2979 | E29: 28.1742 | F29: 52.4514 | G29: 71.1196 | H29: 54.3857 | I29: 59.0558 | J29: 39.5011 | K29: 30.852499 | L29: =L30-L31-L33 -> 32.729354 | P29: =I29/PIB_Nominal!I$6 -> 0.0030397498 | Q29: =J29/PIB_Nominal!J$6 -> 0.0018670205 | R29: =K29/PIB_Nominal!K$6 -> 0.0013047558 | S29: =L29/PIB_Nominal!L$6 -> 0.001225554
C30: Adquisición de activos no financieros | D30: 60.2979 | E30: 57.1742 | F30: 65.4514 | G30: 87.1196 | H30: 68.3857 | I30: 72.0558 | J30: 86.5011 | K30: 44.169321 | L30: ='Hoja-Gob_Exp_Proy.'!I35 -> 49.885507 | N30: ='Hoja-Gob_Exp_Proy.'!I35 -> 49.885507 | P30: =I30/PIB_Nominal!I$6 -> 0.0037088923 | Q30: =J30/PIB_Nominal!J$6 -> 0.0040884767 | R30: =K30/PIB_Nominal!K$6 -> 0.0018679258 | S30: =L30/PIB_Nominal!L$6 -> 0.0018679679
C31: Disposición de activos no financieros | D31: 35 | E31: 17 | F31: 4 | G31: 5 | H31: 4 | I31: 0 | J31: 35 | K31: 0 | L31: 0 | P31: =I31/PIB_Nominal!I$6 -> 0 | Q31: =J31/PIB_Nominal!J$6 -> 0.0016542759 | R31: =K31/PIB_Nominal!K$6 -> 0 | S31: =L31/PIB_Nominal!L$6 -> 0
C32: de la cual: venta de activos (privatización) | D32: 29 | E32: 13 | F32: 0 | G32: 0 | H32: 0 | I32: 0 | J32: 27 | K32: 0 | L32: 0 | P32: =I32/PIB_Nominal!I$6 -> 0 | Q32: =J32/PIB_Nominal!J$6 -> 0.0012761557 | R32: =K32/PIB_Nominal!K$6 -> 0 | S32: =L32/PIB_Nominal!L$6 -> 0
C33: Consumo de capital fijo | D33: 10 | E33: 12 | F33: 9 | G33: 11 | H33: 10 | I33: 13 | J33: 12 | K33: 13.316822 | L33: =L18 -> 17.156154 | P33: =I33/PIB_Nominal!I$6 -> 0.00066914252 | Q33: =J33/PIB_Nominal!J$6 -> 0.00056718031 | R33: =K33/PIB_Nominal!K$6 -> 0.00056316997 | S33: =L33/PIB_Nominal!L$6 -> 0.00064241392
C35: Préstamo neto (-)/endeudamiento neto (+) | D35: -121.0578 | E35: 77.56921 | F35: 94.50338 | G35: -573.041 | H35: -994.2154 | I35: -845.9406 | J35: -1003.1795 | K35: -1879.8373 | L35: =L36-L43 -> -3351.6687 | N35: ='Hoja-Gob_Exp_Proy.'!I37 -> 3351.6687
C36: Adquisición neta de activos financieros | D36: -295 | E36: -268 | F36: 91.9047 | G36: 40 | H36: -10 | I36: -34 | J36: -126 | K36: 0 | L36: =L37+L42 -> 0
C37: Internos | D37: -297 | E37: -265 | F37: 86.9047 | G37: 39 | H37: -12 | I37: -30 | J37: -132 | K37: 0 | L37: 0
C38: Depósitos | D38: -10 | E38: -2 | F38: 5 | G38: 2 | H38: -25 | I38: -30 | J38: -47 | K38: 0 | L38: 0
C39: Acciones, préstamos y otros títulos de participación en el capital | D39: -287 | E39: -263 | F39: 81.9047 | G39: 37 | H39: 13 | I39: 0 | J39: -85 | K39: 0 | L39: 0
C40: de los cuales: venta de participaciones de capital (privatización) | D40: 322 | E40: 310 | F40: 0 | G40: 0 | H40: 43 | I40: 61 | J40: 160 | K40: 0 | L40: 0
C41: de los cuales: préstamos para fines de política | D41: 27 | E41: 35 | F41: 9 | G41: 13 | H41: 37 | I41: 43 | J41: 51 | K41: 0 | L41: 0
C42: Externo | D42: 2 | E42: -3 | F42: 5 | G42: 1 | H42: 2 | I42: -4 | J42: 6 | K42: 0 | L42: 0
C43: Incurrimiento neto de pasivos | D43: -173.9422 | E43: -345.56921 | F43: -2.59868 | G43: 613.041 | H43: 984.2154 | I43: 811.9406 | J43: 877.1795 | K43: 1879.8373 | L43: =L44+L47 -> 3351.6687
C44: Internos | D44: -185.30286 | E44: -415.48144 | F44: 47.345085 | G44: 577.97633 | H44: 764.48166 | I44: 940.41712 | J44: 592.23031 | K44: 1594.8881 | L44: =-L27+L29-L47 -> 3051.6687 | N44: ='Hoja-Gob_Exp_Proy.'!I39 -> 3051.6687
C45: De sociedades de depósito | D45: -131.39651 | E45: -218.43845 | F45: 33.138081 | G45: 260.60918 | H45: -1.7695621 | I45: 196.73287 | J45: 177.66909 | K45: 478.46644 | L45: =0.3*L44 -> 915.5006
C46: Del resto del sector privado | D46: -53.90635 | E46: -197.043 | F46: 14.207004 | G46: 317.36715 | H46: 766.25123 | I46: 743.68424 | J46: 414.56122 | K46: 1116.4217 | L46: =L44-L45 -> 2136.1681
C47: Externo | D47: 11.360658 | E47: 69.912232 | F47: -49.943765 | G47: 35.064671 | H47: 219.73374 | I47: -128.47652 | J47: 284.94919 | K47: 284.94919 | L47: 300
C49: Agregados y saldos seleccionados
C50: Gastos primarios | D50: 1307.4104 | E50: 1579.3161 | F50: 2002.99 | G50: 2505.0796 | H50: 3268.4554 | I50: 3361.3606 | J50: 3763.618 | K50: 4655.7156 | L50: =L15-L19 -> 5997.9906
C51: Resultado operativo neto primario 2/ | D51: 330.9422 | E51: 525.38571 | F51: 487.04058 | G51: -141.8147 | H51: -538.2886 | I51: -337.5067 | J51: -492.0919 | K51: -1030.0822 | L51: =L27+L19 -> -1916.3675
C52: Saldo global (FMI) | D52: -499.0578 | E52: -280.43079 | F52: 85.50338 | G52: -586.041 | H52: -1074.2154 | I52: -949.9406 | J52: -1241.1795 | K52: -1879.8373 | L52: =L35-L32-L40-L41 -> -3351.6687
C53: Saldo primario global (FMI) | D53: -62.3557 | E53: 139.21151 | F53: 425.58918 | G53: -225.9343 | H53: -672.6743 | I53: -500.5625 | J53: -769.593 | K53: -1060.9347 | L53: =L52+L19 -> -1949.0969
C55: Notas:
C56: 1/ Otros ingresos no incluye la renta por concepto de intereses.
C57: 2/ Puede dar por supuesto que la renta por concepto de intereses es cero.
C59: Partidas informativas:
C60: Contribuciones sociales (en porcentaje del PIB) | D60: =100*(D11/PIB_Nominal!D6) -> 0.30389288 | E60: =100*(E11/PIB_Nominal!E6) -> 0.29287941 | F60: =100*(F11/PIB_Nominal!F6) -> 0.29674186 | G60: =100*(G11/PIB_Nominal!G6) -> 0.34518492 | H60: =100*(H11/PIB_Nominal!H6) -> 0.34739083 | I60: =100*(I11/PIB_Nominal!I6) -> 0.34368292 | J60: =100*(J11/PIB_Nominal!J6) -> 0.35015821 | K60: =J60 -> 0.35015821 | L60: =K60 -> 0.35015821
C61: Donaciones (en porcentaje del PIB) | D61: =100*(D12/PIB_Nominal!D$6) -> 0.14848941 | E61: =100*(E12/PIB_Nominal!E$6) -> 0.14031768 | F61: =100*(F12/PIB_Nominal!F$6) -> 0.1759169 | G61: =100*(G12/PIB_Nominal!G$6) -> 0.18588927 | H61: =100*(H12/PIB_Nominal!H$6) -> 0.91506771 | I61: =100*(I12/PIB_Nominal!I$6) -> 0.85107929 | J61: =100*(J12/PIB_Nominal!J$6) -> 0.78340125 | K61: =J61 -> 0.78340125 | L61: =K61 -> 0.78340125
C62: Otros ingresos (en porcentaje del PIB) | D62: =100*(D13/PIB_Nominal!D$6) -> 0.10048319 | E62: =100*(E13/PIB_Nominal!E$6) -> 0.15153297 | F62: =100*(F13/PIB_Nominal!F$6) -> 0.080038347 | G62: =100*(G13/PIB_Nominal!G$6) -> 0.11016251 | H62: =100*(H13/PIB_Nominal!H$6) -> 0.15426729 | I62: =100*(I13/PIB_Nominal!I$6) -> 0.11754518 | J62: =100*(J13/PIB_Nominal!J$6) -> 0.11642227 | K62: =J62 -> 0.11642227 | L62: =K62 -> 0.11642227
C63: Derechos netos frente al gobierno general (miles de millones de MN) factor de monetario | D63: =D45-D38 -> -121.39651 | E63: =E45-E38 -> -216.43845 | F63: =F45-F38 -> 28.138081 | G63: =G45-G38 -> 258.60918 | H63: =H45-H38 -> 23.230438 | I63: =I45-I38 -> 226.73287 | J63: =J45-J38 -> 224.66909 | K63: =K45-K38 -> 478.46644 | L63: =L45-L38 -> 915.5006
C65: verificar línea por encima y por debajo de la línea | D65: =D29+D35-D27 -> 0 | E65: =E29+E35-E27 -> 0 | F65: =F29+F35-F27 -> 0 | G65: =G29+G35-G27 -> 0 | H65: =H29+H35-H27 -> 0 | I65: =I29+I35-I27 -> 0 | J65: =J29+J35-J27 -> 0 | K65: =K29+K35-K27 -> 0 | L65: =L29+L35-L27 -> 0
D66: 2006 | E66: 2007 | F66: 2008 | G66: 2009 | H66: 2010 | I66: 2011 | J66: 2012 | K66: 2013 | L66: 2014
C67: incurrimiento neto de pasivos (en porcentaje del total) | D67: =D68+D71 -> 100 | E67: =E68+E71 -> 100 | F67: =F68+F71 -> 100 | G67: =G68+G71 -> 100 | H67: =H68+H71 -> 100 | I67: =I68+I71 -> 100 | J67: =J68+J71 -> 100 | K67: =K68+K71 -> 100 | L67: =L68+L71 -> 100
C68: Internos | D68: =100*(D44/D$43) -> 106.53128 | E68: =100*(E44/E$43) -> 120.23104 | F68: =100*(F44/F$43) -> -1821.8898 | G68: =100*(G44/G$43) -> 94.280208 | H68: =100*(H44/H$43) -> 77.674223 | I68: =100*(I44/I$43) -> 115.82339 | J68: =100*(J44/J$43) -> 67.515293 | K68: =100*(K44/K$43) -> 84.841816 | L68: =100*(L44/L$43) -> 91.049235
C69: De sociedades de depósito | D69: =100*(D45/D$43) -> 75.540327 | E69: =100*(E45/E$43) -> 63.211201 | F69: =100*(F45/F$43) -> -1275.189 | G69: =100*(G45/G$43) -> 42.510889 | H69: =100*(H45/H$43) -> -0.17979419 | I69: =100*(I45/I$43) -> 24.229959 | J69: =100*(J45/J$43) -> 20.254588 | K69: =100*(K45/K$43) -> 25.452545 | L69: =100*(L45/L$43) -> 27.31477
C70: Del resto del sector privado | D70: =100*(D46/D$43) -> 30.990956 | E70: =100*(E46/E$43) -> 57.019836 | F70: =100*(F46/F$43) -> -546.70078 | G70: =100*(G46/G$43) -> 51.769318 | H70: =100*(H46/H$43) -> 77.854017 | I70: =100*(I46/I$43) -> 91.59343 | J70: =100*(J46/J$43) -> 47.260705 | K70: =100*(K46/K$43) -> 59.389272 | L70: =100*(L46/L$43) -> 63.734464
C71: Externo | D71: =100*(D47/D$43) -> -6.5312831 | E71: =100*(E47/E$43) -> -20.231036 | F71: =100*(F47/F$43) -> 1921.8898 | G71: =100*(G47/G$43) -> 5.7197922 | H71: =100*(H47/H$43) -> 22.325777 | I71: =100*(I47/I$43) -> -15.823388 | J71: =100*(J47/J$43) -> 32.484707 | K71: =100*(K47/K$43) -> 15.158184 | L71: =100*(L47/L$43) -> 8.9507654
C73: Interno (en porcentaje del total) | D73: =100*(D44/D$44) -> 100 | E73: =100*(E44/E$44) -> 100 | F73: =100*(F44/F$44) -> 100 | G73: =100*(G44/G$44) -> 100 | H73: =100*(H44/H$44) -> 100 | I73: =100*(I44/I$44) -> 100 | J73: =100*(J44/J$44) -> 100 | K73: =100*(K44/K$44) -> 100 | L73: =100*(L44/L$44) -> 100
C74: De sociedades de depósito | D74: =100*(D45/D$44) -> 70.909056 | E74: =100*(E45/E$44) -> 52.574778 | F74: =100*(F45/F$44) -> 69.992653 | G74: =100*(G45/G$44) -> 45.08994 | H74: =100*(H45/H$44) -> -0.23147214 | I74: =100*(I45/I$44) -> 20.919746 | J74: =100*(J45/J$44) -> 30 | K74: =100*(K45/K$44) -> 30 | L74: =100*(L45/L$44) -> 30
C75: Del resto del sector privado | D75: =100*(D46/D$44) -> 29.090944 | E75: =100*(E46/E$44) -> 47.425222 | F75: =100*(F46/F$44) -> 30.007347 | G75: =100*(G46/G$44) -> 54.91006 | H75: =100*(H46/H$44) -> 100.23147 | I75: =100*(I46/I$44) -> 79.080254 | J75: =100*(J46/J$44) -> 70 | K75: =100*(K46/K$44) -> 70 | L75: =100*(L46/L$44) -> 70
BC181: =SERIES(' _x000E_Gob_EOG_Ind'!$C$9,' _x000E_Gob_EOG_Ind'!$D$3:$K$3,' _x000E_Gob_EOG_Ind'!$D$9:$L$9,1)
BC182: =SERIES(' _x000E_Gob_EOG_Ind'!$C$13,' _x000E_Gob_EOG_Ind'!$D$3:$L$3,' _x000E_Gob_EOG_Ind'!$D$13:$L$13,2)
BC183: =SERIES(' _x000E_Gob_EOG_Ind'!$C$10,' _x000E_Gob_EOG_Ind'!$D$3:$K$3,' _x000E_Gob_EOG_Ind'!$D$10:$L$10,3)
BC184: =SERIES(' _x000E_Gob_EOG_Ind'!$C$10,' _x000E_Gob_EOG_Ind'!$D$3:$L$3,' _x000E_Gob_EOG_Ind'!$D$10:$L$10,1)
BC185: =SERIES(' _x000E_Gob_EOG_Ind'!$C$21,' _x000E_Gob_EOG_Ind'!$D$3:$L$3,' _x000E_Gob_EOG_Ind'!$D$21:$L$21,2)
BC186: =SERIES(' _x000E_GOB_EOG_Ind'!$C$26,' _x000E_Gob_EOG_Ind'!$D$3:$L$3,' _x000E_Gob_EOG_Ind'!$D$26:$L$26,3)

Sheet Gob_EOG_Ind
B2: Macronia: Sector del gobierno general, indicadores seleccionados, 2006-12
D3: 2006 | E3: 2007 | F3: 2008 | G3: 2009 | H3: 2010 | I3: 2011 | J3: 2012 | K3: 2013 | L3: 2014
B4: (en porcentaje del PIB)
C5: Estado de las operaciones del gobierno
C6: Ingresos | D6: 14.942174 | E6: 16.244593 | F6: 16.896242 | G6: 15.007707 | H6: 15.486725 | I6: 15.564533 | J6: 15.462876 | K6: 15.332847 | L6: =L34*100/L$30 -> 15.283679
C7: Gastos | D7: 15.90673 | E7: 15.42844 | F7: 15.899072 | G7: 18.195114 | H7: 20.817859 | I7: 19.614825 | J7: 20.017705 | K7: 23.152225 | L7: =L35*100/L$30 -> 27.711481 | P7: Referencia: «When and How to Adjust Beyond the Business Cycle? A Guide to Structural Fiscal Balances», abril de 2011 FMI
C8: de los cuales: gastos primarios | D8: 11.923901 | E8: 12.18954 | F8: 13.591401 | G8: 15.908288 | H8: 18.540138 | I8: 17.301764 | J8: 17.78875 | K8: 19.689076 | L8: =L36*100/L$30 -> 22.459537 | P8: http://www.imf.org/external/pubs/cat/longres.aspx?sk=24787
C9: Resultado operativo neto | D9: -0.96455599 | E9: 0.81615299 | F9: 0.99716989 | G9: -3.1874078 | H9: -5.3311336 | I9: -4.0502929 | J9: -4.5548284 | K9: -7.8193786 | L9: =L6-L7 -> -12.427802
C10: Resultado operativo neto primario | D10: 3.0182733 | E10: 4.0550529 | F10: 3.3048411 | G10: -0.90058182 | H10: -3.0534133 | I10: -1.7372314 | J10: -2.3258736 | K10: -4.3562297 | L10: =L6-L8 -> -7.1758577
C11: Adquisición neta de activos no financieros | D11: 0.13952057 | E11: 0.21745523 | F11: 0.35591191 | G11: 0.45163878 | H11: 0.30849997 | I11: 0.30397498 | J11: 0.18670205 | K11: 0.13047558 | L11: =L38*100/L$30 -> 0.1225554
C12: Préstamo neto/endeudamiento neto | D12: -1.1040766 | E12: 0.59869776 | F12: 0.64125797 | G12: -3.6390466 | H12: -5.6396336 | I12: -4.3542679 | J12: -4.7415305 | K12: -7.9498542 | L12: =L39*100/L$30 -> -12.550357
C13: Saldo global | D13: -4.5515284 | E13: -2.1644321 | F13: 0.58018797 | G13: -3.721602 | H13: -6.0934293 | I13: -4.8895819 | J13: -5.8664381 | K13: -7.9498542 | L13: =L41/L30*100 -> -12.550357
C14: Saldo global primario | D14: -0.56869914 | E14: 1.0744678 | F14: 2.8878592 | G14: -1.434776 | H14: -3.8157089 | I14: -2.5765204 | J14: -3.6374833 | K14: -4.4867053 | L14: =L42*100/L$30 -> -7.2984131
B16: (en miles de millones de moneda nacional, salvo indicación en contrario)
C17: Ajuste en función del ciclo
C18: Ingresos, a precios constantes de 2005 | D18: 1473.9114 | E18: 1706.9831 | F18: 1818.0905 | G18: 1588.5471 | H18: 1718.9099 | I18: 1825.2454 | J18: 1889.2151 | K18: 1958.7146 | L18: =L34/L31*100 -> 2039.3501
C19: Gastos primarios, a precios constantes de 2005 | D19: 1176.1858 | E19: 1280.8779 | F19: 1462.4789 | G19: 1683.8725 | H19: 2057.8158 | I19: 2028.9697 | J19: 2173.3844 | K19: 2515.2068 | L19: =L36/L31*100 -> 2996.8477
C21: Brecha del producto: PIB real/PIB potencial | D21: 1.0221966 | E21: 1.0549052 | F21: 1.0375277 | G21: 0.98420258 | H21: 0.98773719 | I21: 0.98643848 | J21: 1.0027332 | K21: 1.0081132 | L21: =L32/L33 -> 1.0124918
C22: Supuesto: Elasticidad de los ingresos fiscales con respecto al PIB | D22: 1.15 | E22: 1.15 | F22: 1.15 | G22: 1.15 | H22: 1.15 | I22: 1.15 | J22: 1.15 | K22: 1.15 | L22: =K22 -> 1.15
C23: Ingresos ajustados, a precios constantes de 2005 | D23: 1437.1655 | E23: 1605.2171 | F23: 1742.6728 | G23: 1617.9046 | H23: 1743.4741 | I23: 1854.1324 | J23: 1883.2943 | K23: 1940.5974 | L23: =L18*((1/L21)^L22) -> 2010.4421
C25: Resultado operativo neto primario ajustado, a precios constantes de 2005 1/ | D25: 260.97969 | E25: 324.33929 | F25: 280.19387 | G25: -65.967921 | H25: -314.34171 | I25: -174.83725 | J25: -290.09019 | K25: -574.60943 | L25: =L23-L19 -> -986.4056
C26: Resultado operativo neto primario ajustado, en porcentaje del producto potencial | D26: 2.7044785 | E26: 3.2560615 | F26: 2.7016741 | G26: -0.61338272 | H26: -2.7973698 | I26: -1.470682 | J26: -2.3808242 | K26: -4.5345448 | L26: =L25*100/L33 -> -7.4848508
C27: Impulso fiscal (expansivo +) | E27: -0.551583 | F27: 0.55438745 | G27: 3.3150568 | H27: 2.1839871 | I27: -1.3266878 | J27: 0.91014217 | K27: 2.1537206 | L27: =-(L26-K26) -> 2.9503059
B28: (en miles de millones de moneda nacional)
C29: Partidas informativas
C30: PIB nominal | D30: 10964.62 | E30: 12956.322 | F30: 14737.186 | G30: 15747.009 | H30: 17629.078 | I30: 19427.849 | J30: 21157.293 | K30: 23646.186 | L30: =PIB_Nominal!L6 -> 26705.763
C31: Deflactor del PIB (2005 = 100) | D31: 111.15679 | E31: 123.29951 | F31: 136.95856 | G31: 148.76896 | H31: 158.83129 | I31: 165.66835 | J31: 173.16854 | K31: 185.1027 | L31: =IF(ISBLANK(Deflactor_PIB!L$35)," ",Deflactor_PIB!L$35) -> 200.14333
C32: PIB real, a precios constantes de 2005 | D32: 9864.103 | E32: 10508.008 | F32: 10760.325 | G32: 10584.876 | H32: 11099.247 | I32: 11726.953 | J32: 12217.747 | K32: 12774.631 | L32: =PIB_real!L6 -> 13343.319
C33: Producto potencial | D33: 9649.9079 | E33: 9961.0923 | F33: 10371.121 | G33: 10754.773 | H33: 11237.045 | I33: 11888.175 | J33: 12184.444 | K33: 12671.821 | L33: =PIB_real!L19 -> 13178.694
C34: Ingresos | D34: 1638.3526 | E34: 2104.7018 | F34: 2490.0306 | G34: 2363.2649 | H34: 2730.1668 | I34: 3023.8539 | J34: 3271.5261 | K34: 3625.6334 | L34: =IF(ISBLANK(Gob_EOG!L5)," ",Gob_EOG!L5) -> 4081.623
C35: Gasto | D35: 1744.1125 | E35: 1998.9584 | F35: 2343.0758 | G35: 2865.1863 | H35: 3669.9965 | I35: 3810.7387 | J35: 4235.2045 | K35: 5474.6182 | L35: =IF(ISBLANK(Gob_EOG!L15)," ",Gob_EOG!L15) -> 7400.5623
C36: Gastos primarios | D36: 1307.4104 | E36: 1579.3161 | F36: 2002.99 | G36: 2505.0796 | H36: 3268.4554 | I36: 3361.3606 | J36: 3763.618 | K36: 4655.7156 | L36: =IF(ISBLANK(Gob_EOG!L50)," ",Gob_EOG!L50) -> 5997.9906
C37: Resultado operativo neto | D37: -105.7599 | E37: 105.74341 | F37: 146.95478 | G37: -501.9214 | H37: -939.8297 | I37: -786.8848 | J37: -963.6784 | K37: -1848.9848 | L37: =IF(ISBLANK(Gob_EOG!L27)," ",Gob_EOG!L27) -> -3318.9393
C38: Adquisición neta de activos no financieros | D38: 15.2979 | E38: 28.1742 | F38: 52.4514 | G38: 71.1196 | H38: 54.3857 | I38: 59.0558 | J38: 39.5011 | K38: 30.852499 | L38: =IF(ISBLANK(Gob_EOG!L29)," ",Gob_EOG!L29) -> 32.729354
C39: Préstamo neto/endeudamiento neto | D39: -121.0578 | E39: 77.56921 | F39: 94.50338 | G39: -573.041 | H39: -994.2154 | I39: -845.9406 | J39: -1003.1795 | K39: -1879.8373 | L39: =IF(ISBLANK(Gob_EOG!L35)," ",Gob_EOG!L35) -> -3351.6687
C40: Saldo operativo primario | D40: 330.9422 | E40: 525.38571 | F40: 487.04058 | G40: -141.8147 | H40: -538.2886 | I40: -337.5067 | J40: -492.0919 | K40: -1030.0822 | L40: =IF(ISBLANK(Gob_EOG!L51)," ",Gob_EOG!L51) -> -1916.3675
C41: Saldo global | D41: -499.0578 | E41: -280.43079 | F41: 85.50338 | G41: -586.041 | H41: -1074.2154 | I41: -949.9406 | J41: -1241.1795 | K41: -1879.8373 | L41: =IF(ISBLANK(Gob_EOG!L52)," ",Gob_EOG!L52) -> -3351.6687
C42: Saldo global primario | D42: -62.3557 | E42: 139.21151 | F42: 425.58918 | G42: -225.9343 | H42: -672.6743 | I42: -500.5625 | J42: -769.593 | K42: -1060.9347 | L42: =IF(ISBLANK(Gob_EOG!L53)," ",Gob_EOG!L53) -> -1949.0969
C43: Consumo del gobierno general | D43: 590.9284 | E43: 673.3051 | F43: 808.3377 | G43: 1043.216 | H43: 1254.4847 | I43: 1403.8266 | J43: 1522.9592 | K43: 2169.1777 | L43: =Gob_EOG!L16+Gob_EOG!L17 -> 2794.5667
C44: Inversión del gobierno general | D44: 15.2979 | E44: 28.1742 | F44: 52.4514 | G44: 71.1196 | H44: 54.3857 | I44: 59.0558 | J44: 39.5011 | K44: 30.852499 | L44: =Gob_EOG!L29 -> 32.729354
C45: Consumo del sector público | D45: 1076.2341 | E45: 1265.7069 | F45: 1555.4684 | G45: 1931.9535 | H45: 2298.9 | I45: 2496.35 | J45: 2733.1145 | K45: 3337.8524 | L45: =PIB_Nominal!L9 -> 4300.1784
C46: Inversión del sector público | D46: 234.02446 | E46: 286.08395 | F46: 335.24812 | G46: 328.85775 | H46: 425.53619 | I46: 510.29972 | J46: 534.88768 | K46: 590.02673 | L46: =PIB_Nominal!L12 -> 666.38523
C48: Notas:
C49: 1/ Suponer que los gastos primarios no se ven afectados por el ciclo económico.

Sheet Gob_Balance
B2: Macronia: Balance del gobierno general, 2006-12
D3: 2006 | E3: 2007 | F3: 2008 | G3: 2009 | H3: 2010 | I3: 2011 | J3: 2012 | K3: 2013 | L3: 2014
B4: (en miles de millones de moneda nacional)
C5: Saldo, final del año
C6: Activos | D6: 7857.2353 | E6: 7566.4095 | F6: 7772.7656 | G6: 7888.8852 | H6: 7958.2709 | I6: 8044.3267 | J6: 7213.8278 | K6: 7255.4257 | L6: =L7+L8 -> 7295.8388
C7: No financieros | D7: 3210.2353 | E7: 3249.4095 | F7: 3296.8609 | G7: 3374.9805 | H7: 3404.3662 | I7: 3476.422 | J7: 2724.9231 | K7: 2755.7756 | L7: =K7+L26+L42 -> 2788.5049
C8: Financieros | D8: 4647 | E8: 4317 | F8: 4475.9047 | G8: 4513.9047 | H8: 4553.9047 | I8: 4567.9047 | J8: 4488.9047 | K8: 4499.6502 | L8: =L9+L12 -> 4507.3338
C9: Internos | D9: 4532 | E9: 4226 | F9: 4364.9047 | G9: 4394.9047 | H9: 4429.9047 | I9: 4440.9047 | J9: 4345.9047 | K9: 4345.9047 | L9: =L10+L11 -> 4345.9047
C10: Depósitos en el sistema bancario | D10: 185 | E10: 183 | F10: 188 | G10: 190 | H10: 165 | I10: 135 | J10: 88 | K10: 88 | L10: =K10+L29+L45 -> 88
C11: Acciones y otras participaciones de capital | D11: 4347 | E11: 4043 | F11: 4176.9047 | G11: 4204.9047 | H11: 4264.9047 | I11: 4305.9047 | J11: 4257.9047 | K11: 4257.9047 | L11: =K11+L30+L46 -> 4257.9047
C12: Externos | D12: 115 | E12: 91 | F12: 111 | G12: 119 | H12: 124 | I12: 127 | J12: 143 | K12: 153.74548 | L12: =K12+L31+L47 -> 161.42913
C14: Pasivos | D14: 6498.0763 | E14: 6152.5071 | F14: 6149.9084 | G14: 6762.9494 | H14: 7747.1648 | I14: 8559.1054 | J14: 9436.2849 | K14: 11374.463 | L14: =L15+L18 -> 14813.916
C15: Internos | D15: 5705.438 | E15: 5339.9565 | F15: 5400.3016 | G15: 5955.2779 | H15: 6708.7596 | I15: 7622.1767 | J15: 8169.407 | K15: 9764.2952 | L15: =L16+L17 -> 12815.964
C16: Frente a instituciones de depósito | D16: 709.20198 | E16: 490.76353 | F16: 523.90162 | G16: 784.5108 | H16: 782.74123 | I16: 979.47411 | J16: 555.47593 | K16: 1033.9424 | L16: =K16+L35+L51 -> 1949.443
C17: Frente al resto del sector privado | D17: 4996.236 | E17: 4849.193 | F17: 4876.4 | G17: 5170.7671 | H17: 5926.0184 | I17: 6642.7026 | J17: 7613.9311 | K17: 8730.3528 | L17: =K17+L36+L52 -> 10866.521
C18: Externos | D18: 792.6383 | E18: 812.55053 | F18: 749.60676 | G18: 807.67144 | H18: 1038.4052 | I18: 936.92866 | J18: 1223 | K18: 1610.1676 | L18: =K18+L37+L53 -> 1997.9518
C20: Patrimonio neto (PN) | D20: 1359.159 | E20: 1413.9024 | F20: 1622.8572 | G20: 1125.9358 | H20: 211.10609 | I20: -514.77871 | J20: -2222.4571 | K20: -4119.037 | L20: =L6-L14 -> -7518.0769
C21: Patrimonio financiero neto (PFN) | D21: -1851.0763 | E21: -1835.5071 | F21: -1674.0037 | G21: -2249.0447 | H21: -3193.2601 | I21: -3991.2007 | J21: -4947.3802 | K21: -6874.8126 | L21: =L8-L14 -> -10306.582
C24: Transacciones
C25: Adquisición neta de activos | D25: -279.7021 | E25: -239.8258 | F25: 144.3561 | G25: 111.1196 | H25: 44.3857 | I25: 25.0558 | J25: -86.4989 | K25: 30.852499 | L25: =L26+L27 -> 32.729354
C26: No financieros | D26: 15.2979 | E26: 28.1742 | F26: 52.4514 | G26: 71.1196 | H26: 54.3857 | I26: 59.0558 | J26: 39.5011 | K26: 30.852499 | L26: =Gob_EOG!L29 -> 32.729354
C27: Financieros | D27: -295 | E27: -268 | F27: 91.9047 | G27: 40 | H27: -10 | I27: -34 | J27: -126 | K27: 0 | L27: =Gob_EOG!L36 -> 0
C28: Internos | D28: -297 | E28: -265 | F28: 86.9047 | G28: 39 | H28: -12 | I28: -30 | J28: -132 | K28: 0 | L28: =Gob_EOG!L37 -> 0
C29: Depósitos en el sistema bancario | D29: -10 | E29: -2 | F29: 5 | G29: 2 | H29: -25 | I29: -30 | J29: -47 | K29: 0 | L29: =Gob_EOG!L38 -> 0
C30: Acciones y otras participaciones de capital | D30: -287 | E30: -263 | F30: 81.9047 | G30: 37 | H30: 13 | I30: 0 | J30: -85 | K30: 0 | L30: =Gob_EOG!L39 -> 0
C31: Externos | D31: 2 | E31: -3 | F31: 5 | G31: 1 | H31: 2 | I31: -4 | J31: 6 | K31: 0 | L31: =Gob_EOG!L42 -> 0
C33: Incurrimiento neto de pasivos | D33: -173.9422 | E33: -345.56921 | F33: -2.59868 | G33: 613.041 | H33: 984.2154 | I33: 811.9406 | J33: 877.1795 | K33: 1879.8373 | L33: =Gob_EOG!L43 -> 3351.6687
C34: Internos | D34: -185.30286 | E34: -415.48144 | F34: 47.345085 | G34: 577.97633 | H34: 764.48166 | I34: 940.41712 | J34: 592.23031 | K34: 1594.8881 | L34: =Gob_EOG!L44 -> 3051.6687
C35: Frente a instituciones de depósito | D35: -131.39651 | E35: -218.43845 | F35: 33.138081 | G35: 260.60918 | H35: -1.7695621 | I35: 196.73287 | J35: 177.66909 | K35: 478.46644 | L35: =Gob_EOG!L45 -> 915.5006
C36: Frente al resto del sector privado | D36: -53.90635 | E36: -197.043 | F36: 14.207004 | G36: 317.36715 | H36: 766.25123 | I36: 743.68424 | J36: 414.56122 | K36: 1116.4217 | L36: =Gob_EOG!L46 -> 2136.1681
C37: Externos | D37: 11.360658 | E37: 69.912232 | F37: -49.943765 | G37: 35.064671 | H37: 219.73374 | I37: -128.47652 | J37: 284.94919 | K37: 284.94919 | L37: =Gob_EOG!L47 -> 300
C40: Otros flujos económicos (incluidas variaciones por revalorización) | D40: 96 | E40: -51 | F40: 62 | G40: 5 | H40: 25 | I40: 61 | J40: -744 | K40: -91.472962 | L40: =L41-L49 -> -80.100552
C41: Activos | D41: 96 | E41: -51 | F41: 62 | G41: 5 | H41: 25 | I41: 61 | J41: -744 | K41: 10.745476 | L41: =L42+L43 -> 7.6836562
C42: No financieros 1/ | D42: 23 | E42: 11 | F42: -5 | G42: 7 | H42: -25 | I42: 13 | J42: -791 | K42: 0 | L42: 0
C43: Financieros | D43: 73 | E43: -62 | F43: 67 | G43: -2 | H43: 50 | I43: 48 | J43: 47 | K43: 10.745476 | L43: =L44+L47 -> 7.6836562
C44: Internos | D44: 63 | E44: -41 | F44: 52 | G44: -9 | H44: 47 | I44: 41 | J44: 37 | K44: 0 | L44: =L45+L46 -> 0
C45: Depósitos en el sistema bancario | D45: 0 | E45: 0 | F45: 0 | G45: 0 | H45: 0 | I45: 0 | J45: 0 | K45: 0 | L45: 0
C46: Acciones y otras participaciones de capital | D46: 63 | E46: -41 | F46: 52 | G46: -9 | H46: 47 | I46: 41 | J46: 37 | K46: 0 | L46: 0
C47: Externos | D47: 10 | E47: -21 | F47: 15 | G47: 7 | H47: 3 | I47: 7 | J47: 10 | K47: 10.745476 | L47: =(K12/'TC nominal'!H$14)*('TC nominal'!I$14-'TC nominal'!H$14) -> 7.6836562
C49: Pasivos | D49: 0 | E49: 0 | F49: 0 | G49: 0 | H49: 0 | I49: 0 | J49: 0 | K49: 102.21844 | L49: =L50+L53 -> 87.784209
C50: Internos | D50: 0 | E50: 50 | F50: 13 | G50: -23 | H50: -11 | I50: -27 | J50: -45 | K50: 0 | L50: =L51+L52 -> 0
C51: Frente a instituciones de depósito | D51: 0 | E51: 0 | F51: 0 | G51: 0 | H51: 0 | I51: 0 | J51: 0 | K51: 0 | L51: 0
C52: Frente al resto del sector privado | D52: 0 | E52: 50 | F52: 13 | G52: -23 | H52: -11 | I52: -27 | J52: -45 | K52: 0 | L52: 0
C53: Externa | D53: 0 | E53: -50 | F53: -13 | G53: 23 | H53: 11 | I53: 27 | J53: 45 | K53: 102.21844 | L53: =(K18/'TC nominal'!H$14)*('TC nominal'!I$14-'TC nominal'!H$14)+(L37/'TC nominal'!I13)*('TC nominal'!I14-'TC nominal'!I13) -> 87.784209
C56: Verificación de coherencia
C57: PNt-1 + RONt + OET(Neto)t - PNt = 0 | D57: … | E57: 0 | F57: 0 | G57: 0 | H57: -1.3642421e-12 | I57: -1.3642421e-12 | J57: 0 | K57: -43.877845 | L57: =K20+L62+L40-L20 -> 0
C58: PFNt-1 + PENt + OET(activos fin.)t - OET(pasivos)t - PFNt = 0 | D58: … | E58: 0 | F58: 0 | G58: 0 | H58: 0 | I58: 0 | J58: 0 | K58: -43.877845 | L58: =K21+L63+L43-L49-L21 -> 0
C61: Partidas informativas
C62: Resultado operativo neto (RON) | D62: -105.7599 | E62: 105.74341 | F62: 146.95478 | G62: -501.9214 | H62: -939.8297 | I62: -786.8848 | J62: -963.6784 | K62: -1848.9848 | L62: =IF(ISBLANK(Gob_EOG!L27)," ",Gob_EOG!L27) -> -3318.9393
C63: Préstamo neto/endeudamiento neto (PEN) | D63: -121.0578 | E63: 77.56921 | F63: 94.50338 | G63: -573.041 | H63: -994.2154 | I63: -845.9406 | J63: -1003.1795 | K63: -1879.8373 | L63: =IF(ISBLANK(Gob_EOG!L35)," ",Gob_EOG!L35) -> -3351.6687
C65: Notas:
C66: 1/ A finales de 2012 Macronia sufrió un desastre natural, que produjo una cuantiosa pérdida de activos no financieros.

Sheet Gob_Stock_Ind
B2: Macronia: Sector del gobierno general, indicadores seleccionados, 2006-12
D3: 2006 | E3: 2007 | F3: 2008 | G3: 2009 | H3: 2010 | I3: 2011 | J3: 2012 | K3: 2013 | L3: 2014
B4: (porcentaje)
C5: Selected stock indicators
C6: Assets-to-GDP | D6: 71.659895 | E6: 58.399362 | F6: 52.742536 | G6: 50.097673 | H6: 45.142865 | I6: 41.406162 | J6: 34.096175 | K6: 30.683281 | L6: =L25/L$24*100 -> 27.319342
C7: Liabilities-to-GDP | D7: 59.264035 | E7: 47.486525 | F7: 41.730548 | G7: 42.947517 | H7: 43.945377 | I7: 44.055857 | J7: 44.600625 | K7: 48.102738 | L7: =L26/L$24*100 -> 55.470857
C8: Net worth-to-GDP | D8: 12.39586 | E8: 10.912838 | F8: 11.011988 | G8: 7.1501565 | H8: 1.197488 | I8: -2.6496948 | J8: -10.504449 | K8: -17.419456 | L8: =L28/L$24*100 -> -28.151515
C9: Net financial worth-to-GDP | D9: -16.882265 | E9: -14.166884 | F9: -11.359046 | G9: -14.282361 | H9: -18.113597 | I9: -20.543708 | J9: -23.383805 | K9: -29.073664 | L9: =L29/L$24*100 -> -38.5931
A10: DROP | C10: General Government liabilities-to-GDP | D10: 59.264035 | E10: 47.486525 | F10: 41.730548 | G10: 42.947517 | H10: 43.945377 | I10: 44.055857 | J10: 44.600625 | K10: 48.102738 | L10: =L7 -> 55.470857
C11: Liabilities-to-revenues | D11: 396.62258 | E11: 292.32203 | F11: 246.98124 | G11: 286.16976 | H11: 283.76159 | I11: 283.05287 | J11: 288.43679 | K11: 313.72346 | L11: =L26/L30*100 -> 362.94179
C14: Indicadores seleccionados
C15: Pagos de intereses/PIB | D15: 3.9828293 | E15: 3.2388999 | F15: 2.3076712 | G15: 2.286826 | H15: 2.2777204 | I15: 2.3130615 | J15: 2.2289548 | K15: 3.463149 | L15: =L31/L24*100 -> 5.2519441
C16: Pagos de intereses/gastos | D16: 25.038643 | E16: 20.993048 | F16: 14.514503 | G16: 12.568352 | H16: 10.941185 | I16: 11.792414 | J16: 11.134917 | K16: 14.958169 | L16: =L31/L33*100 -> 18.952232
C17: Pagos de intereses/ingresos | D17: 26.654952 | E17: 19.938326 | F17: 13.657896 | G17: 15.237678 | H17: 14.707567 | I17: 14.861105 | J17: 14.414878 | K17: 22.586471 | L17: =L31/L30*100 -> 34.363089
C18: Tasa de interés implícita media | D18: …. | E18: 6.6343549 | F18: 5.5287647 | G18: 5.5774904 | H18: 5.5346374 | I18: 5.5117215 | J18: 5.2411923 | K18: 7.8699973 | L18: =L31/AVERAGE(K26:L26)*100 -> 10.711406
C19: Tasa de interés sobre deuda interna | E19: 6.0054677 | F19: 4.7546101 | G19: 4.9427508 | H19: 5.316453 | I19: 5.455003 | J19: 5.3773568 | K19: 9.3329376 | L19: =L20+L21 -> 11.785123
C20: IBR (tasa de préstamos interbancarios) | E20: 7 | F20: 11.5 | G20: 8.25 | H20: 8 | I20: 8 | J20: 9.25 | K20: 12.2 | L20: ='Regla de Taylor '!F32 -> 14.671691 | M20: ='regla de Taylor '!F32
C21: Diferencial de tasas de interés sobre deuda interna e IBR media a dos años | F21: -4.4953899 | G21: -4.9322492 | H21: -2.808547 | I21: -2.544997 | J21: -3.2476432 | K21: -2.8670624 | L21: =AVERAGE(I21:K21) -> -2.8865676
B22: (en miles de millones de moneda nacional)
C23: Partidas informativas
C24: PIB nominal, en miles de millones de moneda local | D24: 10964.62 | E24: 12956.322 | F24: 14737.186 | G24: 15747.009 | H24: 17629.078 | I24: 19427.849 | J24: 21157.293 | K24: 23646.186 | L24: =PIB_Nominal!L6 -> 26705.763
C25: Activos | D25: 7857.2353 | E25: 7566.4095 | F25: 7772.7656 | G25: 7888.8852 | H25: 7958.2709 | I25: 8044.3267 | J25: 7213.8278 | K25: 7255.4257 | L25: =Gob_Balance!L6 -> 7295.8388
C26: Pasivos | D26: 6498.0763 | E26: 6152.5071 | F26: 6149.9084 | G26: 6762.9494 | H26: 7747.1648 | I26: 8559.1054 | J26: 9436.2849 | K26: 11374.463 | L26: =Gob_Balance!L14 -> 14813.916
C27: Pasivos internos | D27: 5705.438 | E27: 5339.9565 | F27: 5400.3016 | G27: 5955.2779 | H27: 6708.7596 | I27: 7622.1767 | J27: 8169.407 | K27: 9764.2952 | L27: =Gob_Balance!L15 -> 12815.964
C28: Patrimonio neto | D28: 1359.159 | E28: 1413.9024 | F28: 1622.8572 | G28: 1125.9358 | H28: 211.10609 | I28: -514.77871 | J28: -2222.4571 | K28: -4119.037 | L28: =IF(ISBLANK(Gob_Balance!L20)," ",Gob_Balance!L20) -> -7518.0769
C29: Patrimonio financiero neto | D29: -1851.0763 | E29: -1835.5071 | F29: -1674.0037 | G29: -2249.0447 | H29: -3193.2601 | I29: -3991.2007 | J29: -4947.3802 | K29: -6874.8126 | L29: =IF(ISBLANK(Gob_Balance!L21)," ",Gob_Balance!L21) -> -10306.582
C30: Ingresos | D30: 1638.3526 | E30: 2104.7018 | F30: 2490.0306 | G30: 2363.2649 | H30: 2730.1668 | I30: 3023.8539 | J30: 3271.5261 | K30: 3625.6334 | L30: =IF(ISBLANK(Gob_EOG!L5)," ",Gob_EOG!L5) -> 4081.623
C31: Pagos de intereses | D31: 436.7021 | E31: 419.6423 | F31: 340.0858 | G31: 360.1067 | H31: 401.5411 | I31: 449.3781 | J31: 471.5865 | K31: 818.90264 | L31: =Gob_EOG!L19 -> 1402.5718
C32: Pagos de intereses internos | D32: 349.4543 | E32: 331.6638 | F32: 255.3287 | G32: 280.639 | H32: 336.6388 | I32: 390.8765 | J32: 424.5849 | K32: 762.44566 | L32: =Gob_EOG!L20 -> 1330.5556
C33: Gastos | D33: 1744.1125 | E33: 1998.9584 | F33: 2343.0758 | G33: 2865.1863 | H33: 3669.9965 | I33: 3810.7387 | J33: 4235.2045 | K33: 5474.6182 | L33: =IF(ISBLANK(Gob_EOG!L15)," ",Gob_EOG!L15) -> 7400.5623
B87: NOTE: No está claro cuál es la serie 1, serie 3.

Sheet Gob_GTR_Proy
C2: Macronia: Impuestos, 2008-2013
D3: 2008 | E3: 2009 | F3: 2010 | G3: 2011 | H3: 2012 | I3: 2013 | J3: 2014
C4: (en miles de millones de moneda nacional)
C6: Ingreso tributario | D6: 2408.5786 | E6: 2262.2893 | F6: 2480.4111 | G6: 2768.9008 | H6: 3007.0638 | I6: 3330.0604 | J6: =SUM(J7:J10) -> 3747.8059
C7: Impuestos sobre el ingreso, las utilidades y las ganancias de capital | D7: 689.2247 | E7: 687.4203 | F7: 752.1716 | G7: 832.2036 | H7: 891.4239 | I7: 983.36609 | J7: =J57 -> 1094.9239
C8: Impuestos sobre bienes y servicios | D8: 465.051 | E8: 476.2986 | F8: 511.6052 | G8: 547.7084 | H8: 610.796 | I8: 672.89058 | J8: =J58 -> 746.7644
C9: Impuestos sobre el comercio internacional | D9: 797.421 | E9: 593.6164 | F9: 686.6615 | G9: 803.4734 | H9: 856.2116 | I9: 957.70308 | J9: =J59 -> 1108.0894
C10: Otros impuestos | D10: 456.8819 | E10: 504.954 | F10: 529.9728 | G10: 585.5154 | H10: 648.6323 | I10: 716.10066 | J10: =J60 -> 798.02819
C12: (variaciones porcentuales)
C14: Ingreso tributario | E14: -6.0736776 | F14: 9.6416404 | G14: 11.630721 | H14: 8.6013555 | I14: 10.741263 | J14: =100*(J6/I6-1) -> 12.544681
C15: Impuestos sobre el ingreso, las utilidades y las ganancias de capital | E15: -0.26180141 | F15: 9.4194629 | G15: 10.640125 | H15: 7.1160831 | I15: 10.314082 | J15: =100*(J7/I7-1) -> 11.344485
C16: Impuestos sobre bienes y servicios | E16: 2.4185734 | F16: 7.4127029 | G16: 7.0568477 | H16: 11.518465 | I16: 10.166174 | J16: =100*(J8/I8-1) -> 10.978577
C17: Impuestos sobre el comercio internacional | E17: -25.557967 | F17: 15.674281 | G17: 17.01157 | H17: 6.5637767 | I17: 11.853551 | J17: =100*(J9/I9-1) -> 15.70281
C18: Otros impuestos | E18: 10.521778 | F18: 4.9546691 | G18: 10.480274 | H18: 10.779716 | I18: 10.401634 | J18: =100*(J10/I10-1) -> 11.440784
C20: PIB nominal (base tributaria representativa) | D20: 14737.186 | E20: 15747.009 | F20: 17629.078 | G20: 19427.849 | H20: 21157.293 | I20: 23646.186 | J20: =PIB_Nominal!L6 -> 26705.763
C21: Consumo (base tributaria representativa) | D21: 12200.565 | E21: 13108.591 | F21: 14576.657 | G21: 16016.788 | H21: 17760.343 | I21: 19985.487 | J21: =PIB_Nominal!L7 -> 22689.509
C22: Importaciones (base tributaria representativa) | D22: 8666.0425 | E22: 7023.6833 | F22: 7680.7522 | G22: 8717.3303 | H22: 9780.042 | I22: 10781.029 | J22: =PIB_Nominal!L16 -> 12242.79
C24: (variación de la base tributaria representativa, porcentaje)
C26: PIB nominal (base tributaria representativa) | E26: 6.8522112 | F26: 11.951913 | G26: 10.203434 | H26: 8.9018811 | I26: 11.763758 | J26: =100*(J20/I20-1) -> 12.938988
C27: Consumo (base tributaria representativa) | E27: 7.4424907 | F27: 11.199268 | G27: 9.8797054 | H27: 10.885793 | I27: 12.528725 | J27: =100*(J21/I21-1) -> 13.529925
C28: Importaciones (base tributaria representativa) | E28: -18.951663 | F28: 9.3550471 | G28: 13.495789 | H28: 12.190793 | I28: 10.234992 | J28: =100*(J22/I22-1) -> 13.558648
C31: (en porcentaje)
C32: Tasas efectivas del impuesto
C33: Ingreso tributario
C34: Impuestos sobre el ingreso, las utilidades y las ganancias de capital | D34: 4.6767728 | E34: 4.3654023 | F34: 4.2666531 | G34: 4.2835601 | H34: 4.2133173 | I34: =100*(I7/I20) -> 4.1586668 | J34: =I34 -> 4.1586668
C35: Impuestos sobre bienes y servicios | D35: 3.8117169 | E35: 3.6334843 | F35: 3.5097566 | G35: 3.4195894 | H35: 3.4391003 | I35: =100*(I8/I21) -> 3.3668961 | J35: =I35 -> 3.3668961
C36: Impuestos sobre el comercio internacional | D36: 9.2016743 | E36: 8.4516396 | F36: 8.9400294 | G36: 9.2169663 | H36: 8.7546822 | I36: =100*(I9/I22) -> 8.8832256 | J36: =I36 -> 8.8832256
C37: Otros impuestos | D37: 3.1001977 | E37: 3.2066661 | F37: 3.0062423 | G37: 3.0137942 | H37: 3.0657622 | I37: =100*(I10/I20) -> 3.0283982 | J37: =I37 -> 3.0283982
C39: Capacidad de reacción | M39: b | N39: =(I7/H7-1)/(I20/H20-1) -> 0.87676761
C40: Impuestos sobre el ingreso, las utilidades y las ganancias de capital | E40: -0.038206851 | F40: 0.7881134 | G40: 1.0427985 | H40: 0.79939095 | I40: =(I7/H7-1)/(I20/H20-1) -> 0.87676761 | J40: =I40 -> 0.87676761 | M40: tmi | N40: =(I7-H7)/(I20-H20) -> 0.036941002
C41: Impuestos sobre bienes y servicios | E41: 0.32496828 | F41: 0.66189171 | G41: 0.71427714 | H41: 1.058119 | I41: =(I8/H8-1)/(I21/H21-1) -> 0.81142929 | J41: =I41 -> 0.81142929 | M41: tei | N41: =100*(J7/J20) -> 4.0999537
C42: Impuestos sobre el comercio internacional | E42: 1.3485871 | F42: 1.6754892 | G42: 1.2605094 | H42: 0.53842081 | I42: =(I9/H9-1)/(I22/H22-1) -> 1.1581398 | J42: =I42 -> 1.1581398
C43: Otros impuestos | E43: 1.5355303 | F43: 0.4145503 | G43: 1.027132 | H43: 1.2109482 | I43: =(I10/H10-1)/(I20/H20-1) -> 0.88421017 | J43: =I43 -> 0.88421017
C47: Macronia: Pronóstico de impuestos
C48: Método 1: Usando tasas efectivas de impuesto (TEI)
C49: Ingreso tributario | J49: =SUM(J50:J53) -> 3770.8474
C50: Impuestos sobre el ingreso, las utilidades y las ganancias de capital | J50: =J20*J34/100 -> 1110.6037
C51: Impuestos sobre bienes y servicios | J51: =J21*J35/100 -> 763.93218
C52: Impuestos sobre el comercio internacional | J52: =J22*J36/100 -> 1087.5547
C53: Otros impuestos | J53: =J20*J37/100 -> 808.75684
C55: Método 2: Usando capacidad de reacción
C56: Ingreso tributario | J56: =SUM(J57:J60) -> 3747.8059
C57: Impuestos sobre el ingreso, las utilidades y las ganancias de capital | J57: =I7*(1+(J40*J26/100)) -> 1094.9239
C58: Impuestos sobre bienes y servicios | J58: =I8*(1+(J41*J27)/100) -> 746.7644
C59: Impuestos sobre el comercio internacional | J59: =I9*(1+(J42*J28)/100) -> 1108.0894
C60: Otros impuestos | J60: =I10*(1+(J43*J26)/100) -> 798.02819

Sheet Hoja-Gob_Exp_Proy.
B1: Hoja de cálculo para pronosticar el gasto del gobierno general en 2014
B2: NO AGREGAR NI ELEMINAR FILAS NI COLUMNAS EN ESTA HOJA. Si lo hace, las direcciones para 'buscar objetivo' serán diferentes de las indicadas en las instrucciones.
I3: Pronóstico
C4: =Gob_EOG!F3 -> 2008 | D4: =Gob_EOG!G3 -> 2009 | E4: =Gob_EOG!H3 -> 2010 | F4: =Gob_EOG!I3 -> 2011 | G4: =Gob_EOG!J3 -> 2012 | H4: 2013 | I4: 2014 | K4: Metodología
C6: (en miles de millones de moneda nacional, salvo indicación en contrario)
B8: Ingresos | C8: =Gob_EOG!F5 -> 2490.0306 | D8: =Gob_EOG!G5 -> 2363.2649 | E8: =Gob_EOG!H5 -> 2730.1668 | F8: =Gob_EOG!I5 -> 3023.8539 | G8: =Gob_EOG!J5 -> 3271.5261 | H8: =Gob_EOG!K5 -> 3625.6334 | I8: =Gob_EOG!L5 -> 4081.623 | K8: De la pestaña Gob_EOG
B10: Gastos | C10: =Gob_EOG!F15 -> 2343.0758 | D10: =Gob_EOG!G15 -> 2865.1863 | E10: =Gob_EOG!H15 -> 3669.9965 | F10: =F11+F12+F13+F15+F28+F29+F30+F31 -> 3810.7387 | G10: =G11+G12+G13+G15+G28+G29+G30+G31 -> 4235.2045 | H10: =H11+H12+H13+H15+H28+H29+H30+H31 -> 5474.6182 | I10: =I11+I12+I13+I15+I28+I29+I30+I31 -> 7400.5623
B11: Remuneración de empleados | C11: =Gob_EOG!F16 -> 720.71 | D11: =Gob_EOG!G16 -> 936.8567 | E11: =Gob_EOG!H16 -> 1133.809 | F11: =Gob_EOG!I16 -> 1268.1951 | G11: =Gob_EOG!J16 -> 1380.02 | H11: 2010.5531 | I11: =H11*(1+$I$46/100)*(1+$I$49/100) -> 2590.2094 | K11: Tasa de crecimiento dada (ver partidas informativas más adelante)
B12: Uso de bienes y servicios | C12: =Gob_EOG!F17 -> 87.6277 | D12: =Gob_EOG!G17 -> 106.3593 | E12: =Gob_EOG!H17 -> 120.6757 | F12: =Gob_EOG!I17 -> 135.6315 | G12: =Gob_EOG!J17 -> 142.9392 | H12: 158.62466 | I12: =H12*(1+$I$46/100)*(1+$I$49/100) -> 204.35724 | K12: Tasa de crecimiento dada (ver partidas informativas más adelante)
B13: Consumo de capital fijo | C13: =Gob_EOG!F18 -> 9 | D13: =Gob_EOG!G18 -> 11 | E13: =Gob_EOG!H18 -> 10 | F13: =Gob_EOG!I18 -> 13 | G13: =Gob_EOG!J18 -> 12 | H13: 13.316822 | I13: =H13*(1+$I$46/100)*(1+$I$49/100) -> 17.156154 | K13: Suponer que es igual a crecimiento del PIB nominal
B15: Intereses | C15: =Gob_EOG!F19 -> 340.0858 | D15: =Gob_EOG!G19 -> 360.1067 | E15: =Gob_EOG!H19 -> 401.5411 | F15: =Gob_EOG!I19 -> 449.3781 | G15: =Gob_EOG!J19 -> 471.5865 | H15: =H16+H25 -> 818.90264 | I15: =I16+I25 -> 1402.5718
B16: 1. Pagos de intereses de la deuda externa | C16: =Gob_EOG!F21 -> 84.7571 | D16: =Gob_EOG!G21 -> 79.4677 | E16: =Gob_EOG!H21 -> 64.9023 | F16: =Gob_EOG!I21 -> 58.5016 | G16: =Gob_EOG!J21 -> 47.0016 | H16: =H17/100*AVERAGE(G18,H18)*H24/1000 -> 56.456986 | I16: =I17/100*AVERAGE(H18,I18)*I24/1000 -> 72.016115 | K16: Tasa de interés * stock de deuda 2013 * tipo de cambio medio
B17: Tasa de interés de la deuda externa | G17: 6 | H17: 4 | I17: 4 | K17: Supuesto exógeno LIBOR + diferencial de 3%
B18: Stock de deuda externa (en millones de USD, f.d.p.) | C18: =Gob_Balance!F18/'TC nominal'!C14*1000 -> 1349.5 | D18: =Gob_Balance!G18/'TC nominal'!D14*1000 -> 1428.9 | E18: =Gob_Balance!H18/'TC nominal'!E14*1000 -> 2024.3 | F18: =Gob_Balance!I18/'TC nominal'!F14*1000 -> 1835.1 | G18: =Gob_Balance!J18/'TC nominal'!G14*1000 -> 2393.2563 | H18: =Gob_Balance!K18/'TC nominal'!H14*1000 -> 2930.6742 | I18: =H18+Gob_EOG!L47/I24*1000 -> 3463.394 | K18: Stock de 2013 en USD + endeudamiento externo neto en 2014 (MN/tipo de cambio medio)
B19: Net foreign borrowing (in billions of national currency) | I19: =+I38 -> 300
B20: 2. Pagos de intereses de deuda del banco central | K20: Tasa de interés * stock de deuda medio 1995-96
B21: Pagos de intereses de deuda del banco central | K21: De la unidad 12, sección 6.2
B22: Stock de deuda del banco central | C22: 0 | D22: 0 | E22: 0 | F22: 0 | G22: 0 | H22: 0 | I22: 0 | K22: stock 1995 + endeudamiento banco central neto en 1996
B23: Endeudamiento del banco central neto | I23: =I39 -> 3051.6687 | K23: De la unidad 12, sección 6.2
B24: Tipo de cambio (promedio) | C24: ='TC nominal'!C13 -> 526.23551 | D24: ='TC nominal'!D13 -> 573.28796 | E24: ='TC nominal'!E13 -> 525.8292 | F24: ='TC nominal'!F13 -> 506.4 | G24: ='TC nominal'!G13 -> 510.78961 | H24: ='TC nominal'!H13 -> 530.21903 | I24: ='TC nominal'!I13 -> 563.14785
B25: 2. Pagos de intereses por deuda interna | C25: =Gob_EOG!F20 -> 255.3287 | D25: =Gob_EOG!G20 -> 280.639 | E25: =Gob_EOG!H20 -> 336.6388 | F25: =Gob_EOG!I20 -> 390.8765 | G25: =Gob_EOG!J20 -> 424.5849 | H25: =H26/100*G27 -> 762.44566 | I25: =I26/100*AVERAGE(H27,I27) -> 1330.5556 | K25: Tasa de interés * 12 stock de deuda de gob. gen.
B26: Tasa de interés sobre deuda interna | H26: =Gob_Stock_Ind!K19 -> 9.3329376 | I26: =Gob_Stock_Ind!L19 -> 11.785123 | K26: De la hoja Gob_Stock_Ind
B27: Stock de deuda externa | C27: =Gob_Balance!F15 -> 5400.3016 | D27: =Gob_Balance!G15 -> 5955.2779 | E27: =Gob_Balance!H15 -> 6708.7596 | F27: =Gob_Balance!I15 -> 7622.1767 | G27: =Gob_Balance!J15 -> 8169.407 | H27: =Gob_Balance!K15 -> 9764.2952 | I27: =H27+I40 -> 12815.964 | K27: stock 2013 stock + endeudamiento interno neto en 2014
B28: Subsidios | C28: =Gob_EOG!F22 -> 1042.2689 | D28: =Gob_EOG!G22 -> 1246.8462 | E28: =Gob_EOG!H22 -> 1758.4533 | F28: =Gob_EOG!I22 -> 1669.5427 | G28: =Gob_EOG!J22 -> 1946.3238 | H28: =Gob_EOG!K22 -> 2159.904 | I28: =H28*(1+$I$46/100)*(1+$I$49/100) -> 2782.6192 | K28: Suponer que es igual a crecimiento del PIB nominal
B29: Donaciones | C29: =Gob_EOG!F23 -> 7.58132 | D29: =Gob_EOG!G23 -> 26.0885 | E29: =Gob_EOG!H23 -> 30.1683 | F29: =Gob_EOG!I23 -> 29.5888 | G29: =Gob_EOG!J23 -> 15.3073 | H29: =Gob_EOG!K23 -> 16.987049 | I29: =H29*(1+$I$46/100)*(1+$I$49/100) -> 21.884533 | K29: Suponer que es igual a crecimiento del PIB nominal
B30: Prestaciones sociales | C30: =Gob_EOG!F24 -> 135.8021 | D30: =Gob_EOG!G24 -> 177.9289 | E30: =Gob_EOG!H24 -> 215.3491 | F30: =Gob_EOG!I24 -> 245.4025 | G30: =Gob_EOG!J24 -> 267.0277 | H30: =Gob_EOG!K24 -> 296.33003 | I30: =H30*(1+$I$46/100)*(1+$I$49/100) -> 381.76402 | K30: Suponer que es igual a crecimiento del PIB nominal
B31: Otros gastos | C31: =Gob_EOG!F25 -> 0 | D31: =Gob_EOG!G25 -> 0 | E31: =Gob_EOG!H25 -> 0 | F31: =Gob_EOG!I25 -> 0 | G31: =Gob_EOG!J25 -> 0 | H31: =Gob_EOG!K25 -> 0 | I31: 0 | K31: Suponer que es igual a crecimiento del PIB nominal
B33: Resultado operativo neto (RON) | C33: =C8-C10 -> 146.95478 | D33: =D8-D10 -> -501.9214 | E33: =E8-E10 -> -939.8297 | F33: =F8-F10 -> -786.8848 | G33: =G8-G10 -> -963.6784 | H33: =H8-H10 -> -1848.9848 | I33: =I8-I10 -> -3318.9393
B34: Adquisición neta de activos no financieros | C34: =C35-C36 -> 43.4514 | D34: =D35-D36 -> 60.1196 | E34: =E35-E36 -> 44.3857 | F34: =F35-F36 -> 46.0558 | G34: =G35-G36 -> 27.5011 | H34: =H35-H36 -> 30.852499 | I34: =I35-I36 -> 32.729354
B35: Adquisición de activos financieros | C35: =Gob_EOG!F29 -> 52.4514 | D35: =Gob_EOG!G29 -> 71.1196 | E35: =Gob_EOG!H29 -> 54.3857 | F35: =Gob_EOG!I29 -> 59.0558 | G35: =Gob_EOG!J29 -> 39.5011 | H35: 44.169321 | I35: =H35*(1+$I$48/100)*(1+$I$50/100) -> 49.885507
B36: Consumo de capital fijo | C36: =C13 -> 9 | D36: =D13 -> 11 | E36: =E13 -> 10 | F36: =F13 -> 13 | G36: =G13 -> 12 | H36: =H13 -> 13.316822 | I36: =I13 -> 17.156154
B37: Financiamiento (préstamo neto/endeudamiento neto) | C37: =-C33+C34 -> -103.50338 | D37: =-D33+D34 -> 562.041 | E37: =-E33+E34 -> 984.2154 | F37: =-F33+F34 -> 832.9406 | G37: =-G33+G34 -> 991.1795 | H37: =-H33+H34 -> 1879.8373 | I37: =-I33+I34 -> 3351.6687 | K37: =Saldo global, con signo opuesto
B38: Endeudamiento externo (neto) | C38: =+Gob_EOG!F47-Gob_EOG!F42 -> -54.943765 | D38: =+Gob_EOG!G47-Gob_EOG!G42 -> 34.064671 | E38: =+Gob_EOG!H47-Gob_EOG!H42 -> 217.73374 | F38: =+Gob_EOG!I47-Gob_EOG!I42 -> -124.47652 | G38: =+Gob_EOG!J47-Gob_EOG!J42 -> 278.94919 | H38: =+Gob_EOG!K47-Gob_EOG!K42 -> 284.94919 | I38: =+Gob_EOG!L47-Gob_EOG!L42 -> 300 | K38: Supuesto
B39: Endeudamiento interno (neto) | C39: =Gob_EOG!F44-Gob_EOG!F37 -> -39.559615 | D39: =Gob_EOG!G44-Gob_EOG!G37 -> 538.97633 | E39: =Gob_EOG!H44-Gob_EOG!H37 -> 776.48166 | F39: =Gob_EOG!I44-Gob_EOG!I37 -> 970.41712 | G39: =Gob_EOG!J44-Gob_EOG!J37 -> 724.23031 | H39: =Gob_EOG!K44-Gob_EOG!K37 -> 1594.8881 | I39: =I37-I38 -> 3051.6687 | K39: Residuo
B40: Supuesto inicial para endeudamiento interno | I40: 3051.6687 | K40: =H39*(1+I45/100)*(1+I46/100) -> 1788.425
B41: Verificación | I41: =I39-I40 -> -4.0927262e-12
B43: Partidas informativas:
B44: PIB nominal | C44: =PIB_Nominal!F6 -> 14737.186 | D44: =PIB_Nominal!G6 -> 15747.009 | E44: =PIB_Nominal!H6 -> 17629.078 | F44: =PIB_Nominal!I6 -> 19427.849 | G44: =PIB_Nominal!J6 -> 21157.293 | H44: =PIB_Nominal!K6 -> 23646.186 | I44: =PIB_Nominal!L6 -> 26705.763 | K44: Supuesto inicial
B45: Crecimiento del PIB real | C45: =PIB_real!F23 -> 2.4011889 | D45: =PIB_real!G23 -> -1.6305202 | E45: =PIB_real!H23 -> 4.8594958 | F45: =PIB_real!I23 -> 5.6553885 | G45: =PIB_real!J23 -> 4.185179 | H45: =PIB_real!K23 -> 4.557993 | I45: ='PIB real y brecha del producto'!G28 -> 4.4517021 | K45: Supuesto inicial
B46: Inflación según IPC | C46: 13.424651 | D46: 7.8427557 | E46: 5.6626532 | F46: 4.8781492 | G46: 4.6130302 | H46: 6.1358513 | I46: =Inflación!O31 -> 7.3556692 | K46: Variable endógena (ver pestaña Inflación)
B47: Tipo de cambio nominal (promedio del período) | C47: =BP!F58 -> 526.23551 | D47: =BP!G58 -> 573.28796 | E47: =BP!H58 -> 525.8292 | F47: =BP!I58 -> 506.4 | G47: =BP!J58 -> 510.78961 | H47: =BP!K58 -> 530.21903 | I47: =BP!L58 -> 563.14785 | K47: Variable endógena (ver pestaña TC nominal)
B48: Deflactor de la inversión | I48: ='Cuadro PIB'!I15 -> 7.5348309 | K48: Variable endógena
B49: Estímulo fiscal (tasa de crecimiento real de consumo del gobierno) | I49: ='Cuadro PIB'!J13 -> 20.003622 | K49: Supuesto exógeno
B50: Crecimiento real de inversión del gobierno | I50: ='Cuadro PIB'!J17 -> 5.0278602 | K50: Variable endógena (ver pestaña Inversión privada real)

Sheet MON_PSD
B2: Macronia: Panorama de las sociedades de depósito (PSD), 2006-14
D3: 2006 | E3: 2007 | F3: 2008 | G3: 2009 | H3: 2010 | I3: 2011 | J3: 2012 | K3: 2013 | L3: 2014
C4: (en miles de millones de moneda nacional)
C5: Panorama de las sociedades de depósito (PSD) | N5: Metodología de pronósticos
C6: ACTIVOS | N6: Recordar que Activos=Pasivos
C7: Activos externos netos | D7: 1670.2627 | E7: 1805.5142 | F7: 1758.4891 | G7: 2256.0146 | H7: 2275.4206 | I7: 1866.1114 | J7: 2473.1559 | K7: 2552.4002 | L7: ='AEN y OPN totales'!C15 -> 2418.4629 | N7: Paso 3: De «AEN y OPN totales»
C8: Activos internos netos | D8: 4551.8195 | E8: 5689.9985 | F8: 7041.3603 | G8: 7250.7497 | H8: 7306.9232 | I8: 8417.6637 | J8: 8746.4429 | K8: 9677.0342 | L8: =L17-L7 -> 10813.506 | N8: Paso 4: Activos - AEN
C9: Crédito interno neto | D9: 5063.3135 | E9: 6526.5447 | F9: 8511.0614 | G9: 9198.6046 | H9: 9664.3277 | I9: 11014.811 | J9: 12108.949 | K9: 13420.484 | L9: =L8-L14 -> 14678.292 | N9: Paso 6: = Activos internos netos - Otras partidas, netas
C10: Derechos netos frente al sector público | D10: 583.81606 | E10: 365.09424 | F10: 401.44403 | G10: 659.25601 | H10: 702.88562 | I10: 942.78868 | J10: 1227.0291 | K10: 1794.3894 | L10: =L11+L12 -> 2709.89 | N10: Paso 8: = Derechos frente al gob. general + Resto del sector público
C11: Frente a gobiernos generales | D11: 524.20198 | E11: 307.76353 | F11: 335.90162 | G11: 594.5108 | H11: 617.74123 | I11: 844.47411 | J11: 1069.1432 | K11: 1636.5035 | L11: =K11+(Gob_EOG!L45-Gob_EOG!L38) -> 2552.0041 | N11: Paso 7: = stock 2013 + endeudamiento de 2014 con el banco central y bancos comerciales Gob_EOG
C12: Frente a resto del sector público | D12: 59.614079 | E12: 57.330705 | F12: 65.542414 | G12: 64.745213 | H12: 85.144382 | I12: 98.314573 | J12: 157.8859 | K12: 157.8859 | L12: =K12 -> 157.8859 | N12: Suponer que no hay variaciones
C13: Derechos frente al resto del sector privado | D13: 4479.4974 | E13: 6161.4504 | F13: 8109.6174 | G13: 8539.3486 | H13: 8961.442 | I13: 10072.023 | J13: 10881.919 | K13: 11626.094 | L13: =L9-L10 -> 11968.402 | N13: Paso 9: Residuo
C14: Otras partidas (netas) | D14: -511.49398 | E14: -836.54619 | F14: -1469.7011 | G14: -1947.8549 | H14: -2357.4045 | I14: -2597.1476 | J14: -3362.5057 | K14: -3743.4495 | L14: ='AEN y OPN totales'!C33 -> -3864.7861 | N14: Paso 5: De «AEN y OPN totales»
C16: PASIVOS
C17: Dinero en sentido amplio (M3) | D17: 6222.0822 | E17: 7495.5127 | F17: 8799.8494 | G17: 9506.7644 | H17: 9582.3438 | I17: 10283.775 | J17: 11219.599 | K17: 12229.434 | L17: ='Velocidad y demanda de dinero '!L7 -> 13231.969 | N17: Paso 1: Escribir pronóstico para dinero en sentido amplio al fin del período usando la hoja «Velocidad y demanda de dinero»
C18: Dinero en circulación | D18: =D35 -> 413.18299 | E18: =E35 -> 546.2615 | F18: =F35 -> 575.00268 | G18: =G35 -> 612.99452 | H18: =H35 -> 665.04553 | I18: =I35 -> 743.08617 | J18: 844.77397 | K18: 887.01266 | L18: =(K18/K17)*L17 -> 959.72746 | N18: Paso 2a: Pronosticar suponiendo que relación con respecto a dinero en sentido amplio en 2012 prevalece en 2013
C19: Depósitos | D19: 4979.7274 | E19: 5861.421 | F19: 7255.4944 | G19: 8111.1079 | H19: 8095.9241 | I19: 8469.8645 | J19: 9050.928 | K19: 8673.474 | L19: =K19/K17*L17 -> 9384.5009 | N19: Paso 2b: Pronosticar suponiendo que relación con respecto a dinero en sentido amplio en 2012 prevalece en 2013
C20: Bonos del banco central en poder el público | D20: =D17-D18-D19 -> 829.17174 | E20: =E17-E18-E19 -> 1087.8302 | F20: =F17-F18-F19 -> 969.35232 | G20: =G17-G18-G19 -> 782.66202 | H20: =H17-H18-H19 -> 821.3742 | I20: =I17-I18-I19 -> 1070.8245 | J20: 1323.8967 | K20: 2668.9477 | L20: =L17-L18-L19 -> 2887.7405 | N20: Paso 2c: M3 - Dinero en circulación - Depósitos
C21: Banco central | N21: Metodología de pronósticos (terminar primero el anterior Panorama de sociedades de depósito)
C22: ACTIVOS | N22: ACTIVOS = PASIVOS
C23: Activos externos netos | D23: 1601.0088 | E23: 2118.4969 | F23: 2178.2399 | G23: 2275.9229 | H23: 2362.5252 | I23: 2445.9606 | J23: 3491.2701 | K23: 3969.9202 | L23: ='AEN y OPN para BC'!E14 -> 4027.2496 | N23: Paso 2: De «AEN y OPN para BC»
C24: Activos internos netos | D24: =D34-D23 -> -416.41042 | E24: =E34-E23 -> -709.45551 | F24: =F34-F23 -> -501.79311 | G24: =G34-G23 -> -330.43093 | H24: =H34-H23 -> -330.51051 | I24: =I34-I23 -> -227.6833 | J24: =J34-J23 -> -1322.5994 | K24: =K34-K23 -> -1413.9599 | L24: =L34-L23 -> -1261.7588 | N24: Paso 3: = Activos - AEN
C25: Derechos netos frente al sector público | D25: -42.255978 | E25: -60.27778 | F25: -17.958973 | G25: -47.644284 | H25: -287.11813 | I25: -85.616364 | J25: -560.99459 | K25: -560.99459 | L25: =L26+L27 -> -560.99459 | N25: Paso 6: Suma de dos celdas siguientes
C26: Frente a gobierno general | D26: -46.854542 | E26: -63.746532 | F26: -20.761049 | G26: -49.422843 | H26: -288.13664 | I26: -86.404637 | J26: -561.55399 | K26: -561.55399 | L26: =K26 -> -561.55399 | N26: Paso 4: Suponer que no hay variaciones
C27: Frente a resto del sector público | D27: 4.5985642 | E27: 3.4687525 | F27: 2.8020759 | G27: 1.7785586 | H27: 1.0185082 | I27: 0.78827342 | J27: 0.55939672 | K27: 0.55939672 | L27: =K27 -> 0.55939672 | N27: Paso 5: Suponer que no hay variaciones
C28: Activos frente a otras sociedades de depósito | D28: =D51 -> -706.0461 | E28: =E51 -> -757.54673 | F28: =F51 -> -543.26139 | G28: =G51 -> -629.49546 | H28: =H51 -> -584.87373 | I28: =I51 -> -658.25402 | J28: =J51 -> -525.92633 | K28: =K51 -> 997.98289 | L28: =L24-L25-L29-L30-L31 -> 1563.7073 | N28: Paso 10: Residuo
C29: Derechos frente al resto del sector privado | D29: 15.456124 | E29: 14.921319 | F29: 2.5439535 | G29: 2.1115481 | H29: 1.5530317 | I29: 1.1984756 | J29: 0.84020127 | K29: 0.84020127 | L29: =K29 -> 0.84020127 | N29: Paso 7: Suponer que no hay variaciones
C30: Bonos del banco central | D30: =D24-D25-D28-D29-D31 -> -829.17174 | E30: =E24-E25-E28-E29-E31 -> -1087.8302 | F30: =F24-F25-F28-F29-F31 -> -969.35232 | G30: =G24-G25-G28-G29-G31 -> -782.66202 | H30: =H24-H25-H28-H29-H31 -> -821.3742 | I30: =I24-I25-I28-I29-I31 -> -1070.8245 | J30: =J24-J25-J28-J29-J31 -> -1323.8967 | K30: =K24-K25-K28-K29-K31 -> -2669.2624 | L30: =-L20 -> -2887.7405 | N30: Paso 8: Del PSD anterior
C31: Otras partidas netas | D31: 1145.6073 | E31: 1181.2779 | F31: 1026.2356 | G31: 1127.2593 | H31: 1361.3025 | I31: 1585.8131 | J31: 1087.3781 | K31: 817.474 | L31: ='AEN y OPN para BC'!E29 -> 622.42878 | N31: Paso 9: De «AEN y OPN para BC»
C33: PASIVOS
C34: Base monetaria | D34: 1184.5984 | E34: 1409.0414 | F34: 1676.4468 | G34: 1945.492 | H34: 2032.0146 | I34: 2218.2773 | J34: 2168.6707 | K34: 2555.9604 | L34: ='Multiplicador del dinero'!K10 -> 2765.4908 | N34: Paso 1: De «Multiplicador del dinero»
C35: Dinero en circulación | D35: 413.18299 | E35: 546.2615 | F35: 575.00268 | G35: 612.99452 | H35: 665.04553 | I35: 743.08617 | J35: 844.77397 | K35: 887.01266 | L35: =L18 -> 959.72746 | N35: Paso 11: Fijar igual que dinero en circulación (componente de dinero en sentido amplio) de la PSD anterior
C36: Pasivos frente a otras sociedades de depósito. | D36: 771.41544 | E36: 862.77994 | F36: 1101.4441 | G36: 1332.4975 | H36: 1366.9691 | I36: 1475.1911 | J36: 1323.8967 | K36: =K34-K35 -> 1668.9477 | L36: =L34-L35 -> 1805.7633 | N36: Paso 12: = Base monetaria - Dinero en circulación
C38: Otras sociedades de depósito | N38: Metodología de pronósticos (terminar primer el Panorama de sociedades de depósito y el balance del banco central)
C39: ACTIVOS | N39: ACTIVOS = PASIVOS
C40: Activos externos netos | D40: 69.253813 | E40: -312.98275 | F40: -419.75076 | G40: -19.908283 | H40: -87.104529 | I40: -579.84916 | J40: -1018.1142 | K40: -1417.2054 | L40: =L7-L23 -> -1608.7867 | N40: Paso 3: AEN del PSD - AEN del banco central
C41: Activos internos netos | D41: =D42+D43+D46+D47 -> 4204.4275 | E41: =E42+E43+E46+E47 -> 5416.857 | F41: =F42+F43+F46+F47 -> 7131.9838 | G41: =G42+G43+G46+G47 -> 7501.5207 | H41: =H42+H43+H46+H47 -> 7598.1549 | I41: =I42+I43+I46+I47 -> 8391.4596 | J41: =J42+J43+J46+J47 -> 9543.1159 | K41: =K42+K43+K46+K47 -> 11088.662 | L41: =L50+L51-L40 -> 12556.995 | N41: Paso 4: AIN = Activos - AEN
C42: Derechos frente al banco central | D42: =D36 -> 771.41544 | E42: =E36 -> 862.77994 | F42: =F36 -> 1101.4441 | G42: =G36 -> 1332.4975 | H42: =H36 -> 1366.9691 | I42: =I36 -> 1475.1911 | J42: =J36 -> 1323.8967 | K42: =K36 -> 1668.9477 | L42: =L36 -> 1805.7633 | N42: Paso 5: De pasivos del BC
C43: Derechos netos frente al sector público | D43: 626.07204 | E43: 425.37202 | F43: 419.403 | G43: 706.90029 | H43: 990.00374 | I43: 1028.405 | J43: 1788.0237 | K43: 2355.384 | L43: =L10-L25 -> 3270.8846 | N43: Paso 6: Derechos netos totales frente al sector público del PSD - Derechos netos totales frente al sector público del BC
C44: Frente a gobiernos generales | D44: 571.05652 | E44: 371.51007 | F44: 356.66266 | G44: 643.93364 | H44: 905.87787 | I44: 930.87875 | J44: 1630.6972 | K44: 2198.0575 | L44: =L43-L45 -> 3113.5581 | N44: Paso 7: = Stock en 2013 más endeudamiento nuevo de la hoja Gob_EOG
C45: Frente a resto del sector público | D45: 55.015515 | E45: 53.861952 | F45: 62.740338 | G45: 62.966654 | H45: 84.125874 | I45: 97.5263 | J45: 157.32651 | K45: 157.32651 | L45: =K45 -> 157.32651 | N45: Paso 8: Suponer que no hay variaciones
C46: Derechos frente a resto del sector privado | D46: =D13-D29 -> 4464.0413 | E46: =E13-E29 -> 6146.5291 | F46: =F13-F29 -> 8107.0734 | G46: =G13-G29 -> 8537.237 | H46: =H13-H29 -> 8959.889 | I46: =I13-I29 -> 10070.824 | J46: =J13-J29 -> 10881.079 | K46: =K13-K29 -> 11625.254 | L46: =L13-L29 -> 11967.562 | N46: Paso 9: = Derechos frente al resto del sector privado del PSD - Derechos frente al resto del sector privado del BC
C47: Otras partidas (netas) | D47: =D14-D31 -> -1657.1013 | E47: =E14-E31 -> -2017.8241 | F47: =F14-F31 -> -2495.9367 | G47: =G14-G31 -> -3075.1142 | H47: =H14-H31 -> -3718.707 | I47: =I14-I31 -> -4182.9607 | J47: =J14-J31 -> -4449.8837 | K47: =K14-K31 -> -4560.9235 | L47: =L14-L31 -> -4487.2149 | N47: Paso 10: = OPN del PSD - OPN del BC
C49: PASIVOS
C50: Depósitos | D50: 4979.7274 | E50: 5861.421 | F50: 7255.4944 | G50: 8111.1079 | H50: 8095.9241 | I50: 8469.8645 | J50: 9050.928 | K50: 8673.474 | L50: =L19 -> 9384.5009 | N50: Paso 1: Del lado del pasivo del PSD
C51: Pasivos frente la banco central | D51: =D41+D40-D50 -> -706.0461 | E51: =E41+E40-E50 -> -757.54673 | F51: =F41+F40-F50 -> -543.26139 | G51: =G41+G40-G50 -> -629.49546 | H51: =H41+H40-H50 -> -584.87373 | I51: =I41+I40-I50 -> -658.25402 | J51: =J41+J40-J50 -> -525.92633 | K51: =K41+K40-K50 -> 997.98289 | L51: =L28 -> 1563.7073 | N51: Paso 2: De los activos del BC

Sheet Velocidad y demanda de dinero 
C2: Macronia: Velocidad de circulación, 2006-2014
D3: 2006 | E3: =1+D3 -> 2007 | F3: =1+E3 -> 2008 | G3: =1+F3 -> 2009 | H3: =1+G3 -> 2010 | I3: =1+H3 -> 2011 | J3: =1+I3 -> 2012 | K3: 2013 | L3: Pronóstico: 2014 | N3: Metodología
C5: (en miles de millones de moneda nacional)
C7: Stock de dinero en sentido amplio (fin del período) | D7: =MON_PSD!D17 -> 6222.0822 | E7: =MON_PSD!E17 -> 7495.5127 | F7: =MON_PSD!F17 -> 8799.8494 | G7: =MON_PSD!G17 -> 9506.7644 | H7: =MON_PSD!H17 -> 9582.3438 | I7: =MON_PSD!I17 -> 10283.775 | J7: =MON_PSD!J17 -> 11219.599 | K7: =MON_PSD!K17 -> 12229.434 | L7: =DD!E33/1000 -> 13231.969 | N7: De la hoja DD
C9: Stock medio de dinero en sentido amplio | D9: =D7 -> 6222.0822 | E9: =AVERAGE(D7:E7) -> 6858.7974 | F9: =AVERAGE(E7:F7) -> 8147.6811 | G9: =AVERAGE(F7:G7) -> 9153.3069 | H9: =AVERAGE(G7:H7) -> 9544.5541 | I9: =AVERAGE(H7:I7) -> 9933.0595 | J9: =AVERAGE(I7:J7) -> 10751.687 | K9: =AVERAGE(J7:K7) -> 11724.517 | L9: =AVERAGE(K7:L7) -> 12730.702 | N9: Promedio
C11: PIB nominal | D11: =PIB_Nominal!D6 -> 10964.62 | E11: =PIB_Nominal!E6 -> 12956.322 | F11: =PIB_Nominal!F6 -> 14737.186 | G11: =PIB_Nominal!G6 -> 15747.009 | H11: =PIB_Nominal!H6 -> 17629.078 | I11: =PIB_Nominal!I6 -> 19427.849 | J11: =PIB_Nominal!J6 -> 21157.293 | K11: =PIB_Nominal!K6 -> 23646.186 | L11: =PIB_Nominal!L6 -> 26705.763 | N11: De PIB_nominal
C13: Velocidad de circulación del stock medio de dinero | D13: =D11/D9 -> 1.7622108 | E13: =E11/E9 -> 1.8890078 | F13: =F11/F9 -> 1.8087583 | G13: =G11/G9 -> 1.7203628 | H13: =H11/H9 -> 1.84703 | I13: =I11/I9 -> 1.9558777 | J13: =J11/J9 -> 1.9678115 | K13: =K11/K9 -> 2.0168154 | L13: =L11/L9 -> 2.0977448

Sheet DD
C3: Serie de datos para estimación de demanda de dinero
C4: ln M3R | M4: Ecuación de demanda de dinero
C5: Efectiva | D5: Ajustada | E5: M3 | F5: IPC | G5: RY | H5: IBR | I5: ln RY | J5: ln IBR
B6: 1987 | C6: 9.7509979 | E6: 138167 | F6: 8.0463651 | G6: 4154.2 | H6: 22 | I6: =LN(G6) -> 8.3318751 | J6: =LN(H6) -> 3.0910425 | L6: ln(M3R) = b0 + b1*ln(RY)+b2*ln(IBR)
B7: 1988 | C7: 9.82923 | D7: =$M$8+I7*$M$9+J7*$M$10 -> 9.8086848 | E7: 180337 | F7: 9.7119064 | G7: 4296.8 | H7: 23.5 | I7: =LN(G7) -> 8.3656258 | J7: =LN(H7) -> 3.1570004
B8: 1989 | C8: 9.863881 | D8: =$M$8+I8*$M$9+J8*$M$10 -> 9.8675481 | E8: 217631 | F8: 11.321179 | G8: 4540.2 | H8: 23.5 | I8: =LN(G8) -> 8.4207263 | J8: =LN(H8) -> 3.1570004 | L8: b0 | M8: 1.4898167
B9: 1990 | C9: 9.9912325 | D9: =$M$8+I9*$M$9+J9*$M$10 -> 9.8330327 | E9: 294366 | F9: 13.481882 | G9: 4703.7 | H9: 34 | I9: =LN(G9) -> 8.4561047 | J9: =LN(H9) -> 3.5263605 | L9: b1 | M9: 1.0682901
B10: 1991 | C10: 10.034016 | D10: =$M$8+I10*$M$9+J10*$M$10 -> 9.878196 | E10: 395454 | F10: 17.35314 | G10: 4810.1 | H10: 30.5 | I10: =LN(G10) -> 8.4784732 | J10: =LN(H10) -> 3.4177267 | L10: b2 | M10: -0.19577031
B11: 1992 | C11: 10.04929 | D11: =$M$8+I11*$M$9+J11*$M$10 -> 10.064419 | E11: 488775 | F11: 21.123115 | G11: 5250.4 | H11: 19 | I11: =LN(G11) -> 8.5660595 | J11: =LN(H11) -> 2.944439
B12: 1993 | C12: 10.108772 | D12: =$M$8+I12*$M$9+J12*$M$10 -> 10.087085 | E12: 569581 | F12: 23.193788 | G12: 5639.6 | H12: 25 | I12: =LN(G12) -> 8.6375684 | J12: =LN(H12) -> 3.2188758
B13: 1994 | C13: 10.180302 | D13: =$M$8+I13*$M$9+J13*$M$10 -> 10.116016 | E13: 694638 | F13: 26.333558 | G13: 5906.3 | H13: 27.75 | I13: =LN(G13) -> 8.6837749 | J13: =LN(H13) -> 3.3232358
B14: 1995 | C14: 10.039142 | D14: =$M$8+I14*$M$9+J14*$M$10 -> 10.151885 | E14: 743160 | F14: 32.444294 | G14: 6137.9 | H14: 28.5 | I14: =LN(G14) -> 8.7222379 | J14: =LN(H14) -> 3.3499041
B15: 1996 | C15: 10.134964 | D15: =$M$8+I15*$M$9+J15*$M$10 -> 10.190121 | E15: 961161 | F15: 38.127391 | G15: 6192.3 | H15: 24.6 | I15: =LN(G15) -> 8.7310619 | J15: =LN(H15) -> 3.2027464
B16: 1997 | C16: 10.152119 | D16: =$M$8+I16*$M$9+J16*$M$10 -> 10.303912 | E16: 1107087 | F16: 43.16903 | G16: 6537.8 | H16: 18.5 | I16: =LN(G16) -> 8.785356 | J16: =LN(H16) -> 2.9177707
B17: 1998 | C17: 10.26668 | D17: =$M$8+I17*$M$9+J17*$M$10 -> 10.33506 | E17: 1386454 | F17: 48.210668 | G17: 7086.8 | H17: 24.5 | I17: =LN(G17) -> 8.8659892 | J17: =LN(H17) -> 3.1986731
B18: 1999 | C18: 10.340206 | D18: =$M$8+I18*$M$9+J18*$M$10 -> 10.477129 | E18: 1642017 | F18: 53.049741 | G18: 7669.5 | H18: 18.25 | I18: =LN(G18) -> 8.9450067 | J18: =LN(H18) -> 2.9041651
B19: 2000 | C19: 10.416544 | D19: =$M$8+I19*$M$9+J19*$M$10 -> 10.528155 | E19: 1966269 | F19: 58.856628 | G19: 7807.5 | H19: 15.5 | I19: =LN(G19) -> 8.9628401 | J19: =LN(H19) -> 2.74084
B20: 2001 | C20: 10.416822 | D20: =$M$8+I20*$M$9+J20*$M$10 -> 10.533371 | E20: 2188318 | F20: 65.485033 | G20: 7891.5 | H20: 16 | I20: =LN(G20) -> 8.9735415 | J20: =LN(H20) -> 2.7725887
B21: 2002 | C21: 10.521641 | D21: =$M$8+I21*$M$9+J21*$M$10 -> 10.5464 | E21: 2652742 | F21: 71.483232 | G21: 8120.6 | H21: 17.5 | I21: =LN(G21) -> 9.0021593 | J21: =LN(H21) -> 2.8622009
B22: 2003 | C22: 10.5965 | D22: =$M$8+I22*$M$9+J22*$M$10 -> 10.659919 | E22: 3128995 | F22: 78.235427 | G22: 8640.6 | H22: 13.75 | I22: =LN(G22) -> 9.0642273 | J22: =LN(H22) -> 2.6210388
... B30: 2011 | C30: 11.038685 | D30: =$M$8+I30*$M$9+J30*$M$10 -> 11.092227 | E30: 10283775 | F30: 165.23903 | G30: 11727 | H30: 8 | I30: =LN(G30) -> 9.3696492 | J30: =LN(H30) -> 2.0794415
B31: 2012 | C31: 11.076989 | D31: =$M$8+I31*$M$9+J31*$M$10 -> 11.095036 | E31: =11219598.7245475 -> 11219599 | F31: 173.50098 | G31: 12074.9 | H31: 9.25 | I31: =LN(G31) -> 9.3988842 | J31: =LN(H31) -> 2.2246236
B32: 2013 | C32: 11.103623 | D32: =$M$8+I32*$M$9+J32*$M$10 -> 11.101024 | E32: 12229434 | F32: 184.14674 | G32: =PIB_real!K6 -> 12774.631 | H32: 12.2 | I32: =LN(G32) -> 9.4552165 | J32: =LN(H32) -> 2.501436
B33: 2014 | C33: =D33 -> 11.111436 | D33: =$M$8+I33*$M$9+J33*$M$10 -> 11.111436 | E33: =EXP(D33)*F33 -> 13231969 | F33: =F32*(1+Inflación!O31/100) -> 197.69197 | G33: =PIB_real!L6 -> 13343.319 | H33: ='Regla de Taylor '!F32 -> 14.671691 | I33: =LN(G33) -> 9.4987711 | J33: =LN(H33) -> 2.6859198
B35: Notación:
B36: RY | C36: PIB real
B37: ln RY | C37: Logaritmo natural del PIB real
B38: M3R | C38: M3 real = M3/IPC
B39: IPC | C39: Índice de precios al consumidor
B40: IBR | C40: Tasa interbancaria (promedio, en %)

Sheet Regla de Taylor 
C2: Serie de datos para la regla de Taylor
D4: Tasa de política monetaria | F4: Inflación según IPC | G4: Inflación según IPC | H4: Inflación según IPC | I4: Brecha de inflación | J4: Tasa de PM rezagada | K4: Tasa de interés real neutral | L4: Tasa interbancaria | M4: PIB real | N4: PIB real potencial | O4: Brecha del producto
D5: Efectiva | E5: Ajustada | F5: Interanual efectiva (%) | G5: Meta (%) | H5: Expectativas interanuales (%) | I5: % | K5: Interanual (%) | L5: Efectiva | M5: Año base=2005 | N5: Año base=2005 | O5: %
C6: 2011 | D6: 5 | E6: =+$C$24*J6+(1-$C$24)*(K6+H6+$C$22*(H6-G6)+$C$23*O6) -> 8.1846799 | F6: 4.8781492 | G6: 5 | H6: 6.5 | I6: =F6-G6 -> -0.12185081 | J6: 10.4 | K6: 2 | L6: 8 | M6: ='PIB real y brecha del producto'!C11 -> 11726.953 | N6: ='PIB real y brecha del producto'!F11 -> 11888.175 | O6: ='PIB real y brecha del producto'!G11 -> -1.3561522
C7: 2012 | D7: 7 | E7: =+$C$24*J7+(1-$C$24)*(K7+H7+$C$22*(H7-G7)+$C$23*O7) -> 6.6 | F7: 5 | G7: 5 | H7: 5 | I7: =F7-G7 -> 0 | J7: =D6 -> 5 | K7: 2 | L7: 9.25 | M7: ='PIB real y brecha del producto'!C12 -> 12184.444 | N7: ='PIB real y brecha del producto'!F12 -> 12184.444 | O7: ='PIB real y brecha del producto'!G12 -> 5.971514e-14
C8: 2013 | D8: 8.8660415 | E8: =+$C$24*J8+(1-$C$24)*(K8+H8+$C$22*(H8-G8)+$C$23*O8) -> 8.4928332 | F8: 6.1358513 | G8: 5 | H8: 5 | I8: =F8-G8 -> 1.1358513 | J8: =D7 -> 7 | K8: 2 | L8: 12.2 | M8: ='PIB real y brecha del producto'!C13 -> 12774.631 | N8: ='PIB real y brecha del producto'!F13 -> 12671.821 | O8: ='PIB real y brecha del producto'!G13 -> 0.81132237
C9: 2014 | D9: =E9 -> 9.6716905 | E9: =$C$24*D8+(1-$C$24)*(K9+H9+$C$22*(H9-G9)+$C$23*O9) -> 9.6716905 | F9: =Inflación!O31 -> 7.3556692 | G9: 5 | H9: 5 | I9: =F9-G9 -> 2.3556692 | J9: =D8 -> 8.8660415 | K9: 2 | L9: =F32 -> 14.671691 | M9: ='PIB real y brecha del producto'!G30 -> 13343.319 | N9: ='PIB real y brecha del producto'!F14 -> 13178.694 | O9: ='PIB real y brecha del producto'!G32 -> 1.2491751
B14: Regla de Taylor:
B21: Coeficientes
B22: Alfa | C22: 1.5
B23: Beta | C23: 2.3
B24: Ro | C24: 0.2
B28: Macronia: Pronóstico de tasa de interés interbancaria para 2014
B30: Pronóstico de la tasa de política monetaria, promedio | F30: =E9 -> 9.6716905
B31: Diferencial, promedio | F31: 5
B32: Pronóstico de tasa de interés interbancaria, promedio | F32: =(F30+F31) -> 14.671691 | G32: Suma de pronóstico y diferencial

Sheet AEN y OPN totales
B3: Macronia: Pronóstico de activos externos netos (AEN) totales
B4: en el panorama de las sociedades de depósito | C4: 2014
D5: Metodología
B6: AEN al final de 2013 (en miles de millones de moneda nacional) | C6: =MON_PSD!K7 -> 2552.4002 | D6: Del Panorama de sociedades de depósito (ver la hoja «MON_PSD»)
B7: Tipo de cambio al final de 2013 (en moneda nacional por dólar de EE.UU.) | C7: ='TC nominal'!H14 -> 549.41884 | D7: De la hoja «TC nominal»
B8: AEN al final de 2013 (en millones de dólares de EE.UU.) | C8: =C6/C7*1000 -> 4645.6364 | D8: = AEN (miles de millones de moneda nacional) / Tipo de cambio al fin del período, convertido a millones
B10: Saldo global de la BP en 2014 (en millones de dólares de EE.UU.) | C10: =BP!L41 -> -244.54656 | D10: De la hoja «BP»
B11: Endeudamiento de banco comerciales (menos) | C11: =-BP!L36 -> -208.75157 | D11: = Incurrimiento neto de pasivos de otras sociedades de depósito (menos). De la hoja «BP»
B13: AEN al final de 2014 (en millones de dólares de EE.UU.) | C13: =C8+C10+C11 -> 4192.3383 | D13: = AEN al final de 2013 + saldo global de la BP en 2014 + Endeudamiento de banco comerciales
B14: Tipo de cambio al final de 2014 (en moneda nacional por dólar de EE.UU.) | C14: ='TC nominal'!I14 -> 576.87685 | D14: De la hoja «TC nominal»
B15: AEN al final de 2014 (en miles de millones de moneda nacional) | C15: =C13/1000*C14 -> 2418.4629 | D15: Volver a convertir de millones de $ a miles de millones de moneda nacional
B20: Macronia: Pronóstico de otras partidas netas (OPN)
B21: en el panorama de las sociedades de depósito
D23: Metodología
B25: Otras partidas netas, al final de 2013 (en miles de millones de moneda nacional) | C25: =MON_PSD!K14 -> -3743.4495 | D25: Del panorama de sociedades de depósito de 2013 (ver la hoja «MON_PSD»)
B27: Ajuste por valoración | C27: =C28-C29-C30-C31 -> 121.33662
B28: AEN al final de 2014 | C28: =C15 -> 2418.4629 | D28: Ver cuadro anterior
B29: Menos: AEN al comienzo de 2014 (es decir, final de 2013) | C29: =MON_PSD!K7 -> 2552.4002 | D29: Del panorama de sociedades de depósito (ver la hoja «MON_PSD»)
B30: Menos: Variación de AEN durante 2014 por saldo global de la BP | C30: =(BP!L41)*'TC nominal'!I13/1000 -> -137.71587 | D30: = Saldo global de la BP evaluado según tipo de cambio medio de 2014. De las hojas «BP» y «TC nominal»
B31: Menos: Variación de AEN durante 2014 por endeudamiento de banco comerciales (menos) | C31: =(-BP!L36)*'TC nominal'!I13/1000 -> -117.558 | D31: = Incurrimiento neto de pasivos de otras sociedades de depósito (menos). De la hoja «BP». Convertido a moneda nacional usando el tipo de cambio medio del período
B33: Otras partidas netas, al final de 2014 | C33: =C25-C27 -> -3864.7861 | D33: Otras partidas netas, al final de 2013 - ajusto por valoración
Z39: 12.37a.

Sheet Multiplicador del dinero
B3: Macronia: Multiplicador del dinero, 2006-2014
K5: Pronóstico
C6: 2006 | D6: =1+C6 -> 2007 | E6: =1+D6 -> 2008 | F6: =1+E6 -> 2009 | G6: =1+F6 -> 2010 | H6: =1+G6 -> 2011 | I6: =1+H6 -> 2012 | J6: =1+I6 -> 2013 | K6: =1+J6 -> 2014 | L6: Metodología
E8: (en miles de millones de moneda nacional, fin del período)
B10: Dinero de reserva (en miles de millones de moneda nacional) | C10: =MON_PSD!D34 -> 1184.5984 | D10: =MON_PSD!E34 -> 1409.0414 | E10: =MON_PSD!F34 -> 1676.4468 | F10: =MON_PSD!G34 -> 1945.492 | G10: =MON_PSD!H34 -> 2032.0146 | H10: =MON_PSD!I34 -> 2218.2773 | I10: =MON_PSD!J34 -> 2168.6707 | J10: =MON_PSD!K34 -> 2555.9604 | K10: =K12/K14 -> 2765.4908 | L10: RM = M2 / mm
B12: Dinero de reserva (en miles de millones de moneda nacional) | C12: =MON_PSD!D17 -> 6222.0822 | D12: =MON_PSD!E17 -> 7495.5127 | E12: =MON_PSD!F17 -> 8799.8494 | F12: =MON_PSD!G17 -> 9506.7644 | G12: =MON_PSD!H17 -> 9582.3438 | H12: =MON_PSD!I17 -> 10283.775 | I12: =MON_PSD!J17 -> 11219.599 | J12: =MON_PSD!K17 -> 12229.434 | K12: =MON_PSD!L17 -> 13231.969 | L12: De MON_PSD
B14: Multiplicador del dinero | C14: =C12/C10 -> 5.2524822 | D14: =D12/D10 -> 5.3195829 | E14: =E12/E10 -> 5.2491075 | F14: =F12/F10 -> 4.8865605 | G14: =G12/G10 -> 4.7156864 | H14: =H12/H10 -> 4.6359286 | I14: =I12/I10 -> 5.1734912 | J14: =J12/J10 -> 4.7846729 | K14: =L14 -> 4.7846729 | L14: =J14 -> 4.7846729 | M14: Método 1: Usar multiplicador de 2013
L15: =AVERAGE(C14:J14) -> 5.002189 | M15: Método 2: Promedio de 2006-13
L16: =TREND(C14:J14,C6:J6,K6) -> 4.6799283 | M16: Método 3: Tendencia
AD37: 12.37a.

Sheet AEN y OPN para BC
B3: Macronia: Pronóstico de activos externos netos del banco central
E4: 2014
F5: Metodología
B6: AEN al final del ejercicio previo (en miles de millones de moneda nacional) | E6: =MON_PSD!K23 -> 3969.9202 | F6: De la hoja MON_PSD
B7: Tipo de cambio al final del ejercicio previo (en moneda nacional por dólar de EE.UU.) | E7: ='TC nominal'!H14 -> 549.41884 | F7: De la hoja «TC nominal»
B8: AEN al final del ejercicio previo (en millones de dólares de EE.UU.) | E8: =E6/E7*1000 -> 7225.6718 | F8: AEN en moneda nacional/Tipo de cambio convertido a millones
B10: Saldo global de la BP en el ejercicio corriente (en millones de dólares de EE.UU.) | E10: =BP!L41 -> -244.54656 | F10: De la hoja «BP»
B12: AEN al final del ejercicio previo (en millones de dólares de EE.UU.) | E12: =E8+E10 -> 6981.1253 | F12: Valor al final de 2013 + variación en 2014 (de BP)
B13: Tipo de cambio al final del ejercicio corriente (en moneda nacional por dólar de EE.UU.) | E13: ='TC nominal'!I14 -> 576.87685 | F13: De la hoja «TC nominal»
B14: AEN al final del ejercicio corriente (en miles de millones de moneda nacional) | E14: =E12*E13/1000 -> 4027.2496 | F14: AEN en $ * tipo de cambio convertido una vez más a miles de millones
B17: Macronia: Pronóstico de otras partidas netas, en el banco central
B22: Otras partidas netas, al final de 2013 | E22: =MON_PSD!K31 -> 817.474 | F22: Del panorama de sociedades de depósito de 2013 (ver la hoja «MON_PSD»)
B24: Ajuste por valoración | E24: =E25-E26-E27 -> 195.04522
B25: AEN al final de 2014 (en miles de millones de moneda nacional) | E25: =E14 -> 4027.2496 | F25: Del cuadro anterior
B26: Menos: AEN al comienzo de 2014 (es decir, final de 2013) (en miles de millones de moneda nacional) | E26: =MON_PSD!K23 -> 3969.9202 | F26: De la hoja MON_PSD
B27: Menos: Variación de AEN durante 2014 (superávit en BP) | E27: ='AEN y OPN totales'!C30 -> -137.71587 | F27: Del cuadro AEN y OPN totales
B29: Otras partidas netas, al final de 2013 | E29: =E22-E24 -> 622.42878

Sheet MON_IND
B2: Macronia: Indicadores de cuentas monetarias, 2006-13
D3: 2006 | E3: 2007 | F3: 2008 | G3: 2009 | H3: 2010 | I3: 2011 | J3: 2012 | K3: 2013 | L3: 2014
B4: (en porcentaje)
C5: Agregados de crecimiento del dinero
C6: Activos externos netos (sociedades financieras) | D6: … | E6: =E34/D34*100-100 -> 8.097621 | F6: =F34/E34*100-100 -> -2.6045243 | G6: =G34/F34*100-100 -> 28.292782 | H6: =H34/G34*100-100 -> 0.86018844 | I6: =I34/H34*100-100 -> -17.988287 | J6: =J34/I34*100-100 -> 32.529913 | K6: =K34/J34*100-100 -> 3.2041775 | L6: =L34/K34*100-100 -> -5.2475021
C7: Crédito interno neto (sociedades financieras) | D7: … | E7: =E35/D35*100-100 -> 28.898688 | F7: =F35/E35*100-100 -> 30.406851 | G7: =G35/F35*100-100 -> 8.078231 | H7: =H35/G35*100-100 -> 5.062975 | I7: =I35/H35*100-100 -> 13.973902 | J7: =J35/I35*100-100 -> 9.9333267 | K7: =K35/J35*100-100 -> 10.831123 | L7: =L35/K35*100-100 -> 9.3723032
C8: Del cual: derechos netos frente al sector público | D8: … | E8: =E36/D36*100-100 -> -37.464167 | F8: =F36/E36*100-100 -> 9.956276 | G8: =G36/F36*100-100 -> 64.221152 | H8: =H36/G36*100-100 -> 6.6180068 | I8: =I36/H36*100-100 -> 34.131167 | J8: =J36/I36*100-100 -> 30.148901 | K8: =K36/J36*100-100 -> 46.23854 | L8: =L36/K36*100-100 -> 51.020173
C9: Del cual: derechos netos frente al resto del sector privado | D9: … | E9: =E37/D37*100-100 -> 37.547806 | F9: =F37/E37*100-100 -> 31.618642 | G9: =G37/F37*100-100 -> 5.299032 | H9: =H37/G37*100-100 -> 4.9429232 | I9: =I37/H37*100-100 -> 12.392878 | J9: =J37/I37*100-100 -> 8.0410539 | K9: =K37/J37*100-100 -> 6.8386355 | L9: =L37/K37*100-100 -> 2.9443063
C10: Otras partidas (sociedades financieras) | D10: … | E10: =E38/D38*100-100 -> 63.549566 | F10: =F38/E38*100-100 -> 75.686784 | G10: =G38/F38*100-100 -> 32.534081 | H10: =H38/G38*100-100 -> 21.025675 | I10: =I38/H38*100-100 -> 10.16979 | J10: =J38/I38*100-100 -> 29.469179 | K10: =K38/J38*100-100 -> 11.329165 | L10: =L38/K38*100-100 -> 3.2413051
C11: Dinero en sentido amplio | D11: … | E11: =E39/D39*100-100 -> 20.466308 | F11: =F39/E39*100-100 -> 17.401568 | G11: =G39/F39*100-100 -> 8.0332619 | H11: =H39/G39*100-100 -> 0.79500651 | I11: =I39/H39*100-100 -> 7.3200399 | J11: =J39/I39*100-100 -> 9.1 | K11: =K39/J39*100-100 -> 9.0006394 | L11: =L39/K39*100-100 -> 8.1977181
C12: Dinero en circulación | D12: … | E12: =E40/D40*100-100 -> 32.208129 | F12: =F40/E40*100-100 -> 5.2614331 | G12: =G40/F40*100-100 -> 6.6072456 | H12: =H40/G40*100-100 -> 8.4912683 | I12: =I40/H40*100-100 -> 11.734631 | J12: =J40/I40*100-100 -> 13.684522 | K12: =K40/J40*100-100 -> 5 | L12: =L40/K40*100-100 -> 8.1977181
C13: Depósitos | D13: … | E13: =E41/D41*100-100 -> 17.705659 | F13: =F41/E41*100-100 -> 23.783882 | G13: =G41/F41*100-100 -> 11.792627 | H13: =H41/G41*100-100 -> -0.18719751 | I13: =I41/H41*100-100 -> 4.6188729 | J13: =J41/I41*100-100 -> 6.8603639 | K13: =K41/J41*100-100 -> -4.1703354 | L13: =L41/K41*100-100 -> 8.1977181
C14: Otros pasivos del BC | D14: … | E14: =E42/D42*100-100 -> 31.194799 | F14: =F42/E42*100-100 -> -10.89121 | G14: =G42/F42*100-100 -> -19.259282 | H14: =H42/G42*100-100 -> 4.946219 | I14: =I42/H42*100-100 -> 30.369874 | J14: =J42/I42*100-100 -> 23.633398 | K14: =K42/J42*100-100 -> 101.59788 | L14: =L42/K42*100-100 -> 8.1977181
C16: Contribución al crecimiento del dinero en sentido amplio
C17: Activos externos netos (sociedades financieras) | D17: … | E17: =(E34-D34)/D$39*100 -> 2.1737344 | F17: =(F34-E34)/E$39*100 -> -0.62737612 | G17: =(G34-F34)/F$39*100 -> 5.6537957 | H17: =(H34-G34)/G$39*100 -> 0.2041281 | I17: =(I34-H34)/H$39*100 -> -4.2714935 | J17: =(J34-I34)/I$39*100 -> 5.9029336 | K17: =(K34-J34)/J$39*100 -> 0.70630247 | L17: =(L34-K34)/K$39*100 -> -1.095204
C18: Crédito interno neto (sociedades financieras) | D18: … | E18: =(E35-D35)/D$39*100 -> 23.516745 | F18: =(F35-E35)/E$39*100 -> 26.476064 | G18: =(G35-F35)/F$39*100 -> 7.8131246 | H18: =(H35-G35)/G$39*100 -> 4.8988597 | I18: =(I35-H35)/H$39*100 -> 14.093459 | J18: =(J35-I35)/I$39*100 -> 10.639451 | K18: =(K35-J35)/J$39*100 -> 11.68968 | L18: =(L35-K35)/K$39*100 -> 10.285091
C19: Del cual: derechos netos frente al sector público | D19: … | E19: =(E36-D36)/D$39*100 -> -3.5152513 | F19: =(F36-E36)/E$39*100 -> 0.48495402 | G19: =(G36-F36)/F$39*100 -> 2.9297317 | H19: =(H36-G36)/G$39*100 -> 0.45893224 | I19: =(I36-H36)/H$39*100 -> 2.5035948 | J19: =(J36-I36)/I$39*100 -> 2.7639696 | K19: =(K36-J36)/J$39*100 -> 5.0568684 | L19: =(L36-K36)/K$39*100 -> 7.4860421
C20: Del cual: derechos netos frente al resto del sector privado | D20: … | E20: =(E37-D37)/D$39*100 -> 27.031996 | F20: =(F37-E37)/E$39*100 -> 25.99111 | G20: =(G37-F37)/F$39*100 -> 4.8833928 | H20: =(H37-G37)/G$39*100 -> 4.4399275 | I20: =(I37-H37)/H$39*100 -> 11.589864 | J20: =(J37-I37)/I$39*100 -> 7.8754811 | K20: =(K37-J37)/J$39*100 -> 6.6328112 | L20: =(L37-K37)/K$39*100 -> 2.7990487
